Workbook
Name ListeComptes: 'Paramètres'!$D$10:$D$49
Name ListeTypes: 'Paramètres'!$M$10:$M$129
Name ListeMoisPaie: 'Référentiel'!$B$2:$B$121
Name ListeNatures: 'Référentiel'!$M$2:$M$26
Name ListeMois: 'Référentiel'!$A$2:$A$61
Name FinReleve: 'Paramètres'!$B$12
Name CompteSorties: 'Paramètres'!$B$13

Sheet Lisez-moi
A1: Budget — modèle de fichier source
A3: Ce classeur est un EXEMPLE complet, rempli avec des données inventées. Remplacez-les par les vôtres.
A5: À remplir : les cellules jaune pâle, sous les en-têtes bleu nuit.
A6: Calculé : les cellules grises, sous les en-têtes gris. N'écrivez rien dedans.
A8: Par où commencer
A9: 1. Paramètres : vos comptes, vos types, vos catégories, vos dates de relevé.
A10: Chaque tableau a son encadré « comment remplir », juste au-dessus.
A11: 2. Transactions : un mouvement par ligne, colonnes A à J. Les listes proposent vos comptes et vos types.
A12: 3. Paie (facultative) : un bulletin par mois.
A13: 4. Patrimoine (facultative) : le solde de chaque compte, un relevé par mois.
A14: 5. Visualisation : choisissez un mois en B1. Tout suit vos Paramètres.
A15: Soldes et recettes à gauche ; épargne et rapprochement bancaire au milieu ; dépenses par catégorie à droite.
... A40: 3. Une feuille dont le nom n'est pas reconnu est ignorée — celle-ci, par exemple.

Sheet Transactions
A1: Date | B1: Libellé | C1: Compte | D1: Type | E1: Montant brut | F1: Sens (si différent) | G1: Enseigne | H1: Événement | I1: Ville | J1: Prévisionnel | K1: Montant | L1: Sens | M1: Classe | N1: Catégorie | O1: Compté | P1: Remboursement | Q1: Dépense nette | R1: Effet sur le compte | S1: Compte lié | T1: Effet sur le compte lié | U1: Sortie d'épargne | V1: N° dépense du mois | X1: Légende : | Y1: À remplir | Z1: Calculé — n'écrivez rien
A2: 45536 | B2: Loisirs | C2: Banque A - Part commune | D2: Loisirs | E2: 91.62 | G2: Abonnement vidéo | H2: Rentrée | I2: Villebourg | K2: =IF($E2="","",ROUND($E2*IF(ISNA(MATCH($C2,'Paramètres'!$D:$D,0)),1,IF(INDEX('Paramètres'!$J:$J,MATCH($C2,'Paramètres'!$D:$D,0))="",1,INDEX('Paramètres'!$J:$J,MATCH($C2,'Paramètres'!$D:$D,0)))),2)) -> 45.81 | L2: =IF($D2="","",IF($F2<>"",$F2,IF(ISNA(MATCH($D2,'Paramètres'!$M:$M,0)),"⚠ Type inconnu",IFERROR(INDEX('Paramètres'!$P:$P,MATCH($D2,'Paramètres'!$M:$M,0))&"","")))) -> Débit | M2: =IF($D2="","",IF(ISNA(MATCH($D2,'Paramètres'!$M:$M,0)),"⚠ Type inconnu",IF($L2="Crédit","",IFERROR(INDEX('Paramètres'!$O:$O,MATCH($D2,'Paramètres'!$M:$M,0))&"","")))) -> Dépense Occasionnelle | N2: =IF($D2="","",IFERROR(INDEX('Paramètres'!$Q:$Q,MATCH($D2,'Paramètres'!$M:$M,0))&"","")) -> Loisir | O2: =IF($A2="","",IF(OR($J2<>"x",$A2<=FinReleve),1,0)) -> 1 | P2: =IF($D2="","",IF(AND($L2="Crédit",OR(IFERROR(INDEX('Paramètres'!$O:$O,MATCH($D2,'Paramètres'!$M:$M,0))&"","")<>"",ISNUMBER(SEARCH("remboursement",IFERROR(INDEX('Paramètres'!$N:$N,MATCH($D2,'Paramètres'!$M:$M,0))&"",""))))),1,0)) -> 0 | Q2: =IF($K2="","",IF(ISNUMBER(SEARCH("transfert-interne",IFERROR(INDEX('Paramètres'!$N:$N,MATCH($D2,'Paramètres'!$M:$M,0))&"",""))),0,IF($L2="Débit",$K2,IF($P2=1,-$K2,0)))) -> 45.81 | R2: =IF($K2="","",IF($L2="Crédit",$K2,-$K2)) -> -45.81 | S2: =IF($C2="","",IFERROR(INDEX('Paramètres'!$H:$H,MATCH($C2,'Paramètres'!$D:$D,0))&"","")) -> Banque A - Courant | T2: =IF($K2="","",IF($S2="",0,IF(ISNUMBER(SEARCH("apport-exterieur",IFERROR(INDEX('Paramètres'!$N:$N,MATCH($D2,'Paramètres'!$M:$M,0))&"",""))),0,IF(OR(IFERROR(INDEX('Paramètres'!$I:$I,MATCH($C2,'Paramètres'!$D:$D,0))&"","")="Les deux",IFERROR(INDEX('Paramètres'!$I:$I,MATCH($C2,'Paramètres'!$D:$D,0))&"","")=IF($P2=1,"Débit",$L2)),-IF($P2=1,-$K2,$K2),0)))) -> -45.81 | U2: =IF($K2="","",IF(ISNUMBER(SEARCH("sortie-epargne",IFERROR(INDEX('Paramètres'!$N:$N,MATCH($D2,'Paramètres'!$M:$M,0))&"",""))),$K2,0)) -> 0 | V2: =IF(AND($A2<>"",$O2=1,$L2="Débit",N($Q2)>0,$A2>=Visualisation!$B$1,$A2<Visualisation!$D$1),MAX($V$1:V1)+1,"")
A3: 45537 | B3: Alimentation compte joint | C3: Banque C - Compte joint | D3: Transfert Banque A vers Banque C | E3: 1160 | K3: =IF($E3="","",ROUND($E3*IF(ISNA(MATCH($C3,'Paramètres'!$D:$D,0)),1,IF(INDEX('Paramètres'!$J:$J,MATCH($C3,'Paramètres'!$D:$D,0))="",1,INDEX('Paramètres'!$J:$J,MATCH($C3,'Paramètres'!$D:$D,0)))),2)) -> 1160 | L3: =IF($D3="","",IF($F3<>"",$F3,IF(ISNA(MATCH($D3,'Paramètres'!$M:$M,0)),"⚠ Type inconnu",IFERROR(INDEX('Paramètres'!$P:$P,MATCH($D3,'Paramètres'!$M:$M,0))&"","")))) -> Crédit | M3: =IF($D3="","",IF(ISNA(MATCH($D3,'Paramètres'!$M:$M,0)),"⚠ Type inconnu",IF($L3="Crédit","",IFERROR(INDEX('Paramètres'!$O:$O,MATCH($D3,'Paramètres'!$M:$M,0))&"","")))) | N3: =IF($D3="","",IFERROR(INDEX('Paramètres'!$Q:$Q,MATCH($D3,'Paramètres'!$M:$M,0))&"","")) -> Comptes Bancaires | O3: =IF($A3="","",IF(OR($J3<>"x",$A3<=FinReleve),1,0)) -> 1 | P3: =IF($D3="","",IF(AND($L3="Crédit",OR(IFERROR(INDEX('Paramètres'!$O:$O,MATCH($D3,'Paramètres'!$M:$M,0))&"","")<>"",ISNUMBER(SEARCH("remboursement",IFERROR(INDEX('Paramètres'!$N:$N,MATCH($D3,'Paramètres'!$M:$M,0))&"",""))))),1,0)) -> 0 | Q3: =IF($K3="","",IF(ISNUMBER(SEARCH("transfert-interne",IFERROR(INDEX('Paramètres'!$N:$N,MATCH($D3,'Paramètres'!$M:$M,0))&"",""))),0,IF($L3="Débit",$K3,IF($P3=1,-$K3,0)))) -> 0 | R3: =IF($K3="","",IF($L3="Crédit",$K3,-$K3)) -> 1160 | S3: =IF($C3="","",IFERROR(INDEX('Paramètres'!$H:$H,MATCH($C3,'Paramètres'!$D:$D,0))&"","")) -> Banque A - Courant | T3: =IF($K3="","",IF($S3="",0,IF(ISNUMBER(SEARCH("apport-exterieur",IFERROR(INDEX('Paramètres'!$N:$N,MATCH($D3,'Paramètres'!$M:$M,0))&"",""))),0,IF(OR(IFERROR(INDEX('Paramètres'!$I:$I,MATCH($C3,'Paramètres'!$D:$D,0))&"","")="Les deux",IFERROR(INDEX('Paramètres'!$I:$I,MATCH($C3,'Paramètres'!$D:$D,0))&"","")=IF($P3=1,"Débit",$L3)),-IF($P3=1,-$K3,$K3),0)))) -> -1160 | U3: =IF($K3="","",IF(ISNUMBER(SEARCH("sortie-epargne",IFERROR(INDEX('Paramètres'!$N:$N,MATCH($D3,'Paramètres'!$M:$M,0))&"",""))),$K3,0)) -> 0 | V3: =IF(AND($A3<>"",$O3=1,$L3="Débit",N($Q3)>0,$A3>=Visualisation!$B$1,$A3<Visualisation!$D$1),MAX($V$1:V2)+1,"")
A4: 45537 | B4: Alimentation compte joint | C4: Banque B - Compte joint | D4: Transfert Banque A vers Banque B | E4: 600 | K4: =IF($E4="","",ROUND($E4*IF(ISNA(MATCH($C4,'Paramètres'!$D:$D,0)),1,IF(INDEX('Paramètres'!$J:$J,MATCH($C4,'Paramètres'!$D:$D,0))="",1,INDEX('Paramètres'!$J:$J,MATCH($C4,'Paramètres'!$D:$D,0)))),2)) -> 300 | L4: =IF($D4="","",IF($F4<>"",$F4,IF(ISNA(MATCH($D4,'Paramètres'!$M:$M,0)),"⚠ Type inconnu",IFERROR(INDEX('Paramètres'!$P:$P,MATCH($D4,'Paramètres'!$M:$M,0))&"","")))) -> Crédit | M4: =IF($D4="","",IF(ISNA(MATCH($D4,'Paramètres'!$M:$M,0)),"⚠ Type inconnu",IF($L4="Crédit","",IFERROR(INDEX('Paramètres'!$O:$O,MATCH($D4,'Paramètres'!$M:$M,0))&"","")))) | N4: =IF($D4="","",IFERROR(INDEX('Paramètres'!$Q:$Q,MATCH($D4,'Paramètres'!$M:$M,0))&"","")) -> Comptes Bancaires | O4: =IF($A4="","",IF(OR($J4<>"x",$A4<=FinReleve),1,0)) -> 1 | P4: =IF($D4="","",IF(AND($L4="Crédit",OR(IFERROR(INDEX('Paramètres'!$O:$O,MATCH($D4,'Paramètres'!$M:$M,0))&"","")<>"",ISNUMBER(SEARCH("remboursement",IFERROR(INDEX('Paramètres'!$N:$N,MATCH($D4,'Paramètres'!$M:$M,0))&"",""))))),1,0)) -> 0 | Q4: =IF($K4="","",IF(ISNUMBER(SEARCH("transfert-interne",IFERROR(INDEX('Paramètres'!$N:$N,MATCH($D4,'Paramètres'!$M:$M,0))&"",""))),0,IF($L4="Débit",$K4,IF($P4=1,-$K4,0)))) -> 0 | R4: =IF($K4="","",IF($L4="Crédit",$K4,-$K4)) -> 300 | S4: =IF($C4="","",IFERROR(INDEX('Paramètres'!$H:$H,MATCH($C4,'Paramètres'!$D:$D,0))&"","")) -> Banque A - Courant | T4: =IF($K4="","",IF($S4="",0,IF(ISNUMBER(SEARCH("apport-exterieur",IFERROR(INDEX('Paramètres'!$N:$N,MATCH($D4,'Paramètres'!$M:$M,0))&"",""))),0,IF(OR(IFERROR(INDEX('Paramètres'!$I:$I,MATCH($C4,'Paramètres'!$D:$D,0))&"","")="Les deux",IFERROR(INDEX('Paramètres'!$I:$I,MATCH($C4,'Paramètres'!$D:$D,0))&"","")=IF($P4=1,"Débit",$L4)),-IF($P4=1,-$K4,$K4),0)))) -> -300 | U4: =IF($K4="","",IF(ISNUMBER(SEARCH("sortie-epargne",IFERROR(INDEX('Paramètres'!$N:$N,MATCH($D4,'Paramètres'!$M:$M,0))&"",""))),$K4,0)) -> 0 | V4: =IF(AND($A4<>"",$O4=1,$L4="Débit",N($Q4)>0,$A4>=Visualisation!$B$1,$A4<Visualisation!$D$1),MAX($V$1:V3)+1,"")
A5: 45537 | B5: Titre restaurant | C5: Titres-restaurant | D5: cantine | E5: 8.03 | G5: Cantine | I5: Rocheville | K5: =IF($E5="","",ROUND($E5*IF(ISNA(MATCH($C5,'Paramètres'!$D:$D,0)),1,IF(INDEX('Paramètres'!$J:$J,MATCH($C5,'Paramètres'!$D:$D,0))="",1,INDEX('Paramètres'!$J:$J,MATCH($C5,'Paramètres'!$D:$D,0)))),2)) -> 8.03 | L5: =IF($D5="","",IF($F5<>"",$F5,IF(ISNA(MATCH($D5,'Paramètres'!$M:$M,0)),"⚠ Type inconnu",IFERROR(INDEX('Paramètres'!$P:$P,MATCH($D5,'Paramètres'!$M:$M,0))&"","")))) -> Débit | M5: =IF($D5="","",IF(ISNA(MATCH($D5,'Paramètres'!$M:$M,0)),"⚠ Type inconnu",IF($L5="Crédit","",IFERROR(INDEX('Paramètres'!$O:$O,MATCH($D5,'Paramètres'!$M:$M,0))&"","")))) -> Dépense Courante | N5: =IF($D5="","",IFERROR(INDEX('Paramètres'!$Q:$Q,MATCH($D5,'Paramètres'!$M:$M,0))&"","")) -> Alimentation | O5: =IF($A5="","",IF(OR($J5<>"x",$A5<=FinReleve),1,0)) -> 1 | P5: =IF($D5="","",IF(AND($L5="Crédit",OR(IFERROR(INDEX('Paramètres'!$O:$O,MATCH($D5,'Paramètres'!$M:$M,0))&"","")<>"",ISNUMBER(SEARCH("remboursement",IFERROR(INDEX('Paramètres'!$N:$N,MATCH($D5,'Paramètres'!$M:$M,0))&"",""))))),1,0)) -> 0 | Q5: =IF($K5="","",IF(ISNUMBER(SEARCH("transfert-interne",IFERROR(INDEX('Paramètres'!$N:$N,MATCH($D5,'Paramètres'!$M:$M,0))&"",""))),0,IF($L5="Débit",$K5,IF($P5=1,-$K5,0)))) -> 8.03 | R5: =IF($K5="","",IF($L5="Crédit",$K5,-$K5)) -> -8.03 | S5: =IF($C5="","",IFERROR(INDEX('Paramètres'!$H:$H,MATCH($C5,'Paramètres'!$D:$D,0))&"","")) | T5: =IF($K5="","",IF($S5="",0,IF(ISNUMBER(SEARCH("apport-exterieur",IFERROR(INDEX('Paramètres'!$N:$N,MATCH($D5,'Paramètres'!$M:$M,0))&"",""))),0,IF(OR(IFERROR(INDEX('Paramètres'!$I:$I,MATCH($C5,'Paramètres'!$D:$D,0))&"","")="Les deux",IFERROR(INDEX('Paramètres'!$I:$I,MATCH($C5,'Paramètres'!$D:$D,0))&"","")=IF($P5=1,"Débit",$L5)),-IF($P5=1,-$K5,$K5),0)))) -> 0 | U5: =IF($K5="","",IF(ISNUMBER(SEARCH("sortie-epargne",IFERROR(INDEX('Paramètres'!$N:$N,MATCH($D5,'Paramètres'!$M:$M,0))&"",""))),$K5,0)) -> 0 | V5: =IF(AND($A5<>"",$O5=1,$L5="Débit",N($Q5)>0,$A5>=Visualisation!$B$1,$A5<Visualisation!$D$1),MAX($V$1:V4)+1,"")
A6: 45538 | B6: Abonnement transport | C6: Banque A - Courant | D6: Abonnement transport | E6: 88.8 | K6: =IF($E6="","",ROUND($E6*IF(ISNA(MATCH($C6,'Paramètres'!$D:$D,0)),1,IF(INDEX('Paramètres'!$J:$J,MATCH($C6,'Paramètres'!$D:$D,0))="",1,INDEX('Paramètres'!$J:$J,MATCH($C6,'Paramètres'!$D:$D,0)))),2)) -> 88.8 | L6: =IF($D6="","",IF($F6<>"",$F6,IF(ISNA(MATCH($D6,'Paramètres'!$M:$M,0)),"⚠ Type inconnu",IFERROR(INDEX('Paramètres'!$P:$P,MATCH($D6,'Paramètres'!$M:$M,0))&"","")))) -> Débit | M6: =IF($D6="","",IF(ISNA(MATCH($D6,'Paramètres'!$M:$M,0)),"⚠ Type inconnu",IF($L6="Crédit","",IFERROR(INDEX('Paramètres'!$O:$O,MATCH($D6,'Paramètres'!$M:$M,0))&"","")))) -> Dépense Fixe | N6: =IF($D6="","",IFERROR(INDEX('Paramètres'!$Q:$Q,MATCH($D6,'Paramètres'!$M:$M,0))&"","")) -> Transport | O6: =IF($A6="","",IF(OR($J6<>"x",$A6<=FinReleve),1,0)) -> 1 | P6: =IF($D6="","",IF(AND($L6="Crédit",OR(IFERROR(INDEX('Paramètres'!$O:$O,MATCH($D6,'Paramètres'!$M:$M,0))&"","")<>"",ISNUMBER(SEARCH("remboursement",IFERROR(INDEX('Paramètres'!$N:$N,MATCH($D6,'Paramètres'!$M:$M,0))&"",""))))),1,0)) -> 0 | Q6: =IF($K6="","",IF(ISNUMBER(SEARCH("transfert-interne",IFERROR(INDEX('Paramètres'!$N:$N,MATCH($D6,'Paramètres'!$M:$M,0))&"",""))),0,IF($L6="Débit",$K6,IF($P6=1,-$K6,0)))) -> 88.8 | R6: =IF($K6="","",IF($L6="Crédit",$K6,-$K6)) -> -88.8 | S6: =IF($C6="","",IFERROR(INDEX('Paramètres'!$H:$H,MATCH($C6,'Paramètres'!$D:$D,0))&"","")) | T6: =IF($K6="","",IF($S6="",0,IF(ISNUMBER(SEARCH("apport-exterieur",IFERROR(INDEX('Paramètres'!$N:$N,MATCH($D6,'Paramètres'!$M:$M,0))&"",""))),0,IF(OR(IFERROR(INDEX('Paramètres'!$I:$I,MATCH($C6,'Paramètres'!$D:$D,0))&"","")="Les deux",IFERROR(INDEX('Paramètres'!$I:$I,MATCH($C6,'Paramètres'!$D:$D,0))&"","")=IF($P6=1,"Débit",$L6)),-IF($P6=1,-$K6,$K6),0)))) -> 0 | U6: =IF($K6="","",IF(ISNUMBER(SEARCH("sortie-epargne",IFERROR(INDEX('Paramètres'!$N:$N,MATCH($D6,'Paramètres'!$M:$M,0))&"",""))),$K6,0)) -> 0 | V6: =IF(AND($A6<>"",$O6=1,$L6="Débit",N($Q6)>0,$A6>=Visualisation!$B$1,$A6<Visualisation!$D$1),MAX($V$1:V5)+1,"")
A7: 45539 | B7: Achat carte | C7: Banque A - Part commune | D7: courses | E7: 30.86 | G7: Supermarché Centre | I7: Villebourg-sur-Rive | K7: =IF($E7="","",ROUND($E7*IF(ISNA(MATCH($C7,'Paramètres'!$D:$D,0)),1,IF(INDEX('Paramètres'!$J:$J,MATCH($C7,'Paramètres'!$D:$D,0))="",1,INDEX('Paramètres'!$J:$J,MATCH($C7,'Paramètres'!$D:$D,0)))),2)) -> 15.43 | L7: =IF($D7="","",IF($F7<>"",$F7,IF(ISNA(MATCH($D7,'Paramètres'!$M:$M,0)),"⚠ Type inconnu",IFERROR(INDEX('Paramètres'!$P:$P,MATCH($D7,'Paramètres'!$M:$M,0))&"","")))) -> Débit | M7: =IF($D7="","",IF(ISNA(MATCH($D7,'Paramètres'!$M:$M,0)),"⚠ Type inconnu",IF($L7="Crédit","",IFERROR(INDEX('Paramètres'!$O:$O,MATCH($D7,'Paramètres'!$M:$M,0))&"","")))) -> Dépense Courante | N7: =IF($D7="","",IFERROR(INDEX('Paramètres'!$Q:$Q,MATCH($D7,'Paramètres'!$M:$M,0))&"","")) -> Alimentation | O7: =IF($A7="","",IF(OR($J7<>"x",$A7<=FinReleve),1,0)) -> 1 | P7: =IF($D7="","",IF(AND($L7="Crédit",OR(IFERROR(INDEX('Paramètres'!$O:$O,MATCH($D7,'Paramètres'!$M:$M,0))&"","")<>"",ISNUMBER(SEARCH("remboursement",IFERROR(INDEX('Paramètres'!$N:$N,MATCH($D7,'Paramètres'!$M:$M,0))&"",""))))),1,0)) -> 0 | Q7: =IF($K7="","",IF(ISNUMBER(SEARCH("transfert-interne",IFERROR(INDEX('Paramètres'!$N:$N,MATCH($D7,'Paramètres'!$M:$M,0))&"",""))),0,IF($L7="Débit",$K7,IF($P7=1,-$K7,0)))) -> 15.43 | R7: =IF($K7="","",IF($L7="Crédit",$K7,-$K7)) -> -15.43 | S7: =IF($C7="","",IFERROR(INDEX('Paramètres'!$H:$H,MATCH($C7,'Paramètres'!$D:$D,0))&"","")) -> Banque A - Courant | T7: =IF($K7="","",IF($S7="",0,IF(ISNUMBER(SEARCH("apport-exterieur",IFERROR(INDEX('Paramètres'!$N:$N,MATCH($D7,'Paramètres'!$M:$M,0))&"",""))),0,IF(OR(IFERROR(INDEX('Paramètres'!$I:$I,MATCH($C7,'Paramètres'!$D:$D,0))&"","")="Les deux",IFERROR(INDEX('Paramètres'!$I:$I,MATCH($C7,'Paramètres'!$D:$D,0))&"","")=IF($P7=1,"Débit",$L7)),-IF($P7=1,-$K7,$K7),0)))) -> -15.43 | U7: =IF($K7="","",IF(ISNUMBER(SEARCH("sortie-epargne",IFERROR(INDEX('Paramètres'!$N:$N,MATCH($D7,'Paramètres'!$M:$M,0))&"",""))),$K7,0)) -> 0 | V7: =IF(AND($A7<>"",$O7=1,$L7="Débit",N($Q7)>0,$A7>=Visualisation!$B$1,$A7<Visualisation!$D$1),MAX($V$1:V6)+1,"")
A8: 45539 | B8: Dotation titres | C8: Titres-restaurant | D8: Ticket Restaurant | E8: 121.8 | K8: =IF($E8="","",ROUND($E8*IF(ISNA(MATCH($C8,'Paramètres'!$D:$D,0)),1,IF(INDEX('Paramètres'!$J:$J,MATCH($C8,'Paramètres'!$D:$D,0))="",1,INDEX('Paramètres'!$J:$J,MATCH($C8,'Paramètres'!$D:$D,0)))),2)) -> 121.8 | L8: =IF($D8="","",IF($F8<>"",$F8,IF(ISNA(MATCH($D8,'Paramètres'!$M:$M,0)),"⚠ Type inconnu",IFERROR(INDEX('Paramètres'!$P:$P,MATCH($D8,'Paramètres'!$M:$M,0))&"","")))) -> Crédit | M8: =IF($D8="","",IF(ISNA(MATCH($D8,'Paramètres'!$M:$M,0)),"⚠ Type inconnu",IF($L8="Crédit","",IFERROR(INDEX('Paramètres'!$O:$O,MATCH($D8,'Paramètres'!$M:$M,0))&"","")))) | N8: =IF($D8="","",IFERROR(INDEX('Paramètres'!$Q:$Q,MATCH($D8,'Paramètres'!$M:$M,0))&"","")) -> Comptes Bancaires | O8: =IF($A8="","",IF(OR($J8<>"x",$A8<=FinReleve),1,0)) -> 1 | P8: =IF($D8="","",IF(AND($L8="Crédit",OR(IFERROR(INDEX('Paramètres'!$O:$O,MATCH($D8,'Paramètres'!$M:$M,0))&"","")<>"",ISNUMBER(SEARCH("remboursement",IFERROR(INDEX('Paramètres'!$N:$N,MATCH($D8,'Paramètres'!$M:$M,0))&"",""))))),1,0)) -> 0 | Q8: =IF($K8="","",IF(ISNUMBER(SEARCH("transfert-interne",IFERROR(INDEX('Paramètres'!$N:$N,MATCH($D8,'Paramètres'!$M:$M,0))&"",""))),0,IF($L8="Débit",$K8,IF($P8=1,-$K8,0)))) -> 0 | R8: =IF($K8="","",IF($L8="Crédit",$K8,-$K8)) -> 121.8 | S8: =IF($C8="","",IFERROR(INDEX('Paramètres'!$H:$H,MATCH($C8,'Paramètres'!$D:$D,0))&"","")) | T8: =IF($K8="","",IF($S8="",0,IF(ISNUMBER(SEARCH("apport-exterieur",IFERROR(INDEX('Paramètres'!$N:$N,MATCH($D8,'Paramètres'!$M:$M,0))&"",""))),0,IF(OR(IFERROR(INDEX('Paramètres'!$I:$I,MATCH($C8,'Paramètres'!$D:$D,0))&"","")="Les deux",IFERROR(INDEX('Paramètres'!$I:$I,MATCH($C8,'Paramètres'!$D:$D,0))&"","")=IF($P8=1,"Débit",$L8)),-IF($P8=1,-$K8,$K8),0)))) -> 0 | U8: =IF($K8="","",IF(ISNUMBER(SEARCH("sortie-epargne",IFERROR(INDEX('Paramètres'!$N:$N,MATCH($D8,'Paramètres'!$M:$M,0))&"",""))),$K8,0)) -> 0 | V8: =IF(AND($A8<>"",$O8=1,$L8="Débit",N($Q8)>0,$A8>=Visualisation!$B$1,$A8<Visualisation!$D$1),MAX($V$1:V7)+1,"")
A9: 45540 | B9: Échéance prêt — capital | C9: Banque C - Compte joint | D9: Crédit Immobilier | E9: 645.51 | G9: Remboursement capital | K9: =IF($E9="","",ROUND($E9*IF(ISNA(MATCH($C9,'Paramètres'!$D:$D,0)),1,IF(INDEX('Paramètres'!$J:$J,MATCH($C9,'Paramètres'!$D:$D,0))="",1,INDEX('Paramètres'!$J:$J,MATCH($C9,'Paramètres'!$D:$D,0)))),2)) -> 645.51 | L9: =IF($D9="","",IF($F9<>"",$F9,IF(ISNA(MATCH($D9,'Paramètres'!$M:$M,0)),"⚠ Type inconnu",IFERROR(INDEX('Paramètres'!$P:$P,MATCH($D9,'Paramètres'!$M:$M,0))&"","")))) -> Débit | M9: =IF($D9="","",IF(ISNA(MATCH($D9,'Paramètres'!$M:$M,0)),"⚠ Type inconnu",IF($L9="Crédit","",IFERROR(INDEX('Paramètres'!$O:$O,MATCH($D9,'Paramètres'!$M:$M,0))&"","")))) | N9: =IF($D9="","",IFERROR(INDEX('Paramètres'!$Q:$Q,MATCH($D9,'Paramètres'!$M:$M,0))&"","")) -> Immobilier | O9: =IF($A9="","",IF(OR($J9<>"x",$A9<=FinReleve),1,0)) -> 1 | P9: =IF($D9="","",IF(AND($L9="Crédit",OR(IFERROR(INDEX('Paramètres'!$O:$O,MATCH($D9,'Paramètres'!$M:$M,0))&"","")<>"",ISNUMBER(SEARCH("remboursement",IFERROR(INDEX('Paramètres'!$N:$N,MATCH($D9,'Paramètres'!$M:$M,0))&"",""))))),1,0)) -> 0 | Q9: =IF($K9="","",IF(ISNUMBER(SEARCH("transfert-interne",IFERROR(INDEX('Paramètres'!$N:$N,MATCH($D9,'Paramètres'!$M:$M,0))&"",""))),0,IF($L9="Débit",$K9,IF($P9=1,-$K9,0)))) -> 645.51 | R9: =IF($K9="","",IF($L9="Crédit",$K9,-$K9)) -> -645.51 | S9: =IF($C9="","",IFERROR(INDEX('Paramètres'!$H:$H,MATCH($C9,'Paramètres'!$D:$D,0))&"","")) -> Banque A - Courant | T9: =IF($K9="","",IF($S9="",0,IF(ISNUMBER(SEARCH("apport-exterieur",IFERROR(INDEX('Paramètres'!$N:$N,MATCH($D9,'Paramètres'!$M:$M,0))&"",""))),0,IF(OR(IFERROR(INDEX('Paramètres'!$I:$I,MATCH($C9,'Paramètres'!$D:$D,0))&"","")="Les deux",IFERROR(INDEX('Paramètres'!$I:$I,MATCH($C9,'Paramètres'!$D:$D,0))&"","")=IF($P9=1,"Débit",$L9)),-IF($P9=1,-$K9,$K9),0)))) -> 0 | U9: =IF($K9="","",IF(ISNUMBER(SEARCH("sortie-epargne",IFERROR(INDEX('Paramètres'!$N:$N,MATCH($D9,'Paramètres'!$M:$M,0))&"",""))),$K9,0)) -> 0 | V9: =IF(AND($A9<>"",$O9=1,$L9="Débit",N($Q9)>0,$A9>=Visualisation!$B$1,$A9<Visualisation!$D$1),MAX($V$1:V8)+1,"")
A10: 45540 | B10: Échéance prêt — intérêts | C10: Banque C - Compte joint | D10: Intérêt du prêt | E10: 248.13 | G10: Intérêts | K10: =IF($E10="","",ROUND($E10*IF(ISNA(MATCH($C10,'Paramètres'!$D:$D,0)),1,IF(INDEX('Paramètres'!$J:$J,MATCH($C10,'Paramètres'!$D:$D,0))="",1,INDEX('Paramètres'!$J:$J,MATCH($C10,'Paramètres'!$D:$D,0)))),2)) -> 248.13 | L10: =IF($D10="","",IF($F10<>"",$F10,IF(ISNA(MATCH($D10,'Paramètres'!$M:$M,0)),"⚠ Type inconnu",IFERROR(INDEX('Paramètres'!$P:$P,MATCH($D10,'Paramètres'!$M:$M,0))&"","")))) -> Débit | M10: =IF($D10="","",IF(ISNA(MATCH($D10,'Paramètres'!$M:$M,0)),"⚠ Type inconnu",IF($L10="Crédit","",IFERROR(INDEX('Paramètres'!$O:$O,MATCH($D10,'Paramètres'!$M:$M,0))&"","")))) -> Dépense Fixe | N10: =IF($D10="","",IFERROR(INDEX('Paramètres'!$Q:$Q,MATCH($D10,'Paramètres'!$M:$M,0))&"","")) -> Immobilier | O10: =IF($A10="","",IF(OR($J10<>"x",$A10<=FinReleve),1,0)) -> 1 | P10: =IF($D10="","",IF(AND($L10="Crédit",OR(IFERROR(INDEX('Paramètres'!$O:$O,MATCH($D10,'Paramètres'!$M:$M,0))&"","")<>"",ISNUMBER(SEARCH("remboursement",IFERROR(INDEX('Paramètres'!$N:$N,MATCH($D10,'Paramètres'!$M:$M,0))&"",""))))),1,0)) -> 0 | Q10: =IF($K10="","",IF(ISNUMBER(SEARCH("transfert-interne",IFERROR(INDEX('Paramètres'!$N:$N,MATCH($D10,'Paramètres'!$M:$M,0))&"",""))),0,IF($L10="Débit",$K10,IF($P10=1,-$K10,0)))) -> 248.13 | R10: =IF($K10="","",IF($L10="Crédit",$K10,-$K10)) -> -248.13 | S10: =IF($C10="","",IFERROR(INDEX('Paramètres'!$H:$H,MATCH($C10,'Paramètres'!$D:$D,0))&"","")) -> Banque A - Courant | T10: =IF($K10="","",IF($S10="",0,IF(ISNUMBER(SEARCH("apport-exterieur",IFERROR(INDEX('Paramètres'!$N:$N,MATCH($D10,'Paramètres'!$M:$M,0))&"",""))),0,IF(OR(IFERROR(INDEX('Paramètres'!$I:$I,MATCH($C10,'Paramètres'!$D:$D,0))&"","")="Les deux",IFERROR(INDEX('Paramètres'!$I:$I,MATCH($C10,'Paramètres'!$D:$D,0))&"","")=IF($P10=1,"Débit",$L10)),-IF($P10=1,-$K10,$K10),0)))) -> 0 | U10: =IF($K10="","",IF(ISNUMBER(SEARCH("sortie-epargne",IFERROR(INDEX('Paramètres'!$N:$N,MATCH($D10,'Paramètres'!$M:$M,0))&"",""))),$K10,0)) -> 0 | V10: =IF(AND($A10<>"",$O10=1,$L10="Débit",N($Q10)>0,$A10>=Visualisation!$B$1,$A10<Visualisation!$D$1),MAX($V$1:V9)+1,"")
A11: 45540 | B11: Assurance prêt | C11: Banque C - Compte joint | D11: Assurance prêt | E11: 31.2 | K11: =IF($E11="","",ROUND($E11*IF(ISNA(MATCH($C11,'Paramètres'!$D:$D,0)),1,IF(INDEX('Paramètres'!$J:$J,MATCH($C11,'Paramètres'!$D:$D,0))="",1,INDEX('Paramètres'!$J:$J,MATCH($C11,'Paramètres'!$D:$D,0)))),2)) -> 31.2 | L11: =IF($D11="","",IF($F11<>"",$F11,IF(ISNA(MATCH($D11,'Paramètres'!$M:$M,0)),"⚠ Type inconnu",IFERROR(INDEX('Paramètres'!$P:$P,MATCH($D11,'Paramètres'!$M:$M,0))&"","")))) -> Débit | M11: =IF($D11="","",IF(ISNA(MATCH($D11,'Paramètres'!$M:$M,0)),"⚠ Type inconnu",IF($L11="Crédit","",IFERROR(INDEX('Paramètres'!$O:$O,MATCH($D11,'Paramètres'!$M:$M,0))&"","")))) -> Dépense Fixe | N11: =IF($D11="","",IFERROR(INDEX('Paramètres'!$Q:$Q,MATCH($D11,'Paramètres'!$M:$M,0))&"","")) -> Assurances | O11: =IF($A11="","",IF(OR($J11<>"x",$A11<=FinReleve),1,0)) -> 1 | P11: =IF($D11="","",IF(AND($L11="Crédit",OR(IFERROR(INDEX('Paramètres'!$O:$O,MATCH($D11,'Paramètres'!$M:$M,0))&"","")<>"",ISNUMBER(SEARCH("remboursement",IFERROR(INDEX('Paramètres'!$N:$N,MATCH($D11,'Paramètres'!$M:$M,0))&"",""))))),1,0)) -> 0 | Q11: =IF($K11="","",IF(ISNUMBER(SEARCH("transfert-interne",IFERROR(INDEX('Paramètres'!$N:$N,MATCH($D11,'Paramètres'!$M:$M,0))&"",""))),0,IF($L11="Débit",$K11,IF($P11=1,-$K11,0)))) -> 31.2 | R11: =IF($K11="","",IF($L11="Crédit",$K11,-$K11)) -> -31.2 | S11: =IF($C11="","",IFERROR(INDEX('Paramètres'!$H:$H,MATCH($C11,'Paramètres'!$D:$D,0))&"","")) -> Banque A - Courant | T11: =IF($K11="","",IF($S11="",0,IF(ISNUMBER(SEARCH("apport-exterieur",IFERROR(INDEX('Paramètres'!$N:$N,MATCH($D11,'Paramètres'!$M:$M,0))&"",""))),0,IF(OR(IFERROR(INDEX('Paramètres'!$I:$I,MATCH($C11,'Paramètres'!$D:$D,0))&"","")="Les deux",IFERROR(INDEX('Paramètres'!$I:$I,MATCH($C11,'Paramètres'!$D:$D,0))&"","")=IF($P11=1,"Débit",$L11)),-IF($P11=1,-$K11,$K11),0)))) -> 0 | U11: =IF($K11="","",IF(ISNUMBER(SEARCH("sortie-epargne",IFERROR(INDEX('Paramètres'!$N:$N,MATCH($D11,'Paramètres'!$M:$M,0))&"",""))),$K11,0)) -> 0 | V11: =IF(AND($A11<>"",$O11=1,$L11="Débit",N($Q11)>0,$A11>=Visualisation!$B$1,$A11<Visualisation!$D$1),MAX($V$1:V10)+1,"")
A12: 45541 | B12: Internet et Forfait téléphone | C12: Banque A - Courant | D12: Internet et Forfait téléphone | E12: 49.9 | K12: =IF($E12="","",ROUND($E12*IF(ISNA(MATCH($C12,'Paramètres'!$D:$D,0)),1,IF(INDEX('Paramètres'!$J:$J,MATCH($C12,'Paramètres'!$D:$D,0))="",1,INDEX('Paramètres'!$J:$J,MATCH($C12,'Paramètres'!$D:$D,0)))),2)) -> 49.9 | L12: =IF($D12="","",IF($F12<>"",$F12,IF(ISNA(MATCH($D12,'Paramètres'!$M:$M,0)),"⚠ Type inconnu",IFERROR(INDEX('Paramètres'!$P:$P,MATCH($D12,'Paramètres'!$M:$M,0))&"","")))) -> Débit | M12: =IF($D12="","",IF(ISNA(MATCH($D12,'Paramètres'!$M:$M,0)),"⚠ Type inconnu",IF($L12="Crédit","",IFERROR(INDEX('Paramètres'!$O:$O,MATCH($D12,'Paramètres'!$M:$M,0))&"","")))) -> Dépense Fixe | N12: =IF($D12="","",IFERROR(INDEX('Paramètres'!$Q:$Q,MATCH($D12,'Paramètres'!$M:$M,0))&"","")) -> Autre | O12: =IF($A12="","",IF(OR($J12<>"x",$A12<=FinReleve),1,0)) -> 1 | P12: =IF($D12="","",IF(AND($L12="Crédit",OR(IFERROR(INDEX('Paramètres'!$O:$O,MATCH($D12,'Paramètres'!$M:$M,0))&"","")<>"",ISNUMBER(SEARCH("remboursement",IFERROR(INDEX('Paramètres'!$N:$N,MATCH($D12,'Paramètres'!$M:$M,0))&"",""))))),1,0)) -> 0 | Q12: =IF($K12="","",IF(ISNUMBER(SEARCH("transfert-interne",IFERROR(INDEX('Paramètres'!$N:$N,MATCH($D12,'Paramètres'!$M:$M,0))&"",""))),0,IF($L12="Débit",$K12,IF($P12=1,-$K12,0)))) -> 49.9 | R12: =IF($K12="","",IF($L12="Crédit",$K12,-$K12)) -> -49.9 | S12: =IF($C12="","",IFERROR(INDEX('Paramètres'!$H:$H,MATCH($C12,'Paramètres'!$D:$D,0))&"","")) | T12: =IF($K12="","",IF($S12="",0,IF(ISNUMBER(SEARCH("apport-exterieur",IFERROR(INDEX('Paramètres'!$N:$N,MATCH($D12,'Paramètres'!$M:$M,0))&"",""))),0,IF(OR(IFERROR(INDEX('Paramètres'!$I:$I,MATCH($C12,'Paramètres'!$D:$D,0))&"","")="Les deux",IFERROR(INDEX('Paramètres'!$I:$I,MATCH($C12,'Paramètres'!$D:$D,0))&"","")=IF($P12=1,"Débit",$L12)),-IF($P12=1,-$K12,$K12),0)))) -> 0 | U12: =IF($K12="","",IF(ISNUMBER(SEARCH("sortie-epargne",IFERROR(INDEX('Paramètres'!$N:$N,MATCH($D12,'Paramètres'!$M:$M,0))&"",""))),$K12,0)) -> 0 | V12: =IF(AND($A12<>"",$O12=1,$L12="Débit",N($Q12)>0,$A12>=Visualisation!$B$1,$A12<Visualisation!$D$1),MAX($V$1:V11)+1,"")
A13: 45542 | B13: Carburant | C13: Banque A - Courant | D13: Essence | E13: 80.64 | G13: Parking | I13: Grandval | K13: =IF($E13="","",ROUND($E13*IF(ISNA(MATCH($C13,'Paramètres'!$D:$D,0)),1,IF(INDEX('Paramètres'!$J:$J,MATCH($C13,'Paramètres'!$D:$D,0))="",1,INDEX('Paramètres'!$J:$J,MATCH($C13,'Paramètres'!$D:$D,0)))),2)) -> 80.64 | L13: =IF($D13="","",IF($F13<>"",$F13,IF(ISNA(MATCH($D13,'Paramètres'!$M:$M,0)),"⚠ Type inconnu",IFERROR(INDEX('Paramètres'!$P:$P,MATCH($D13,'Paramètres'!$M:$M,0))&"","")))) -> Débit | M13: =IF($D13="","",IF(ISNA(MATCH($D13,'Paramètres'!$M:$M,0)),"⚠ Type inconnu",IF($L13="Crédit","",IFERROR(INDEX('Paramètres'!$O:$O,MATCH($D13,'Paramètres'!$M:$M,0))&"","")))) -> Dépense Courante | N13: =IF($D13="","",IFERROR(INDEX('Paramètres'!$Q:$Q,MATCH($D13,'Paramètres'!$M:$M,0))&"","")) -> Transport | O13: =IF($A13="","",IF(OR($J13<>"x",$A13<=FinReleve),1,0)) -> 1 | P13: =IF($D13="","",IF(AND($L13="Crédit",OR(IFERROR(INDEX('Paramètres'!$O:$O,MATCH($D13,'Paramètres'!$M:$M,0))&"","")<>"",ISNUMBER(SEARCH("remboursement",IFERROR(INDEX('Paramètres'!$N:$N,MATCH($D13,'Paramètres'!$M:$M,0))&"",""))))),1,0)) -> 0 | Q13: =IF($K13="","",IF(ISNUMBER(SEARCH("transfert-interne",IFERROR(INDEX('Paramètres'!$N:$N,MATCH($D13,'Paramètres'!$M:$M,0))&"",""))),0,IF($L13="Débit",$K13,IF($P13=1,-$K13,0)))) -> 80.64 | R13: =IF($K13="","",IF($L13="Crédit",$K13,-$K13)) -> -80.64 | S13: =IF($C13="","",IFERROR(INDEX('Paramètres'!$H:$H,MATCH($C13,'Paramètres'!$D:$D,0))&"","")) | T13: =IF($K13="","",IF($S13="",0,IF(ISNUMBER(SEARCH("apport-exterieur",IFERROR(INDEX('Paramètres'!$N:$N,MATCH($D13,'Paramètres'!$M:$M,0))&"",""))),0,IF(OR(IFERROR(INDEX('Paramètres'!$I:$I,MATCH($C13,'Paramètres'!$D:$D,0))&"","")="Les deux",IFERROR(INDEX('Paramètres'!$I:$I,MATCH($C13,'Paramètres'!$D:$D,0))&"","")=IF($P13=1,"Débit",$L13)),-IF($P13=1,-$K13,$K13),0)))) -> 0 | U13: =IF($K13="","",IF(ISNUMBER(SEARCH("sortie-epargne",IFERROR(INDEX('Paramètres'!$N:$N,MATCH($D13,'Paramètres'!$M:$M,0))&"",""))),$K13,0)) -> 0 | V13: =IF(AND($A13<>"",$O13=1,$L13="Débit",N($Q13)>0,$A13>=Visualisation!$B$1,$A13<Visualisation!$D$1),MAX($V$1:V12)+1,"")
A14: 45543 | B14: Frais de Copropriété | C14: Banque C - Compte joint | D14: Frais de Copropriété | E14: 168 | K14: =IF($E14="","",ROUND($E14*IF(ISNA(MATCH($C14,'Paramètres'!$D:$D,0)),1,IF(INDEX('Paramètres'!$J:$J,MATCH($C14,'Paramètres'!$D:$D,0))="",1,INDEX('Paramètres'!$J:$J,MATCH($C14,'Paramètres'!$D:$D,0)))),2)) -> 168 | L14: =IF($D14="","",IF($F14<>"",$F14,IF(ISNA(MATCH($D14,'Paramètres'!$M:$M,0)),"⚠ Type inconnu",IFERROR(INDEX('Paramètres'!$P:$P,MATCH($D14,'Paramètres'!$M:$M,0))&"","")))) -> Débit | M14: =IF($D14="","",IF(ISNA(MATCH($D14,'Paramètres'!$M:$M,0)),"⚠ Type inconnu",IF($L14="Crédit","",IFERROR(INDEX('Paramètres'!$O:$O,MATCH($D14,'Paramètres'!$M:$M,0))&"","")))) -> Dépense Fixe | N14: =IF($D14="","",IFERROR(INDEX('Paramètres'!$Q:$Q,MATCH($D14,'Paramètres'!$M:$M,0))&"","")) -> Immobilier | O14: =IF($A14="","",IF(OR($J14<>"x",$A14<=FinReleve),1,0)) -> 1 | P14: =IF($D14="","",IF(AND($L14="Crédit",OR(IFERROR(INDEX('Paramètres'!$O:$O,MATCH($D14,'Paramètres'!$M:$M,0))&"","")<>"",ISNUMBER(SEARCH("remboursement",IFERROR(INDEX('Paramètres'!$N:$N,MATCH($D14,'Paramètres'!$M:$M,0))&"",""))))),1,0)) -> 0 | Q14: =IF($K14="","",IF(ISNUMBER(SEARCH("transfert-interne",IFERROR(INDEX('Paramètres'!$N:$N,MATCH($D14,'Paramètres'!$M:$M,0))&"",""))),0,IF($L14="Débit",$K14,IF($P14=1,-$K14,0)))) -> 168 | R14: =IF($K14="","",IF($L14="Crédit",$K14,-$K14)) -> -168 | S14: =IF($C14="","",IFERROR(INDEX('Paramètres'!$H:$H,MATCH($C14,'Paramètres'!$D:$D,0))&"","")) -> Banque A - Courant | T14: =IF($K14="","",IF($S14="",0,IF(ISNUMBER(SEARCH("apport-exterieur",IFERROR(INDEX('Paramètres'!$N:$N,MATCH($D14,'Paramètres'!$M:$M,0))&"",""))),0,IF(OR(IFERROR(INDEX('Paramètres'!$I:$I,MATCH($C14,'Paramètres'!$D:$D,0))&"","")="Les deux",IFERROR(INDEX('Paramètres'!$I:$I,MATCH($C14,'Paramètres'!$D:$D,0))&"","")=IF($P14=1,"Débit",$L14)),-IF($P14=1,-$K14,$K14),0)))) -> 0 | U14: =IF($K14="","",IF(ISNUMBER(SEARCH("sortie-epargne",IFERROR(INDEX('Paramètres'!$N:$N,MATCH($D14,'Paramètres'!$M:$M,0))&"",""))),$K14,0)) -> 0 | V14: =IF(AND($A14<>"",$O14=1,$L14="Débit",N($Q14)>0,$A14>=Visualisation!$B$1,$A14<Visualisation!$D$1),MAX($V$1:V13)+1,"")
A15: 45543 | B15: Titre restaurant | C15: Titres-restaurant | D15: cantine | E15: 8.1 | G15: Cantine | I15: Grandval | K15: =IF($E15="","",ROUND($E15*IF(ISNA(MATCH($C15,'Paramètres'!$D:$D,0)),1,IF(INDEX('Paramètres'!$J:$J,MATCH($C15,'Paramètres'!$D:$D,0))="",1,INDEX('Paramètres'!$J:$J,MATCH($C15,'Paramètres'!$D:$D,0)))),2)) -> 8.1 | L15: =IF($D15="","",IF($F15<>"",$F15,IF(ISNA(MATCH($D15,'Paramètres'!$M:$M,0)),"⚠ Type inconnu",IFERROR(INDEX('Paramètres'!$P:$P,MATCH($D15,'Paramètres'!$M:$M,0))&"","")))) -> Débit | M15: =IF($D15="","",IF(ISNA(MATCH($D15,'Paramètres'!$M:$M,0)),"⚠ Type inconnu",IF($L15="Crédit","",IFERROR(INDEX('Paramètres'!$O:$O,MATCH($D15,'Paramètres'!$M:$M,0))&"","")))) -> Dépense Courante | N15: =IF($D15="","",IFERROR(INDEX('Paramètres'!$Q:$Q,MATCH($D15,'Paramètres'!$M:$M,0))&"","")) -> Alimentation | O15: =IF($A15="","",IF(OR($J15<>"x",$A15<=FinReleve),1,0)) -> 1 | P15: =IF($D15="","",IF(AND($L15="Crédit",OR(IFERROR(INDEX('Paramètres'!$O:$O,MATCH($D15,'Paramètres'!$M:$M,0))&"","")<>"",ISNUMBER(SEARCH("remboursement",IFERROR(INDEX('Paramètres'!$N:$N,MATCH($D15,'Paramètres'!$M:$M,0))&"",""))))),1,0)) -> 0 | Q15: =IF($K15="","",IF(ISNUMBER(SEARCH("transfert-interne",IFERROR(INDEX('Paramètres'!$N:$N,MATCH($D15,'Paramètres'!$M:$M,0))&"",""))),0,IF($L15="Débit",$K15,IF($P15=1,-$K15,0)))) -> 8.1 | R15: =IF($K15="","",IF($L15="Crédit",$K15,-$K15)) -> -8.1 | S15: =IF($C15="","",IFERROR(INDEX('Paramètres'!$H:$H,MATCH($C15,'Paramètres'!$D:$D,0))&"","")) | T15: =IF($K15="","",IF($S15="",0,IF(ISNUMBER(SEARCH("apport-exterieur",IFERROR(INDEX('Paramètres'!$N:$N,MATCH($D15,'Paramètres'!$M:$M,0))&"",""))),0,IF(OR(IFERROR(INDEX('Paramètres'!$I:$I,MATCH($C15,'Paramètres'!$D:$D,0))&"","")="Les deux",IFERROR(INDEX('Paramètres'!$I:$I,MATCH($C15,'Paramètres'!$D:$D,0))&"","")=IF($P15=1,"Débit",$L15)),-IF($P15=1,-$K15,$K15),0)))) -> 0 | U15: =IF($K15="","",IF(ISNUMBER(SEARCH("sortie-epargne",IFERROR(INDEX('Paramètres'!$N:$N,MATCH($D15,'Paramètres'!$M:$M,0))&"",""))),$K15,0)) -> 0 | V15: =IF(AND($A15<>"",$O15=1,$L15="Débit",N($Q15)>0,$A15>=Visualisation!$B$1,$A15<Visualisation!$D$1),MAX($V$1:V14)+1,"")
A16: 45544 | B16: Achat carte | C16: Banque B - Compte joint | D16: courses | E16: 145.44 | G16: Supermarché Ouest | I16: Villebourg-sur-Rive | K16: =IF($E16="","",ROUND($E16*IF(ISNA(MATCH($C16,'Paramètres'!$D:$D,0)),1,IF(INDEX('Paramètres'!$J:$J,MATCH($C16,'Paramètres'!$D:$D,0))="",1,INDEX('Paramètres'!$J:$J,MATCH($C16,'Paramètres'!$D:$D,0)))),2)) -> 72.72 | L16: =IF($D16="","",IF($F16<>"",$F16,IF(ISNA(MATCH($D16,'Paramètres'!$M:$M,0)),"⚠ Type inconnu",IFERROR(INDEX('Paramètres'!$P:$P,MATCH($D16,'Paramètres'!$M:$M,0))&"","")))) -> Débit | M16: =IF($D16="","",IF(ISNA(MATCH($D16,'Paramètres'!$M:$M,0)),"⚠ Type inconnu",IF($L16="Crédit","",IFERROR(INDEX('Paramètres'!$O:$O,MATCH($D16,'Paramètres'!$M:$M,0))&"","")))) -> Dépense Courante | N16: =IF($D16="","",IFERROR(INDEX('Paramètres'!$Q:$Q,MATCH($D16,'Paramètres'!$M:$M,0))&"","")) -> Alimentation | O16: =IF($A16="","",IF(OR($J16<>"x",$A16<=FinReleve),1,0)) -> 1 | P16: =IF($D16="","",IF(AND($L16="Crédit",OR(IFERROR(INDEX('Paramètres'!$O:$O,MATCH($D16,'Paramètres'!$M:$M,0))&"","")<>"",ISNUMBER(SEARCH("remboursement",IFERROR(INDEX('Paramètres'!$N:$N,MATCH($D16,'Paramètres'!$M:$M,0))&"",""))))),1,0)) -> 0 | Q16: =IF($K16="","",IF(ISNUMBER(SEARCH("transfert-interne",IFERROR(INDEX('Paramètres'!$N:$N,MATCH($D16,'Paramètres'!$M:$M,0))&"",""))),0,IF($L16="Débit",$K16,IF($P16=1,-$K16,0)))) -> 72.72 | R16: =IF($K16="","",IF($L16="Crédit",$K16,-$K16)) -> -72.72 | S16: =IF($C16="","",IFERROR(INDEX('Paramètres'!$H:$H,MATCH($C16,'Paramètres'!$D:$D,0))&"","")) -> Banque A - Courant | T16: =IF($K16="","",IF($S16="",0,IF(ISNUMBER(SEARCH("apport-exterieur",IFERROR(INDEX('Paramètres'!$N:$N,MATCH($D16,'Paramètres'!$M:$M,0))&"",""))),0,IF(OR(IFERROR(INDEX('Paramètres'!$I:$I,MATCH($C16,'Paramètres'!$D:$D,0))&"","")="Les deux",IFERROR(INDEX('Paramètres'!$I:$I,MATCH($C16,'Paramètres'!$D:$D,0))&"","")=IF($P16=1,"Débit",$L16)),-IF($P16=1,-$K16,$K16),0)))) -> 0 | U16: =IF($K16="","",IF(ISNUMBER(SEARCH("sortie-epargne",IFERROR(INDEX('Paramètres'!$N:$N,MATCH($D16,'Paramètres'!$M:$M,0))&"",""))),$K16,0)) -> 0 | V16: =IF(AND($A16<>"",$O16=1,$L16="Débit",N($Q16)>0,$A16>=Visualisation!$B$1,$A16<Visualisation!$D$1),MAX($V$1:V15)+1,"")
A17: 45545 | B17: Assurance habitation | C17: Banque A - Courant | D17: Assurance habitation | E17: 22.4 | K17: =IF($E17="","",ROUND($E17*IF(ISNA(MATCH($C17,'Paramètres'!$D:$D,0)),1,IF(INDEX('Paramètres'!$J:$J,MATCH($C17,'Paramètres'!$D:$D,0))="",1,INDEX('Paramètres'!$J:$J,MATCH($C17,'Paramètres'!$D:$D,0)))),2)) -> 22.4 | L17: =IF($D17="","",IF($F17<>"",$F17,IF(ISNA(MATCH($D17,'Paramètres'!$M:$M,0)),"⚠ Type inconnu",IFERROR(INDEX('Paramètres'!$P:$P,MATCH($D17,'Paramètres'!$M:$M,0))&"","")))) -> Débit | M17: =IF($D17="","",IF(ISNA(MATCH($D17,'Paramètres'!$M:$M,0)),"⚠ Type inconnu",IF($L17="Crédit","",IFERROR(INDEX('Paramètres'!$O:$O,MATCH($D17,'Paramètres'!$M:$M,0))&"","")))) -> Dépense Fixe | N17: =IF($D17="","",IFERROR(INDEX('Paramètres'!$Q:$Q,MATCH($D17,'Paramètres'!$M:$M,0))&"","")) -> Assurances | O17: =IF($A17="","",IF(OR($J17<>"x",$A17<=FinReleve),1,0)) -> 1 | P17: =IF($D17="","",IF(AND($L17="Crédit",OR(IFERROR(INDEX('Paramètres'!$O:$O,MATCH($D17,'Paramètres'!$M:$M,0))&"","")<>"",ISNUMBER(SEARCH("remboursement",IFERROR(INDEX('Paramètres'!$N:$N,MATCH($D17,'Paramètres'!$M:$M,0))&"",""))))),1,0)) -> 0 | Q17: =IF($K17="","",IF(ISNUMBER(SEARCH("transfert-interne",IFERROR(INDEX('Paramètres'!$N:$N,MATCH($D17,'Paramètres'!$M:$M,0))&"",""))),0,IF($L17="Débit",$K17,IF($P17=1,-$K17,0)))) -> 22.4 | R17: =IF($K17="","",IF($L17="Crédit",$K17,-$K17)) -> -22.4 | S17: =IF($C17="","",IFERROR(INDEX('Paramètres'!$H:$H,MATCH($C17,'Paramètres'!$D:$D,0))&"","")) | T17: =IF($K17="","",IF($S17="",0,IF(ISNUMBER(SEARCH("apport-exterieur",IFERROR(INDEX('Paramètres'!$N:$N,MATCH($D17,'Paramètres'!$M:$M,0))&"",""))),0,IF(OR(IFERROR(INDEX('Paramètres'!$I:$I,MATCH($C17,'Paramètres'!$D:$D,0))&"","")="Les deux",IFERROR(INDEX('Paramètres'!$I:$I,MATCH($C17,'Paramètres'!$D:$D,0))&"","")=IF($P17=1,"Débit",$L17)),-IF($P17=1,-$K17,$K17),0)))) -> 0 | U17: =IF($K17="","",IF(ISNUMBER(SEARCH("sortie-epargne",IFERROR(INDEX('Paramètres'!$N:$N,MATCH($D17,'Paramètres'!$M:$M,0))&"",""))),$K17,0)) -> 0 | V17: =IF(AND($A17<>"",$O17=1,$L17="Débit",N($Q17)>0,$A17>=Visualisation!$B$1,$A17<Visualisation!$D$1),MAX($V$1:V16)+1,"")
A18: 45545 | B18: Achat carte | C18: Banque B - Compte joint | D18: courses | E18: 31.26 | G18: Supermarché Ouest | I18: Villebourg | K18: =IF($E18="","",ROUND($E18*IF(ISNA(MATCH($C18,'Paramètres'!$D:$D,0)),1,IF(INDEX('Paramètres'!$J:$J,MATCH($C18,'Paramètres'!$D:$D,0))="",1,INDEX('Paramètres'!$J:$J,MATCH($C18,'Paramètres'!$D:$D,0)))),2)) -> 15.63 | L18: =IF($D18="","",IF($F18<>"",$F18,IF(ISNA(MATCH($D18,'Paramètres'!$M:$M,0)),"⚠ Type inconnu",IFERROR(INDEX('Paramètres'!$P:$P,MATCH($D18,'Paramètres'!$M:$M,0))&"","")))) -> Débit | M18: =IF($D18="","",IF(ISNA(MATCH($D18,'Paramètres'!$M:$M,0)),"⚠ Type inconnu",IF($L18="Crédit","",IFERROR(INDEX('Paramètres'!$O:$O,MATCH($D18,'Paramètres'!$M:$M,0))&"","")))) -> Dépense Courante | N18: =IF($D18="","",IFERROR(INDEX('Paramètres'!$Q:$Q,MATCH($D18,'Paramètres'!$M:$M,0))&"","")) -> Alimentation | O18: =IF($A18="","",IF(OR($J18<>"x",$A18<=FinReleve),1,0)) -> 1 | P18: =IF($D18="","",IF(AND($L18="Crédit",OR(IFERROR(INDEX('Paramètres'!$O:$O,MATCH($D18,'Paramètres'!$M:$M,0))&"","")<>"",ISNUMBER(SEARCH("remboursement",IFERROR(INDEX('Paramètres'!$N:$N,MATCH($D18,'Paramètres'!$M:$M,0))&"",""))))),1,0)) -> 0 | Q18: =IF($K18="","",IF(ISNUMBER(SEARCH("transfert-interne",IFERROR(INDEX('Paramètres'!$N:$N,MATCH($D18,'Paramètres'!$M:$M,0))&"",""))),0,IF($L18="Débit",$K18,IF($P18=1,-$K18,0)))) -> 15.63 | R18: =IF($K18="","",IF($L18="Crédit",$K18,-$K18)) -> -15.63 | S18: =IF($C18="","",IFERROR(INDEX('Paramètres'!$H:$H,MATCH($C18,'Paramètres'!$D:$D,0))&"","")) -> Banque A - Courant | T18: =IF($K18="","",IF($S18="",0,IF(ISNUMBER(SEARCH("apport-exterieur",IFERROR(INDEX('Paramètres'!$N:$N,MATCH($D18,'Paramètres'!$M:$M,0))&"",""))),0,IF(OR(IFERROR(INDEX('Paramètres'!$I:$I,MATCH($C18,'Paramètres'!$D:$D,0))&"","")="Les deux",IFERROR(INDEX('Paramètres'!$I:$I,MATCH($C18,'Paramètres'!$D:$D,0))&"","")=IF($P18=1,"Débit",$L18)),-IF($P18=1,-$K18,$K18),0)))) -> 0 | U18: =IF($K18="","",IF(ISNUMBER(SEARCH("sortie-epargne",IFERROR(INDEX('Paramètres'!$N:$N,MATCH($D18,'Paramètres'!$M:$M,0))&"",""))),$K18,0)) -> 0 | V18: =IF(AND($A18<>"",$O18=1,$L18="Débit",N($Q18)>0,$A18>=Visualisation!$B$1,$A18<Visualisation!$D$1),MAX($V$1:V17)+1,"")
A19: 45547 | B19: Assurance auto | C19: Banque A - Courant | D19: Assurance auto | E19: 47.9 | K19: =IF($E19="","",ROUND($E19*IF(ISNA(MATCH($C19,'Paramètres'!$D:$D,0)),1,IF(INDEX('Paramètres'!$J:$J,MATCH($C19,'Paramètres'!$D:$D,0))="",1,INDEX('Paramètres'!$J:$J,MATCH($C19,'Paramètres'!$D:$D,0)))),2)) -> 47.9 | L19: =IF($D19="","",IF($F19<>"",$F19,IF(ISNA(MATCH($D19,'Paramètres'!$M:$M,0)),"⚠ Type inconnu",IFERROR(INDEX('Paramètres'!$P:$P,MATCH($D19,'Paramètres'!$M:$M,0))&"","")))) -> Débit | M19: =IF($D19="","",IF(ISNA(MATCH($D19,'Paramètres'!$M:$M,0)),"⚠ Type inconnu",IF($L19="Crédit","",IFERROR(INDEX('Paramètres'!$O:$O,MATCH($D19,'Paramètres'!$M:$M,0))&"","")))) -> Dépense Fixe | N19: =IF($D19="","",IFERROR(INDEX('Paramètres'!$Q:$Q,MATCH($D19,'Paramètres'!$M:$M,0))&"","")) -> Assurances | O19: =IF($A19="","",IF(OR($J19<>"x",$A19<=FinReleve),1,0)) -> 1 | P19: =IF($D19="","",IF(AND($L19="Crédit",OR(IFERROR(INDEX('Paramètres'!$O:$O,MATCH($D19,'Paramètres'!$M:$M,0))&"","")<>"",ISNUMBER(SEARCH("remboursement",IFERROR(INDEX('Paramètres'!$N:$N,MATCH($D19,'Paramètres'!$M:$M,0))&"",""))))),1,0)) -> 0 | Q19: =IF($K19="","",IF(ISNUMBER(SEARCH("transfert-interne",IFERROR(INDEX('Paramètres'!$N:$N,MATCH($D19,'Paramètres'!$M:$M,0))&"",""))),0,IF($L19="Débit",$K19,IF($P19=1,-$K19,0)))) -> 47.9 | R19: =IF($K19="","",IF($L19="Crédit",$K19,-$K19)) -> -47.9 | S19: =IF($C19="","",IFERROR(INDEX('Paramètres'!$H:$H,MATCH($C19,'Paramètres'!$D:$D,0))&"","")) | T19: =IF($K19="","",IF($S19="",0,IF(ISNUMBER(SEARCH("apport-exterieur",IFERROR(INDEX('Paramètres'!$N:$N,MATCH($D19,'Paramètres'!$M:$M,0))&"",""))),0,IF(OR(IFERROR(INDEX('Paramètres'!$I:$I,MATCH($C19,'Paramètres'!$D:$D,0))&"","")="Les deux",IFERROR(INDEX('Paramètres'!$I:$I,MATCH($C19,'Paramètres'!$D:$D,0))&"","")=IF($P19=1,"Débit",$L19)),-IF($P19=1,-$K19,$K19),0)))) -> 0 | U19: =IF($K19="","",IF(ISNUMBER(SEARCH("sortie-epargne",IFERROR(INDEX('Paramètres'!$N:$N,MATCH($D19,'Paramètres'!$M:$M,0))&"",""))),$K19,0)) -> 0 | V19: =IF(AND($A19<>"",$O19=1,$L19="Débit",N($Q19)>0,$A19>=Visualisation!$B$1,$A19<Visualisation!$D$1),MAX($V$1:V18)+1,"")
A20: 45547 | B20: Achat carte | C20: Banque B - Compte joint | D20: courses | E20: 191.52 | G20: Primeur | I20: Grandval | K20: =IF($E20="","",ROUND($E20*IF(ISNA(MATCH($C20,'Paramètres'!$D:$D,0)),1,IF(INDEX('Paramètres'!$J:$J,MATCH($C20,'Paramètres'!$D:$D,0))="",1,INDEX('Paramètres'!$J:$J,MATCH($C20,'Paramètres'!$D:$D,0)))),2)) -> 95.76 | L20: =IF($D20="","",IF($F20<>"",$F20,IF(ISNA(MATCH($D20,'Paramètres'!$M:$M,0)),"⚠ Type inconnu",IFERROR(INDEX('Paramètres'!$P:$P,MATCH($D20,'Paramètres'!$M:$M,0))&"","")))) -> Débit | M20: =IF($D20="","",IF(ISNA(MATCH($D20,'Paramètres'!$M:$M,0)),"⚠ Type inconnu",IF($L20="Crédit","",IFERROR(INDEX('Paramètres'!$O:$O,MATCH($D20,'Paramètres'!$M:$M,0))&"","")))) -> Dépense Courante | N20: =IF($D20="","",IFERROR(INDEX('Paramètres'!$Q:$Q,MATCH($D20,'Paramètres'!$M:$M,0))&"","")) -> Alimentation | O20: =IF($A20="","",IF(OR($J20<>"x",$A20<=FinReleve),1,0)) -> 1 | P20: =IF($D20="","",IF(AND($L20="Crédit",OR(IFERROR(INDEX('Paramètres'!$O:$O,MATCH($D20,'Paramètres'!$M:$M,0))&"","")<>"",ISNUMBER(SEARCH("remboursement",IFERROR(INDEX('Paramètres'!$N:$N,MATCH($D20,'Paramètres'!$M:$M,0))&"",""))))),1,0)) -> 0 | Q20: =IF($K20="","",IF(ISNUMBER(SEARCH("transfert-interne",IFERROR(INDEX('Paramètres'!$N:$N,MATCH($D20,'Paramètres'!$M:$M,0))&"",""))),0,IF($L20="Débit",$K20,IF($P20=1,-$K20,0)))) -> 95.76 | R20: =IF($K20="","",IF($L20="Crédit",$K20,-$K20)) -> -95.76 | S20: =IF($C20="","",IFERROR(INDEX('Paramètres'!$H:$H,MATCH($C20,'Paramètres'!$D:$D,0))&"","")) -> Banque A - Courant | T20: =IF($K20="","",IF($S20="",0,IF(ISNUMBER(SEARCH("apport-exterieur",IFERROR(INDEX('Paramètres'!$N:$N,MATCH($D20,'Paramètres'!$M:$M,0))&"",""))),0,IF(OR(IFERROR(INDEX('Paramètres'!$I:$I,MATCH($C20,'Paramètres'!$D:$D,0))&"","")="Les deux",IFERROR(INDEX('Paramètres'!$I:$I,MATCH($C20,'Paramètres'!$D:$D,0))&"","")=IF($P20=1,"Débit",$L20)),-IF($P20=1,-$K20,$K20),0)))) -> 0 | U20: =IF($K20="","",IF(ISNUMBER(SEARCH("sortie-epargne",IFERROR(INDEX('Paramètres'!$N:$N,MATCH($D20,'Paramètres'!$M:$M,0))&"",""))),$K20,0)) -> 0 | V20: =IF(AND($A20<>"",$O20=1,$L20="Débit",N($Q20)>0,$A20>=Visualisation!$B$1,$A20<Visualisation!$D$1),MAX($V$1:V19)+1,"")
A21: 45548 | B21: Titre restaurant | C21: Titres-restaurant | D21: cantine | E21: 11.17 | G21: Cantine | I21: Villebourg | K21: =IF($E21="","",ROUND($E21*IF(ISNA(MATCH($C21,'Paramètres'!$D:$D,0)),1,IF(INDEX('Paramètres'!$J:$J,MATCH($C21,'Paramètres'!$D:$D,0))="",1,INDEX('Paramètres'!$J:$J,MATCH($C21,'Paramètres'!$D:$D,0)))),2)) -> 11.17 | L21: =IF($D21="","",IF($F21<>"",$F21,IF(ISNA(MATCH($D21,'Paramètres'!$M:$M,0)),"⚠ Type inconnu",IFERROR(INDEX('Paramètres'!$P:$P,MATCH($D21,'Paramètres'!$M:$M,0))&"","")))) -> Débit | M21: =IF($D21="","",IF(ISNA(MATCH($D21,'Paramètres'!$M:$M,0)),"⚠ Type inconnu",IF($L21="Crédit","",IFERROR(INDEX('Paramètres'!$O:$O,MATCH($D21,'Paramètres'!$M:$M,0))&"","")))) -> Dépense Courante | N21: =IF($D21="","",IFERROR(INDEX('Paramètres'!$Q:$Q,MATCH($D21,'Paramètres'!$M:$M,0))&"","")) -> Alimentation | O21: =IF($A21="","",IF(OR($J21<>"x",$A21<=FinReleve),1,0)) -> 1 | P21: =IF($D21="","",IF(AND($L21="Crédit",OR(IFERROR(INDEX('Paramètres'!$O:$O,MATCH($D21,'Paramètres'!$M:$M,0))&"","")<>"",ISNUMBER(SEARCH("remboursement",IFERROR(INDEX('Paramètres'!$N:$N,MATCH($D21,'Paramètres'!$M:$M,0))&"",""))))),1,0)) -> 0 | Q21: =IF($K21="","",IF(ISNUMBER(SEARCH("transfert-interne",IFERROR(INDEX('Paramètres'!$N:$N,MATCH($D21,'Paramètres'!$M:$M,0))&"",""))),0,IF($L21="Débit",$K21,IF($P21=1,-$K21,0)))) -> 11.17 | R21: =IF($K21="","",IF($L21="Crédit",$K21,-$K21)) -> -11.17 | S21: =IF($C21="","",IFERROR(INDEX('Paramètres'!$H:$H,MATCH($C21,'Paramètres'!$D:$D,0))&"","")) | T21: =IF($K21="","",IF($S21="",0,IF(ISNUMBER(SEARCH("apport-exterieur",IFERROR(INDEX('Paramètres'!$N:$N,MATCH($D21,'Paramètres'!$M:$M,0))&"",""))),0,IF(OR(IFERROR(INDEX('Paramètres'!$I:$I,MATCH($C21,'Paramètres'!$D:$D,0))&"","")="Les deux",IFERROR(INDEX('Paramètres'!$I:$I,MATCH($C21,'Paramètres'!$D:$D,0))&"","")=IF($P21=1,"Débit",$L21)),-IF($P21=1,-$K21,$K21),0)))) -> 0 | U21: =IF($K21="","",IF(ISNUMBER(SEARCH("sortie-epargne",IFERROR(INDEX('Paramètres'!$N:$N,MATCH($D21,'Paramètres'!$M:$M,0))&"",""))),$K21,0)) -> 0 | V21: =IF(AND($A21<>"",$O21=1,$L21="Débit",N($Q21)>0,$A21>=Visualisation!$B$1,$A21<Visualisation!$D$1),MAX($V$1:V20)+1,"")
A22: 45549 | B22: Titre restaurant | C22: Titres-restaurant | D22: cantine | E22: 9.43 | G22: Cantine | I22: Villebourg-sur-Rive | K22: =IF($E22="","",ROUND($E22*IF(ISNA(MATCH($C22,'Paramètres'!$D:$D,0)),1,IF(INDEX('Paramètres'!$J:$J,MATCH($C22,'Paramètres'!$D:$D,0))="",1,INDEX('Paramètres'!$J:$J,MATCH($C22,'Paramètres'!$D:$D,0)))),2)) -> 9.43 | L22: =IF($D22="","",IF($F22<>"",$F22,IF(ISNA(MATCH($D22,'Paramètres'!$M:$M,0)),"⚠ Type inconnu",IFERROR(INDEX('Paramètres'!$P:$P,MATCH($D22,'Paramètres'!$M:$M,0))&"","")))) -> Débit | M22: =IF($D22="","",IF(ISNA(MATCH($D22,'Paramètres'!$M:$M,0)),"⚠ Type inconnu",IF($L22="Crédit","",IFERROR(INDEX('Paramètres'!$O:$O,MATCH($D22,'Paramètres'!$M:$M,0))&"","")))) -> Dépense Courante | N22: =IF($D22="","",IFERROR(INDEX('Paramètres'!$Q:$Q,MATCH($D22,'Paramètres'!$M:$M,0))&"","")) -> Alimentation | O22: =IF($A22="","",IF(OR($J22<>"x",$A22<=FinReleve),1,0)) -> 1 | P22: =IF($D22="","",IF(AND($L22="Crédit",OR(IFERROR(INDEX('Paramètres'!$O:$O,MATCH($D22,'Paramètres'!$M:$M,0))&"","")<>"",ISNUMBER(SEARCH("remboursement",IFERROR(INDEX('Paramètres'!$N:$N,MATCH($D22,'Paramètres'!$M:$M,0))&"",""))))),1,0)) -> 0 | Q22: =IF($K22="","",IF(ISNUMBER(SEARCH("transfert-interne",IFERROR(INDEX('Paramètres'!$N:$N,MATCH($D22,'Paramètres'!$M:$M,0))&"",""))),0,IF($L22="Débit",$K22,IF($P22=1,-$K22,0)))) -> 9.43 | R22: =IF($K22="","",IF($L22="Crédit",$K22,-$K22)) -> -9.43 | S22: =IF($C22="","",IFERROR(INDEX('Paramètres'!$H:$H,MATCH($C22,'Paramètres'!$D:$D,0))&"","")) | T22: =IF($K22="","",IF($S22="",0,IF(ISNUMBER(SEARCH("apport-exterieur",IFERROR(INDEX('Paramètres'!$N:$N,MATCH($D22,'Paramètres'!$M:$M,0))&"",""))),0,IF(OR(IFERROR(INDEX('Paramètres'!$I:$I,MATCH($C22,'Paramètres'!$D:$D,0))&"","")="Les deux",IFERROR(INDEX('Paramètres'!$I:$I,MATCH($C22,'Paramètres'!$D:$D,0))&"","")=IF($P22=1,"Débit",$L22)),-IF($P22=1,-$K22,$K22),0)))) -> 0 | U22: =IF($K22="","",IF(ISNUMBER(SEARCH("sortie-epargne",IFERROR(INDEX('Paramètres'!$N:$N,MATCH($D22,'Paramètres'!$M:$M,0))&"",""))),$K22,0)) -> 0 | V22: =IF(AND($A22<>"",$O22=1,$L22="Débit",N($Q22)>0,$A22>=Visualisation!$B$1,$A22<Visualisation!$D$1),MAX($V$1:V21)+1,"")
A23: 45549 | B23: Loisirs | C23: Banque A - Part commune | D23: Loisirs | E23: 49.84 | G23: Concert | H23: Rentrée | I23: Villebourg-sur-Rive | K23: =IF($E23="","",ROUND($E23*IF(ISNA(MATCH($C23,'Paramètres'!$D:$D,0)),1,IF(INDEX('Paramètres'!$J:$J,MATCH($C23,'Paramètres'!$D:$D,0))="",1,INDEX('Paramètres'!$J:$J,MATCH($C23,'Paramètres'!$D:$D,0)))),2)) -> 24.92 | L23: =IF($D23="","",IF($F23<>"",$F23,IF(ISNA(MATCH($D23,'Paramètres'!$M:$M,0)),"⚠ Type inconnu",IFERROR(INDEX('Paramètres'!$P:$P,MATCH($D23,'Paramètres'!$M:$M,0))&"","")))) -> Débit | M23: =IF($D23="","",IF(ISNA(MATCH($D23,'Paramètres'!$M:$M,0)),"⚠ Type inconnu",IF($L23="Crédit","",IFERROR(INDEX('Paramètres'!$O:$O,MATCH($D23,'Paramètres'!$M:$M,0))&"","")))) -> Dépense Occasionnelle | N23: =IF($D23="","",IFERROR(INDEX('Paramètres'!$Q:$Q,MATCH($D23,'Paramètres'!$M:$M,0))&"","")) -> Loisir | O23: =IF($A23="","",IF(OR($J23<>"x",$A23<=FinReleve),1,0)) -> 1 | P23: =IF($D23="","",IF(AND($L23="Crédit",OR(IFERROR(INDEX('Paramètres'!$O:$O,MATCH($D23,'Paramètres'!$M:$M,0))&"","")<>"",ISNUMBER(SEARCH("remboursement",IFERROR(INDEX('Paramètres'!$N:$N,MATCH($D23,'Paramètres'!$M:$M,0))&"",""))))),1,0)) -> 0 | Q23: =IF($K23="","",IF(ISNUMBER(SEARCH("transfert-interne",IFERROR(INDEX('Paramètres'!$N:$N,MATCH($D23,'Paramètres'!$M:$M,0))&"",""))),0,IF($L23="Débit",$K23,IF($P23=1,-$K23,0)))) -> 24.92 | R23: =IF($K23="","",IF($L23="Crédit",$K23,-$K23)) -> -24.92 | S23: =IF($C23="","",IFERROR(INDEX('Paramètres'!$H:$H,MATCH($C23,'Paramètres'!$D:$D,0))&"","")) -> Banque A - Courant | T23: =IF($K23="","",IF($S23="",0,IF(ISNUMBER(SEARCH("apport-exterieur",IFERROR(INDEX('Paramètres'!$N:$N,MATCH($D23,'Paramètres'!$M:$M,0))&"",""))),0,IF(OR(IFERROR(INDEX('Paramètres'!$I:$I,MATCH($C23,'Paramètres'!$D:$D,0))&"","")="Les deux",IFERROR(INDEX('Paramètres'!$I:$I,MATCH($C23,'Paramètres'!$D:$D,0))&"","")=IF($P23=1,"Débit",$L23)),-IF($P23=1,-$K23,$K23),0)))) -> -24.92 | U23: =IF($K23="","",IF(ISNUMBER(SEARCH("sortie-epargne",IFERROR(INDEX('Paramètres'!$N:$N,MATCH($D23,'Paramètres'!$M:$M,0))&"",""))),$K23,0)) -> 0 | V23: =IF(AND($A23<>"",$O23=1,$L23="Débit",N($Q23)>0,$A23>=Visualisation!$B$1,$A23<Visualisation!$D$1),MAX($V$1:V22)+1,"")
A24: 45550 | B24: Electricité | C24: Banque C - Compte joint | D24: Electricité | E24: 86.34 | K24: =IF($E24="","",ROUND($E24*IF(ISNA(MATCH($C24,'Paramètres'!$D:$D,0)),1,IF(INDEX('Paramètres'!$J:$J,MATCH($C24,'Paramètres'!$D:$D,0))="",1,INDEX('Paramètres'!$J:$J,MATCH($C24,'Paramètres'!$D:$D,0)))),2)) -> 86.34 | L24: =IF($D24="","",IF($F24<>"",$F24,IF(ISNA(MATCH($D24,'Paramètres'!$M:$M,0)),"⚠ Type inconnu",IFERROR(INDEX('Paramètres'!$P:$P,MATCH($D24,'Paramètres'!$M:$M,0))&"","")))) -> Débit | M24: =IF($D24="","",IF(ISNA(MATCH($D24,'Paramètres'!$M:$M,0)),"⚠ Type inconnu",IF($L24="Crédit","",IFERROR(INDEX('Paramètres'!$O:$O,MATCH($D24,'Paramètres'!$M:$M,0))&"","")))) -> Dépense Fixe | N24: =IF($D24="","",IFERROR(INDEX('Paramètres'!$Q:$Q,MATCH($D24,'Paramètres'!$M:$M,0))&"","")) -> Immobilier | O24: =IF($A24="","",IF(OR($J24<>"x",$A24<=FinReleve),1,0)) -> 1 | P24: =IF($D24="","",IF(AND($L24="Crédit",OR(IFERROR(INDEX('Paramètres'!$O:$O,MATCH($D24,'Paramètres'!$M:$M,0))&"","")<>"",ISNUMBER(SEARCH("remboursement",IFERROR(INDEX('Paramètres'!$N:$N,MATCH($D24,'Paramètres'!$M:$M,0))&"",""))))),1,0)) -> 0 | Q24: =IF($K24="","",IF(ISNUMBER(SEARCH("transfert-interne",IFERROR(INDEX('Paramètres'!$N:$N,MATCH($D24,'Paramètres'!$M:$M,0))&"",""))),0,IF($L24="Débit",$K24,IF($P24=1,-$K24,0)))) -> 86.34 | R24: =IF($K24="","",IF($L24="Crédit",$K24,-$K24)) -> -86.34 | S24: =IF($C24="","",IFERROR(INDEX('Paramètres'!$H:$H,MATCH($C24,'Paramètres'!$D:$D,0))&"","")) -> Banque A - Courant | T24: =IF($K24="","",IF($S24="",0,IF(ISNUMBER(SEARCH("apport-exterieur",IFERROR(INDEX('Paramètres'!$N:$N,MATCH($D24,'Paramètres'!$M:$M,0))&"",""))),0,IF(OR(IFERROR(INDEX('Paramètres'!$I:$I,MATCH($C24,'Paramètres'!$D:$D,0))&"","")="Les deux",IFERROR(INDEX('Paramètres'!$I:$I,MATCH($C24,'Paramètres'!$D:$D,0))&"","")=IF($P24=1,"Débit",$L24)),-IF($P24=1,-$K24,$K24),0)))) -> 0 | U24: =IF($K24="","",IF(ISNUMBER(SEARCH("sortie-epargne",IFERROR(INDEX('Paramètres'!$N:$N,MATCH($D24,'Paramètres'!$M:$M,0))&"",""))),$K24,0)) -> 0 | V24: =IF(AND($A24<>"",$O24=1,$L24="Débit",N($Q24)>0,$A24>=Visualisation!$B$1,$A24<Visualisation!$D$1),MAX($V$1:V23)+1,"")
A25: 45550 | B25: Remboursement | C25: Banque B - Compte joint | D25: Virement extérieur | E25: 386.04 | K25: =IF($E25="","",ROUND($E25*IF(ISNA(MATCH($C25,'Paramètres'!$D:$D,0)),1,IF(INDEX('Paramètres'!$J:$J,MATCH($C25,'Paramètres'!$D:$D,0))="",1,INDEX('Paramètres'!$J:$J,MATCH($C25,'Paramètres'!$D:$D,0)))),2)) -> 193.02 | L25: =IF($D25="","",IF($F25<>"",$F25,IF(ISNA(MATCH($D25,'Paramètres'!$M:$M,0)),"⚠ Type inconnu",IFERROR(INDEX('Paramètres'!$P:$P,MATCH($D25,'Paramètres'!$M:$M,0))&"","")))) -> Crédit | M25: =IF($D25="","",IF(ISNA(MATCH($D25,'Paramètres'!$M:$M,0)),"⚠ Type inconnu",IF($L25="Crédit","",IFERROR(INDEX('Paramètres'!$O:$O,MATCH($D25,'Paramètres'!$M:$M,0))&"","")))) | N25: =IF($D25="","",IFERROR(INDEX('Paramètres'!$Q:$Q,MATCH($D25,'Paramètres'!$M:$M,0))&"","")) -> Comptes Bancaires | O25: =IF($A25="","",IF(OR($J25<>"x",$A25<=FinReleve),1,0)) -> 1 | P25: =IF($D25="","",IF(AND($L25="Crédit",OR(IFERROR(INDEX('Paramètres'!$O:$O,MATCH($D25,'Paramètres'!$M:$M,0))&"","")<>"",ISNUMBER(SEARCH("remboursement",IFERROR(INDEX('Paramètres'!$N:$N,MATCH($D25,'Paramètres'!$M:$M,0))&"",""))))),1,0)) -> 0 | Q25: =IF($K25="","",IF(ISNUMBER(SEARCH("transfert-interne",IFERROR(INDEX('Paramètres'!$N:$N,MATCH($D25,'Paramètres'!$M:$M,0))&"",""))),0,IF($L25="Débit",$K25,IF($P25=1,-$K25,0)))) -> 0 | R25: =IF($K25="","",IF($L25="Crédit",$K25,-$K25)) -> 193.02 | S25: =IF($C25="","",IFERROR(INDEX('Paramètres'!$H:$H,MATCH($C25,'Paramètres'!$D:$D,0))&"","")) -> Banque A - Courant | T25: =IF($K25="","",IF($S25="",0,IF(ISNUMBER(SEARCH("apport-exterieur",IFERROR(INDEX('Paramètres'!$N:$N,MATCH($D25,'Paramètres'!$M:$M,0))&"",""))),0,IF(OR(IFERROR(INDEX('Paramètres'!$I:$I,MATCH($C25,'Paramètres'!$D:$D,0))&"","")="Les deux",IFERROR(INDEX('Paramètres'!$I:$I,MATCH($C25,'Paramètres'!$D:$D,0))&"","")=IF($P25=1,"Débit",$L25)),-IF($P25=1,-$K25,$K25),0)))) -> 0 | U25: =IF($K25="","",IF(ISNUMBER(SEARCH("sortie-epargne",IFERROR(INDEX('Paramètres'!$N:$N,MATCH($D25,'Paramètres'!$M:$M,0))&"",""))),$K25,0)) -> 0 | V25: =IF(AND($A25<>"",$O25=1,$L25="Débit",N($Q25)>0,$A25>=Visualisation!$B$1,$A25<Visualisation!$D$1),MAX($V$1:V24)+1,"")
A26: 45551 | B26: Achat carte | C26: Banque B - Compte joint | D26: courses | E26: 100.4 | G26: Boulangerie | I26: Villebourg-sur-Rive | K26: =IF($E26="","",ROUND($E26*IF(ISNA(MATCH($C26,'Paramètres'!$D:$D,0)),1,IF(INDEX('Paramètres'!$J:$J,MATCH($C26,'Paramètres'!$D:$D,0))="",1,INDEX('Paramètres'!$J:$J,MATCH($C26,'Paramètres'!$D:$D,0)))),2)) -> 50.2 | L26: =IF($D26="","",IF($F26<>"",$F26,IF(ISNA(MATCH($D26,'Paramètres'!$M:$M,0)),"⚠ Type inconnu",IFERROR(INDEX('Paramètres'!$P:$P,MATCH($D26,'Paramètres'!$M:$M,0))&"","")))) -> Débit | M26: =IF($D26="","",IF(ISNA(MATCH($D26,'Paramètres'!$M:$M,0)),"⚠ Type inconnu",IF($L26="Crédit","",IFERROR(INDEX('Paramètres'!$O:$O,MATCH($D26,'Paramètres'!$M:$M,0))&"","")))) -> Dépense Courante | N26: =IF($D26="","",IFERROR(INDEX('Paramètres'!$Q:$Q,MATCH($D26,'Paramètres'!$M:$M,0))&"","")) -> Alimentation | O26: =IF($A26="","",IF(OR($J26<>"x",$A26<=FinReleve),1,0)) -> 1 | P26: =IF($D26="","",IF(AND($L26="Crédit",OR(IFERROR(INDEX('Paramètres'!$O:$O,MATCH($D26,'Paramètres'!$M:$M,0))&"","")<>"",ISNUMBER(SEARCH("remboursement",IFERROR(INDEX('Paramètres'!$N:$N,MATCH($D26,'Paramètres'!$M:$M,0))&"",""))))),1,0)) -> 0 | Q26: =IF($K26="","",IF(ISNUMBER(SEARCH("transfert-interne",IFERROR(INDEX('Paramètres'!$N:$N,MATCH($D26,'Paramètres'!$M:$M,0))&"",""))),0,IF($L26="Débit",$K26,IF($P26=1,-$K26,0)))) -> 50.2 | R26: =IF($K26="","",IF($L26="Crédit",$K26,-$K26)) -> -50.2 | S26: =IF($C26="","",IFERROR(INDEX('Paramètres'!$H:$H,MATCH($C26,'Paramètres'!$D:$D,0))&"","")) -> Banque A - Courant | T26: =IF($K26="","",IF($S26="",0,IF(ISNUMBER(SEARCH("apport-exterieur",IFERROR(INDEX('Paramètres'!$N:$N,MATCH($D26,'Paramètres'!$M:$M,0))&"",""))),0,IF(OR(IFERROR(INDEX('Paramètres'!$I:$I,MATCH($C26,'Paramètres'!$D:$D,0))&"","")="Les deux",IFERROR(INDEX('Paramètres'!$I:$I,MATCH($C26,'Paramètres'!$D:$D,0))&"","")=IF($P26=1,"Débit",$L26)),-IF($P26=1,-$K26,$K26),0)))) -> 0 | U26: =IF($K26="","",IF(ISNUMBER(SEARCH("sortie-epargne",IFERROR(INDEX('Paramètres'!$N:$N,MATCH($D26,'Paramètres'!$M:$M,0))&"",""))),$K26,0)) -> 0 | V26: =IF(AND($A26<>"",$O26=1,$L26="Débit",N($Q26)>0,$A26>=Visualisation!$B$1,$A26<Visualisation!$D$1),MAX($V$1:V25)+1,"")
A27: 45552 | B27: Titre restaurant | C27: Titres-restaurant | D27: cantine | E27: 7.96 | G27: Cantine | I27: Villebourg-sur-Rive | K27: =IF($E27="","",ROUND($E27*IF(ISNA(MATCH($C27,'Paramètres'!$D:$D,0)),1,IF(INDEX('Paramètres'!$J:$J,MATCH($C27,'Paramètres'!$D:$D,0))="",1,INDEX('Paramètres'!$J:$J,MATCH($C27,'Paramètres'!$D:$D,0)))),2)) -> 7.96 | L27: =IF($D27="","",IF($F27<>"",$F27,IF(ISNA(MATCH($D27,'Paramètres'!$M:$M,0)),"⚠ Type inconnu",IFERROR(INDEX('Paramètres'!$P:$P,MATCH($D27,'Paramètres'!$M:$M,0))&"","")))) -> Débit | M27: =IF($D27="","",IF(ISNA(MATCH($D27,'Paramètres'!$M:$M,0)),"⚠ Type inconnu",IF($L27="Crédit","",IFERROR(INDEX('Paramètres'!$O:$O,MATCH($D27,'Paramètres'!$M:$M,0))&"","")))) -> Dépense Courante | N27: =IF($D27="","",IFERROR(INDEX('Paramètres'!$Q:$Q,MATCH($D27,'Paramètres'!$M:$M,0))&"","")) -> Alimentation | O27: =IF($A27="","",IF(OR($J27<>"x",$A27<=FinReleve),1,0)) -> 1 | P27: =IF($D27="","",IF(AND($L27="Crédit",OR(IFERROR(INDEX('Paramètres'!$O:$O,MATCH($D27,'Paramètres'!$M:$M,0))&"","")<>"",ISNUMBER(SEARCH("remboursement",IFERROR(INDEX('Paramètres'!$N:$N,MATCH($D27,'Paramètres'!$M:$M,0))&"",""))))),1,0)) -> 0 | Q27: =IF($K27="","",IF(ISNUMBER(SEARCH("transfert-interne",IFERROR(INDEX('Paramètres'!$N:$N,MATCH($D27,'Paramètres'!$M:$M,0))&"",""))),0,IF($L27="Débit",$K27,IF($P27=1,-$K27,0)))) -> 7.96 | R27: =IF($K27="","",IF($L27="Crédit",$K27,-$K27)) -> -7.96 | S27: =IF($C27="","",IFERROR(INDEX('Paramètres'!$H:$H,MATCH($C27,'Paramètres'!$D:$D,0))&"","")) | T27: =IF($K27="","",IF($S27="",0,IF(ISNUMBER(SEARCH("apport-exterieur",IFERROR(INDEX('Paramètres'!$N:$N,MATCH($D27,'Paramètres'!$M:$M,0))&"",""))),0,IF(OR(IFERROR(INDEX('Paramètres'!$I:$I,MATCH($C27,'Paramètres'!$D:$D,0))&"","")="Les deux",IFERROR(INDEX('Paramètres'!$I:$I,MATCH($C27,'Paramètres'!$D:$D,0))&"","")=IF($P27=1,"Débit",$L27)),-IF($P27=1,-$K27,$K27),0)))) -> 0 | U27: =IF($K27="","",IF(ISNUMBER(SEARCH("sortie-epargne",IFERROR(INDEX('Paramètres'!$N:$N,MATCH($D27,'Paramètres'!$M:$M,0))&"",""))),$K27,0)) -> 0 | V27: =IF(AND($A27<>"",$O27=1,$L27="Débit",N($Q27)>0,$A27>=Visualisation!$B$1,$A27<Visualisation!$D$1),MAX($V$1:V26)+1,"")
A28: 45553 | B28: Impôt sur Revenu | C28: Banque A - Courant | D28: Impôt sur Revenu | E28: 212 | K28: =IF($E28="","",ROUND($E28*IF(ISNA(MATCH($C28,'Paramètres'!$D:$D,0)),1,IF(INDEX('Paramètres'!$J:$J,MATCH($C28,'Paramètres'!$D:$D,0))="",1,INDEX('Paramètres'!$J:$J,MATCH($C28,'Paramètres'!$D:$D,0)))),2)) -> 212 | L28: =IF($D28="","",IF($F28<>"",$F28,IF(ISNA(MATCH($D28,'Paramètres'!$M:$M,0)),"⚠ Type inconnu",IFERROR(INDEX('Paramètres'!$P:$P,MATCH($D28,'Paramètres'!$M:$M,0))&"","")))) -> Débit | M28: =IF($D28="","",IF(ISNA(MATCH($D28,'Paramètres'!$M:$M,0)),"⚠ Type inconnu",IF($L28="Crédit","",IFERROR(INDEX('Paramètres'!$O:$O,MATCH($D28,'Paramètres'!$M:$M,0))&"","")))) -> Dépense Fixe | N28: =IF($D28="","",IFERROR(INDEX('Paramètres'!$Q:$Q,MATCH($D28,'Paramètres'!$M:$M,0))&"","")) -> Impots | O28: =IF($A28="","",IF(OR($J28<>"x",$A28<=FinReleve),1,0)) -> 1 | P28: =IF($D28="","",IF(AND($L28="Crédit",OR(IFERROR(INDEX('Paramètres'!$O:$O,MATCH($D28,'Paramètres'!$M:$M,0))&"","")<>"",ISNUMBER(SEARCH("remboursement",IFERROR(INDEX('Paramètres'!$N:$N,MATCH($D28,'Paramètres'!$M:$M,0))&"",""))))),1,0)) -> 0 | Q28: =IF($K28="","",IF(ISNUMBER(SEARCH("transfert-interne",IFERROR(INDEX('Paramètres'!$N:$N,MATCH($D28,'Paramètres'!$M:$M,0))&"",""))),0,IF($L28="Débit",$K28,IF($P28=1,-$K28,0)))) -> 212 | R28: =IF($K28="","",IF($L28="Crédit",$K28,-$K28)) -> -212 | S28: =IF($C28="","",IFERROR(INDEX('Paramètres'!$H:$H,MATCH($C28,'Paramètres'!$D:$D,0))&"","")) | T28: =IF($K28="","",IF($S28="",0,IF(ISNUMBER(SEARCH("apport-exterieur",IFERROR(INDEX('Paramètres'!$N:$N,MATCH($D28,'Paramètres'!$M:$M,0))&"",""))),0,IF(OR(IFERROR(INDEX('Paramètres'!$I:$I,MATCH($C28,'Paramètres'!$D:$D,0))&"","")="Les deux",IFERROR(INDEX('Paramètres'!$I:$I,MATCH($C28,'Paramètres'!$D:$D,0))&"","")=IF($P28=1,"Débit",$L28)),-IF($P28=1,-$K28,$K28),0)))) -> 0 | U28: =IF($K28="","",IF(ISNUMBER(SEARCH("sortie-epargne",IFERROR(INDEX('Paramètres'!$N:$N,MATCH($D28,'Paramètres'!$M:$M,0))&"",""))),$K28,0)) -> 0 | V28: =IF(AND($A28<>"",$O28=1,$L28="Débit",N($Q28)>0,$A28>=Visualisation!$B$1,$A28<Visualisation!$D$1),MAX($V$1:V27)+1,"")
A29: 45554 | B29: Achat carte | C29: Banque B - Compte joint | D29: courses | E29: 120.22 | G29: Supermarché Centre | I29: Rocheville | K29: =IF($E29="","",ROUND($E29*IF(ISNA(MATCH($C29,'Paramètres'!$D:$D,0)),1,IF(INDEX('Paramètres'!$J:$J,MATCH($C29,'Paramètres'!$D:$D,0))="",1,INDEX('Paramètres'!$J:$J,MATCH($C29,'Paramètres'!$D:$D,0)))),2)) -> 60.11 | L29: =IF($D29="","",IF($F29<>"",$F29,IF(ISNA(MATCH($D29,'Paramètres'!$M:$M,0)),"⚠ Type inconnu",IFERROR(INDEX('Paramètres'!$P:$P,MATCH($D29,'Paramètres'!$M:$M,0))&"","")))) -> Débit | M29: =IF($D29="","",IF(ISNA(MATCH($D29,'Paramètres'!$M:$M,0)),"⚠ Type inconnu",IF($L29="Crédit","",IFERROR(INDEX('Paramètres'!$O:$O,MATCH($D29,'Paramètres'!$M:$M,0))&"","")))) -> Dépense Courante | N29: =IF($D29="","",IFERROR(INDEX('Paramètres'!$Q:$Q,MATCH($D29,'Paramètres'!$M:$M,0))&"","")) -> Alimentation | O29: =IF($A29="","",IF(OR($J29<>"x",$A29<=FinReleve),1,0)) -> 1 | P29: =IF($D29="","",IF(AND($L29="Crédit",OR(IFERROR(INDEX('Paramètres'!$O:$O,MATCH($D29,'Paramètres'!$M:$M,0))&"","")<>"",ISNUMBER(SEARCH("remboursement",IFERROR(INDEX('Paramètres'!$N:$N,MATCH($D29,'Paramètres'!$M:$M,0))&"",""))))),1,0)) -> 0 | Q29: =IF($K29="","",IF(ISNUMBER(SEARCH("transfert-interne",IFERROR(INDEX('Paramètres'!$N:$N,MATCH($D29,'Paramètres'!$M:$M,0))&"",""))),0,IF($L29="Débit",$K29,IF($P29=1,-$K29,0)))) -> 60.11 | R29: =IF($K29="","",IF($L29="Crédit",$K29,-$K29)) -> -60.11 | S29: =IF($C29="","",IFERROR(INDEX('Paramètres'!$H:$H,MATCH($C29,'Paramètres'!$D:$D,0))&"","")) -> Banque A - Courant | T29: =IF($K29="","",IF($S29="",0,IF(ISNUMBER(SEARCH("apport-exterieur",IFERROR(INDEX('Paramètres'!$N:$N,MATCH($D29,'Paramètres'!$M:$M,0))&"",""))),0,IF(OR(IFERROR(INDEX('Paramètres'!$I:$I,MATCH($C29,'Paramètres'!$D:$D,0))&"","")="Les deux",IFERROR(INDEX('Paramètres'!$I:$I,MATCH($C29,'Paramètres'!$D:$D,0))&"","")=IF($P29=1,"Débit",$L29)),-IF($P29=1,-$K29,$K29),0)))) -> 0 | U29: =IF($K29="","",IF(ISNUMBER(SEARCH("sortie-epargne",IFERROR(INDEX('Paramètres'!$N:$N,MATCH($D29,'Paramètres'!$M:$M,0))&"",""))),$K29,0)) -> 0 | V29: =IF(AND($A29<>"",$O29=1,$L29="Débit",N($Q29)>0,$A29>=Visualisation!$B$1,$A29<Visualisation!$D$1),MAX($V$1:V28)+1,"")
A30: 45555 | B30: Titre restaurant | C30: Titres-restaurant | D30: cantine | E30: 12.3 | G30: Cantine | I30: Rocheville | K30: =IF($E30="","",ROUND($E30*IF(ISNA(MATCH($C30,'Paramètres'!$D:$D,0)),1,IF(INDEX('Paramètres'!$J:$J,MATCH($C30,'Paramètres'!$D:$D,0))="",1,INDEX('Paramètres'!$J:$J,MATCH($C30,'Paramètres'!$D:$D,0)))),2)) -> 12.3 | L30: =IF($D30="","",IF($F30<>"",$F30,IF(ISNA(MATCH($D30,'Paramètres'!$M:$M,0)),"⚠ Type inconnu",IFERROR(INDEX('Paramètres'!$P:$P,MATCH($D30,'Paramètres'!$M:$M,0))&"","")))) -> Débit | M30: =IF($D30="","",IF(ISNA(MATCH($D30,'Paramètres'!$M:$M,0)),"⚠ Type inconnu",IF($L30="Crédit","",IFERROR(INDEX('Paramètres'!$O:$O,MATCH($D30,'Paramètres'!$M:$M,0))&"","")))) -> Dépense Courante | N30: =IF($D30="","",IFERROR(INDEX('Paramètres'!$Q:$Q,MATCH($D30,'Paramètres'!$M:$M,0))&"","")) -> Alimentation | O30: =IF($A30="","",IF(OR($J30<>"x",$A30<=FinReleve),1,0)) -> 1 | P30: =IF($D30="","",IF(AND($L30="Crédit",OR(IFERROR(INDEX('Paramètres'!$O:$O,MATCH($D30,'Paramètres'!$M:$M,0))&"","")<>"",ISNUMBER(SEARCH("remboursement",IFERROR(INDEX('Paramètres'!$N:$N,MATCH($D30,'Paramètres'!$M:$M,0))&"",""))))),1,0)) -> 0 | Q30: =IF($K30="","",IF(ISNUMBER(SEARCH("transfert-interne",IFERROR(INDEX('Paramètres'!$N:$N,MATCH($D30,'Paramètres'!$M:$M,0))&"",""))),0,IF($L30="Débit",$K30,IF($P30=1,-$K30,0)))) -> 12.3 | R30: =IF($K30="","",IF($L30="Crédit",$K30,-$K30)) -> -12.3 | S30: =IF($C30="","",IFERROR(INDEX('Paramètres'!$H:$H,MATCH($C30,'Paramètres'!$D:$D,0))&"","")) | T30: =IF($K30="","",IF($S30="",0,IF(ISNUMBER(SEARCH("apport-exterieur",IFERROR(INDEX('Paramètres'!$N:$N,MATCH($D30,'Paramètres'!$M:$M,0))&"",""))),0,IF(OR(IFERROR(INDEX('Paramètres'!$I:$I,MATCH($C30,'Paramètres'!$D:$D,0))&"","")="Les deux",IFERROR(INDEX('Paramètres'!$I:$I,MATCH($C30,'Paramètres'!$D:$D,0))&"","")=IF($P30=1,"Débit",$L30)),-IF($P30=1,-$K30,$K30),0)))) -> 0 | U30: =IF($K30="","",IF(ISNUMBER(SEARCH("sortie-epargne",IFERROR(INDEX('Paramètres'!$N:$N,MATCH($D30,'Paramètres'!$M:$M,0))&"",""))),$K30,0)) -> 0 | V30: =IF(AND($A30<>"",$O30=1,$L30="Débit",N($Q30)>0,$A30>=Visualisation!$B$1,$A30<Visualisation!$D$1),MAX($V$1:V29)+1,"")
A31: 45556 | B31: Titre restaurant | C31: Titres-restaurant | D31: cantine | E31: 10.4 | G31: Cantine | I31: Villebourg | K31: =IF($E31="","",ROUND($E31*IF(ISNA(MATCH($C31,'Paramètres'!$D:$D,0)),1,IF(INDEX('Paramètres'!$J:$J,MATCH($C31,'Paramètres'!$D:$D,0))="",1,INDEX('Paramètres'!$J:$J,MATCH($C31,'Paramètres'!$D:$D,0)))),2)) -> 10.4 | L31: =IF($D31="","",IF($F31<>"",$F31,IF(ISNA(MATCH($D31,'Paramètres'!$M:$M,0)),"⚠ Type inconnu",IFERROR(INDEX('Paramètres'!$P:$P,MATCH($D31,'Paramètres'!$M:$M,0))&"","")))) -> Débit | M31: =IF($D31="","",IF(ISNA(MATCH($D31,'Paramètres'!$M:$M,0)),"⚠ Type inconnu",IF($L31="Crédit","",IFERROR(INDEX('Paramètres'!$O:$O,MATCH($D31,'Paramètres'!$M:$M,0))&"","")))) -> Dépense Courante | N31: =IF($D31="","",IFERROR(INDEX('Paramètres'!$Q:$Q,MATCH($D31,'Paramètres'!$M:$M,0))&"","")) -> Alimentation | O31: =IF($A31="","",IF(OR($J31<>"x",$A31<=FinReleve),1,0)) -> 1 | P31: =IF($D31="","",IF(AND($L31="Crédit",OR(IFERROR(INDEX('Paramètres'!$O:$O,MATCH($D31,'Paramètres'!$M:$M,0))&"","")<>"",ISNUMBER(SEARCH("remboursement",IFERROR(INDEX('Paramètres'!$N:$N,MATCH($D31,'Paramètres'!$M:$M,0))&"",""))))),1,0)) -> 0 | Q31: =IF($K31="","",IF(ISNUMBER(SEARCH("transfert-interne",IFERROR(INDEX('Paramètres'!$N:$N,MATCH($D31,'Paramètres'!$M:$M,0))&"",""))),0,IF($L31="Débit",$K31,IF($P31=1,-$K31,0)))) -> 10.4 | R31: =IF($K31="","",IF($L31="Crédit",$K31,-$K31)) -> -10.4 | S31: =IF($C31="","",IFERROR(INDEX('Paramètres'!$H:$H,MATCH($C31,'Paramètres'!$D:$D,0))&"","")) | T31: =IF($K31="","",IF($S31="",0,IF(ISNUMBER(SEARCH("apport-exterieur",IFERROR(INDEX('Paramètres'!$N:$N,MATCH($D31,'Paramètres'!$M:$M,0))&"",""))),0,IF(OR(IFERROR(INDEX('Paramètres'!$I:$I,MATCH($C31,'Paramètres'!$D:$D,0))&"","")="Les deux",IFERROR(INDEX('Paramètres'!$I:$I,MATCH($C31,'Paramètres'!$D:$D,0))&"","")=IF($P31=1,"Débit",$L31)),-IF($P31=1,-$K31,$K31),0)))) -> 0 | U31: =IF($K31="","",IF(ISNUMBER(SEARCH("sortie-epargne",IFERROR(INDEX('Paramètres'!$N:$N,MATCH($D31,'Paramètres'!$M:$M,0))&"",""))),$K31,0)) -> 0 | V31: =IF(AND($A31<>"",$O31=1,$L31="Débit",N($Q31)>0,$A31>=Visualisation!$B$1,$A31<Visualisation!$D$1),MAX($V$1:V30)+1,"")
A32: 45557 | B32: Titre restaurant | C32: Titres-restaurant | D32: cantine | E32: 8.27 | G32: Cantine | I32: Villebourg-sur-Rive | K32: =IF($E32="","",ROUND($E32*IF(ISNA(MATCH($C32,'Paramètres'!$D:$D,0)),1,IF(INDEX('Paramètres'!$J:$J,MATCH($C32,'Paramètres'!$D:$D,0))="",1,INDEX('Paramètres'!$J:$J,MATCH($C32,'Paramètres'!$D:$D,0)))),2)) -> 8.27 | L32: =IF($D32="","",IF($F32<>"",$F32,IF(ISNA(MATCH($D32,'Paramètres'!$M:$M,0)),"⚠ Type inconnu",IFERROR(INDEX('Paramètres'!$P:$P,MATCH($D32,'Paramètres'!$M:$M,0))&"","")))) -> Débit | M32: =IF($D32="","",IF(ISNA(MATCH($D32,'Paramètres'!$M:$M,0)),"⚠ Type inconnu",IF($L32="Crédit","",IFERROR(INDEX('Paramètres'!$O:$O,MATCH($D32,'Paramètres'!$M:$M,0))&"","")))) -> Dépense Courante | N32: =IF($D32="","",IFERROR(INDEX('Paramètres'!$Q:$Q,MATCH($D32,'Paramètres'!$M:$M,0))&"","")) -> Alimentation | O32: =IF($A32="","",IF(OR($J32<>"x",$A32<=FinReleve),1,0)) -> 1 | P32: =IF($D32="","",IF(AND($L32="Crédit",OR(IFERROR(INDEX('Paramètres'!$O:$O,MATCH($D32,'Paramètres'!$M:$M,0))&"","")<>"",ISNUMBER(SEARCH("remboursement",IFERROR(INDEX('Paramètres'!$N:$N,MATCH($D32,'Paramètres'!$M:$M,0))&"",""))))),1,0)) -> 0 | Q32: =IF($K32="","",IF(ISNUMBER(SEARCH("transfert-interne",IFERROR(INDEX('Paramètres'!$N:$N,MATCH($D32,'Paramètres'!$M:$M,0))&"",""))),0,IF($L32="Débit",$K32,IF($P32=1,-$K32,0)))) -> 8.27 | R32: =IF($K32="","",IF($L32="Crédit",$K32,-$K32)) -> -8.27 | S32: =IF($C32="","",IFERROR(INDEX('Paramètres'!$H:$H,MATCH($C32,'Paramètres'!$D:$D,0))&"","")) | T32: =IF($K32="","",IF($S32="",0,IF(ISNUMBER(SEARCH("apport-exterieur",IFERROR(INDEX('Paramètres'!$N:$N,MATCH($D32,'Paramètres'!$M:$M,0))&"",""))),0,IF(OR(IFERROR(INDEX('Paramètres'!$I:$I,MATCH($C32,'Paramètres'!$D:$D,0))&"","")="Les deux",IFERROR(INDEX('Paramètres'!$I:$I,MATCH($C32,'Paramètres'!$D:$D,0))&"","")=IF($P32=1,"Débit",$L32)),-IF($P32=1,-$K32,$K32),0)))) -> 0 | U32: =IF($K32="","",IF(ISNUMBER(SEARCH("sortie-epargne",IFERROR(INDEX('Paramètres'!$N:$N,MATCH($D32,'Paramètres'!$M:$M,0))&"",""))),$K32,0)) -> 0 | V32: =IF(AND($A32<>"",$O32=1,$L32="Débit",N($Q32)>0,$A32>=Visualisation!$B$1,$A32<Visualisation!$D$1),MAX($V$1:V31)+1,"")
A33: 45558 | B33: Achat carte | C33: Banque B - Compte joint | D33: courses | E33: 131.6 | G33: Boulangerie | I33: Rocheville | K33: =IF($E33="","",ROUND($E33*IF(ISNA(MATCH($C33,'Paramètres'!$D:$D,0)),1,IF(INDEX('Paramètres'!$J:$J,MATCH($C33,'Paramètres'!$D:$D,0))="",1,INDEX('Paramètres'!$J:$J,MATCH($C33,'Paramètres'!$D:$D,0)))),2)) -> 65.8 | L33: =IF($D33="","",IF($F33<>"",$F33,IF(ISNA(MATCH($D33,'Paramètres'!$M:$M,0)),"⚠ Type inconnu",IFERROR(INDEX('Paramètres'!$P:$P,MATCH($D33,'Paramètres'!$M:$M,0))&"","")))) -> Débit | M33: =IF($D33="","",IF(ISNA(MATCH($D33,'Paramètres'!$M:$M,0)),"⚠ Type inconnu",IF($L33="Crédit","",IFERROR(INDEX('Paramètres'!$O:$O,MATCH($D33,'Paramètres'!$M:$M,0))&"","")))) -> Dépense Courante | N33: =IF($D33="","",IFERROR(INDEX('Paramètres'!$Q:$Q,MATCH($D33,'Paramètres'!$M:$M,0))&"","")) -> Alimentation | O33: =IF($A33="","",IF(OR($J33<>"x",$A33<=FinReleve),1,0)) -> 1 | P33: =IF($D33="","",IF(AND($L33="Crédit",OR(IFERROR(INDEX('Paramètres'!$O:$O,MATCH($D33,'Paramètres'!$M:$M,0))&"","")<>"",ISNUMBER(SEARCH("remboursement",IFERROR(INDEX('Paramètres'!$N:$N,MATCH($D33,'Paramètres'!$M:$M,0))&"",""))))),1,0)) -> 0 | Q33: =IF($K33="","",IF(ISNUMBER(SEARCH("transfert-interne",IFERROR(INDEX('Paramètres'!$N:$N,MATCH($D33,'Paramètres'!$M:$M,0))&"",""))),0,IF($L33="Débit",$K33,IF($P33=1,-$K33,0)))) -> 65.8 | R33: =IF($K33="","",IF($L33="Crédit",$K33,-$K33)) -> -65.8 | S33: =IF($C33="","",IFERROR(INDEX('Paramètres'!$H:$H,MATCH($C33,'Paramètres'!$D:$D,0))&"","")) -> Banque A - Courant | T33: =IF($K33="","",IF($S33="",0,IF(ISNUMBER(SEARCH("apport-exterieur",IFERROR(INDEX('Paramètres'!$N:$N,MATCH($D33,'Paramètres'!$M:$M,0))&"",""))),0,IF(OR(IFERROR(INDEX('Paramètres'!$I:$I,MATCH($C33,'Paramètres'!$D:$D,0))&"","")="Les deux",IFERROR(INDEX('Paramètres'!$I:$I,MATCH($C33,'Paramètres'!$D:$D,0))&"","")=IF($P33=1,"Débit",$L33)),-IF($P33=1,-$K33,$K33),0)))) -> 0 | U33: =IF($K33="","",IF(ISNUMBER(SEARCH("sortie-epargne",IFERROR(INDEX('Paramètres'!$N:$N,MATCH($D33,'Paramètres'!$M:$M,0))&"",""))),$K33,0)) -> 0 | V33: =IF(AND($A33<>"",$O33=1,$L33="Débit",N($Q33)>0,$A33>=Visualisation!$B$1,$A33<Visualisation!$D$1),MAX($V$1:V32)+1,"")
A34: 45558 | B34: Carburant | C34: Banque A - Courant | D34: Essence | E34: 58.69 | G34: Transport urbain | I34: Grandval | K34: =IF($E34="","",ROUND($E34*IF(ISNA(MATCH($C34,'Paramètres'!$D:$D,0)),1,IF(INDEX('Paramètres'!$J:$J,MATCH($C34,'Paramètres'!$D:$D,0))="",1,INDEX('Paramètres'!$J:$J,MATCH($C34,'Paramètres'!$D:$D,0)))),2)) -> 58.69 | L34: =IF($D34="","",IF($F34<>"",$F34,IF(ISNA(MATCH($D34,'Paramètres'!$M:$M,0)),"⚠ Type inconnu",IFERROR(INDEX('Paramètres'!$P:$P,MATCH($D34,'Paramètres'!$M:$M,0))&"","")))) -> Débit | M34: =IF($D34="","",IF(ISNA(MATCH($D34,'Paramètres'!$M:$M,0)),"⚠ Type inconnu",IF($L34="Crédit","",IFERROR(INDEX('Paramètres'!$O:$O,MATCH($D34,'Paramètres'!$M:$M,0))&"","")))) -> Dépense Courante | N34: =IF($D34="","",IFERROR(INDEX('Paramètres'!$Q:$Q,MATCH($D34,'Paramètres'!$M:$M,0))&"","")) -> Transport | O34: =IF($A34="","",IF(OR($J34<>"x",$A34<=FinReleve),1,0)) -> 1 | P34: =IF($D34="","",IF(AND($L34="Crédit",OR(IFERROR(INDEX('Paramètres'!$O:$O,MATCH($D34,'Paramètres'!$M:$M,0))&"","")<>"",ISNUMBER(SEARCH("remboursement",IFERROR(INDEX('Paramètres'!$N:$N,MATCH($D34,'Paramètres'!$M:$M,0))&"",""))))),1,0)) -> 0 | Q34: =IF($K34="","",IF(ISNUMBER(SEARCH("transfert-interne",IFERROR(INDEX('Paramètres'!$N:$N,MATCH($D34,'Paramètres'!$M:$M,0))&"",""))),0,IF($L34="Débit",$K34,IF($P34=1,-$K34,0)))) -> 58.69 | R34: =IF($K34="","",IF($L34="Crédit",$K34,-$K34)) -> -58.69 | S34: =IF($C34="","",IFERROR(INDEX('Paramètres'!$H:$H,MATCH($C34,'Paramètres'!$D:$D,0))&"","")) | T34: =IF($K34="","",IF($S34="",0,IF(ISNUMBER(SEARCH("apport-exterieur",IFERROR(INDEX('Paramètres'!$N:$N,MATCH($D34,'Paramètres'!$M:$M,0))&"",""))),0,IF(OR(IFERROR(INDEX('Paramètres'!$I:$I,MATCH($C34,'Paramètres'!$D:$D,0))&"","")="Les deux",IFERROR(INDEX('Paramètres'!$I:$I,MATCH($C34,'Paramètres'!$D:$D,0))&"","")=IF($P34=1,"Débit",$L34)),-IF($P34=1,-$K34,$K34),0)))) -> 0 | U34: =IF($K34="","",IF(ISNUMBER(SEARCH("sortie-epargne",IFERROR(INDEX('Paramètres'!$N:$N,MATCH($D34,'Paramètres'!$M:$M,0))&"",""))),$K34,0)) -> 0 | V34: =IF(AND($A34<>"",$O34=1,$L34="Débit",N($Q34)>0,$A34>=Visualisation!$B$1,$A34<Visualisation!$D$1),MAX($V$1:V33)+1,"")
A35: 45558 | B35: Virement épargne | C35: Banque A - Courant | D35: Epargne Banque B | E35: 96.79 | K35: =IF($E35="","",ROUND($E35*IF(ISNA(MATCH($C35,'Paramètres'!$D:$D,0)),1,IF(INDEX('Paramètres'!$J:$J,MATCH($C35,'Paramètres'!$D:$D,0))="",1,INDEX('Paramètres'!$J:$J,MATCH($C35,'Paramètres'!$D:$D,0)))),2)) -> 96.79 | L35: =IF($D35="","",IF($F35<>"",$F35,IF(ISNA(MATCH($D35,'Paramètres'!$M:$M,0)),"⚠ Type inconnu",IFERROR(INDEX('Paramètres'!$P:$P,MATCH($D35,'Paramètres'!$M:$M,0))&"","")))) -> Débit | M35: =IF($D35="","",IF(ISNA(MATCH($D35,'Paramètres'!$M:$M,0)),"⚠ Type inconnu",IF($L35="Crédit","",IFERROR(INDEX('Paramètres'!$O:$O,MATCH($D35,'Paramètres'!$M:$M,0))&"","")))) | N35: =IF($D35="","",IFERROR(INDEX('Paramètres'!$Q:$Q,MATCH($D35,'Paramètres'!$M:$M,0))&"","")) -> Comptes Bancaires | O35: =IF($A35="","",IF(OR($J35<>"x",$A35<=FinReleve),1,0)) -> 1 | P35: =IF($D35="","",IF(AND($L35="Crédit",OR(IFERROR(INDEX('Paramètres'!$O:$O,MATCH($D35,'Paramètres'!$M:$M,0))&"","")<>"",ISNUMBER(SEARCH("remboursement",IFERROR(INDEX('Paramètres'!$N:$N,MATCH($D35,'Paramètres'!$M:$M,0))&"",""))))),1,0)) -> 0 | Q35: =IF($K35="","",IF(ISNUMBER(SEARCH("transfert-interne",IFERROR(INDEX('Paramètres'!$N:$N,MATCH($D35,'Paramètres'!$M:$M,0))&"",""))),0,IF($L35="Débit",$K35,IF($P35=1,-$K35,0)))) -> 96.79 | R35: =IF($K35="","",IF($L35="Crédit",$K35,-$K35)) -> -96.79 | S35: =IF($C35="","",IFERROR(INDEX('Paramètres'!$H:$H,MATCH($C35,'Paramètres'!$D:$D,0))&"","")) | T35: =IF($K35="","",IF($S35="",0,IF(ISNUMBER(SEARCH("apport-exterieur",IFERROR(INDEX('Paramètres'!$N:$N,MATCH($D35,'Paramètres'!$M:$M,0))&"",""))),0,IF(OR(IFERROR(INDEX('Paramètres'!$I:$I,MATCH($C35,'Paramètres'!$D:$D,0))&"","")="Les deux",IFERROR(INDEX('Paramètres'!$I:$I,MATCH($C35,'Paramètres'!$D:$D,0))&"","")=IF($P35=1,"Débit",$L35)),-IF($P35=1,-$K35,$K35),0)))) -> 0 | U35: =IF($K35="","",IF(ISNUMBER(SEARCH("sortie-epargne",IFERROR(INDEX('Paramètres'!$N:$N,MATCH($D35,'Paramètres'!$M:$M,0))&"",""))),$K35,0)) -> 0 | V35: =IF(AND($A35<>"",$O35=1,$L35="Débit",N($Q35)>0,$A35>=Visualisation!$B$1,$A35<Visualisation!$D$1),MAX($V$1:V34)+1,"")
A36: 45559 | B36: Achat carte | C36: Banque B - Courant | D36: CB | E36: 60.9 | G36: Pressing | I36: Rocheville | K36: =IF($E36="","",ROUND($E36*IF(ISNA(MATCH($C36,'Paramètres'!$D:$D,0)),1,IF(INDEX('Paramètres'!$J:$J,MATCH($C36,'Paramètres'!$D:$D,0))="",1,INDEX('Paramètres'!$J:$J,MATCH($C36,'Paramètres'!$D:$D,0)))),2)) -> 60.9 | L36: =IF($D36="","",IF($F36<>"",$F36,IF(ISNA(MATCH($D36,'Paramètres'!$M:$M,0)),"⚠ Type inconnu",IFERROR(INDEX('Paramètres'!$P:$P,MATCH($D36,'Paramètres'!$M:$M,0))&"","")))) -> Débit | M36: =IF($D36="","",IF(ISNA(MATCH($D36,'Paramètres'!$M:$M,0)),"⚠ Type inconnu",IF($L36="Crédit","",IFERROR(INDEX('Paramètres'!$O:$O,MATCH($D36,'Paramètres'!$M:$M,0))&"","")))) -> Dépense Occasionnelle | N36: =IF($D36="","",IFERROR(INDEX('Paramètres'!$Q:$Q,MATCH($D36,'Paramètres'!$M:$M,0))&"","")) -> Autre | O36: =IF($A36="","",IF(OR($J36<>"x",$A36<=FinReleve),1,0)) -> 1 | P36: =IF($D36="","",IF(AND($L36="Crédit",OR(IFERROR(INDEX('Paramètres'!$O:$O,MATCH($D36,'Paramètres'!$M:$M,0))&"","")<>"",ISNUMBER(SEARCH("remboursement",IFERROR(INDEX('Paramètres'!$N:$N,MATCH($D36,'Paramètres'!$M:$M,0))&"",""))))),1,0)) -> 0 | Q36: =IF($K36="","",IF(ISNUMBER(SEARCH("transfert-interne",IFERROR(INDEX('Paramètres'!$N:$N,MATCH($D36,'Paramètres'!$M:$M,0))&"",""))),0,IF($L36="Débit",$K36,IF($P36=1,-$K36,0)))) -> 60.9 | R36: =IF($K36="","",IF($L36="Crédit",$K36,-$K36)) -> -60.9 | S36: =IF($C36="","",IFERROR(INDEX('Paramètres'!$H:$H,MATCH($C36,'Paramètres'!$D:$D,0))&"","")) | T36: =IF($K36="","",IF($S36="",0,IF(ISNUMBER(SEARCH("apport-exterieur",IFERROR(INDEX('Paramètres'!$N:$N,MATCH($D36,'Paramètres'!$M:$M,0))&"",""))),0,IF(OR(IFERROR(INDEX('Paramètres'!$I:$I,MATCH($C36,'Paramètres'!$D:$D,0))&"","")="Les deux",IFERROR(INDEX('Paramètres'!$I:$I,MATCH($C36,'Paramètres'!$D:$D,0))&"","")=IF($P36=1,"Débit",$L36)),-IF($P36=1,-$K36,$K36),0)))) -> 0 | U36: =IF($K36="","",IF(ISNUMBER(SEARCH("sortie-epargne",IFERROR(INDEX('Paramètres'!$N:$N,MATCH($D36,'Paramètres'!$M:$M,0))&"",""))),$K36,0)) -> 0 | V36: =IF(AND($A36<>"",$O36=1,$L36="Débit",N($Q36)>0,$A36>=Visualisation!$B$1,$A36<Visualisation!$D$1),MAX($V$1:V35)+1,"")
A37: 45561 | B37: Virement épargne | C37: Banque A - Courant | D37: Epargne Banque A | E37: 150 | K37: =IF($E37="","",ROUND($E37*IF(ISNA(MATCH($C37,'Paramètres'!$D:$D,0)),1,IF(INDEX('Paramètres'!$J:$J,MATCH($C37,'Paramètres'!$D:$D,0))="",1,INDEX('Paramètres'!$J:$J,MATCH($C37,'Paramètres'!$D:$D,0)))),2)) -> 150 | L37: =IF($D37="","",IF($F37<>"",$F37,IF(ISNA(MATCH($D37,'Paramètres'!$M:$M,0)),"⚠ Type inconnu",IFERROR(INDEX('Paramètres'!$P:$P,MATCH($D37,'Paramètres'!$M:$M,0))&"","")))) -> Débit | M37: =IF($D37="","",IF(ISNA(MATCH($D37,'Paramètres'!$M:$M,0)),"⚠ Type inconnu",IF($L37="Crédit","",IFERROR(INDEX('Paramètres'!$O:$O,MATCH($D37,'Paramètres'!$M:$M,0))&"","")))) | N37: =IF($D37="","",IFERROR(INDEX('Paramètres'!$Q:$Q,MATCH($D37,'Paramètres'!$M:$M,0))&"","")) -> Comptes Bancaires | O37: =IF($A37="","",IF(OR($J37<>"x",$A37<=FinReleve),1,0)) -> 1 | P37: =IF($D37="","",IF(AND($L37="Crédit",OR(IFERROR(INDEX('Paramètres'!$O:$O,MATCH($D37,'Paramètres'!$M:$M,0))&"","")<>"",ISNUMBER(SEARCH("remboursement",IFERROR(INDEX('Paramètres'!$N:$N,MATCH($D37,'Paramètres'!$M:$M,0))&"",""))))),1,0)) -> 0 | Q37: =IF($K37="","",IF(ISNUMBER(SEARCH("transfert-interne",IFERROR(INDEX('Paramètres'!$N:$N,MATCH($D37,'Paramètres'!$M:$M,0))&"",""))),0,IF($L37="Débit",$K37,IF($P37=1,-$K37,0)))) -> 0 | R37: =IF($K37="","",IF($L37="Crédit",$K37,-$K37)) -> -150 | S37: =IF($C37="","",IFERROR(INDEX('Paramètres'!$H:$H,MATCH($C37,'Paramètres'!$D:$D,0))&"","")) | T37: =IF($K37="","",IF($S37="",0,IF(ISNUMBER(SEARCH("apport-exterieur",IFERROR(INDEX('Paramètres'!$N:$N,MATCH($D37,'Paramètres'!$M:$M,0))&"",""))),0,IF(OR(IFERROR(INDEX('Paramètres'!$I:$I,MATCH($C37,'Paramètres'!$D:$D,0))&"","")="Les deux",IFERROR(INDEX('Paramètres'!$I:$I,MATCH($C37,'Paramètres'!$D:$D,0))&"","")=IF($P37=1,"Débit",$L37)),-IF($P37=1,-$K37,$K37),0)))) -> 0 | U37: =IF($K37="","",IF(ISNUMBER(SEARCH("sortie-epargne",IFERROR(INDEX('Paramètres'!$N:$N,MATCH($D37,'Paramètres'!$M:$M,0))&"",""))),$K37,0)) -> 0 | V37: =IF(AND($A37<>"",$O37=1,$L37="Débit",N($Q37)>0,$A37>=Visualisation!$B$1,$A37<Visualisation!$D$1),MAX($V$1:V36)+1,"")
A38: 45561 | B38: Virement épargne | C38: Banque A - Courant | D38: Epargne Banque C | E38: 200 | K38: =IF($E38="","",ROUND($E38*IF(ISNA(MATCH($C38,'Paramètres'!$D:$D,0)),1,IF(INDEX('Paramètres'!$J:$J,MATCH($C38,'Paramètres'!$D:$D,0))="",1,INDEX('Paramètres'!$J:$J,MATCH($C38,'Paramètres'!$D:$D,0)))),2)) -> 200 | L38: =IF($D38="","",IF($F38<>"",$F38,IF(ISNA(MATCH($D38,'Paramètres'!$M:$M,0)),"⚠ Type inconnu",IFERROR(INDEX('Paramètres'!$P:$P,MATCH($D38,'Paramètres'!$M:$M,0))&"","")))) -> Débit | M38: =IF($D38="","",IF(ISNA(MATCH($D38,'Paramètres'!$M:$M,0)),"⚠ Type inconnu",IF($L38="Crédit","",IFERROR(INDEX('Paramètres'!$O:$O,MATCH($D38,'Paramètres'!$M:$M,0))&"","")))) | N38: =IF($D38="","",IFERROR(INDEX('Paramètres'!$Q:$Q,MATCH($D38,'Paramètres'!$M:$M,0))&"","")) -> Comptes Bancaires | O38: =IF($A38="","",IF(OR($J38<>"x",$A38<=FinReleve),1,0)) -> 1 | P38: =IF($D38="","",IF(AND($L38="Crédit",OR(IFERROR(INDEX('Paramètres'!$O:$O,MATCH($D38,'Paramètres'!$M:$M,0))&"","")<>"",ISNUMBER(SEARCH("remboursement",IFERROR(INDEX('Paramètres'!$N:$N,MATCH($D38,'Paramètres'!$M:$M,0))&"",""))))),1,0)) -> 0 | Q38: =IF($K38="","",IF(ISNUMBER(SEARCH("transfert-interne",IFERROR(INDEX('Paramètres'!$N:$N,MATCH($D38,'Paramètres'!$M:$M,0))&"",""))),0,IF($L38="Débit",$K38,IF($P38=1,-$K38,0)))) -> 200 | R38: =IF($K38="","",IF($L38="Crédit",$K38,-$K38)) -> -200 | S38: =IF($C38="","",IFERROR(INDEX('Paramètres'!$H:$H,MATCH($C38,'Paramètres'!$D:$D,0))&"","")) | T38: =IF($K38="","",IF($S38="",0,IF(ISNUMBER(SEARCH("apport-exterieur",IFERROR(INDEX('Paramètres'!$N:$N,MATCH($D38,'Paramètres'!$M:$M,0))&"",""))),0,IF(OR(IFERROR(INDEX('Paramètres'!$I:$I,MATCH($C38,'Paramètres'!$D:$D,0))&"","")="Les deux",IFERROR(INDEX('Paramètres'!$I:$I,MATCH($C38,'Paramètres'!$D:$D,0))&"","")=IF($P38=1,"Débit",$L38)),-IF($P38=1,-$K38,$K38),0)))) -> 0 | U38: =IF($K38="","",IF(ISNUMBER(SEARCH("sortie-epargne",IFERROR(INDEX('Paramètres'!$N:$N,MATCH($D38,'Paramètres'!$M:$M,0))&"",""))),$K38,0)) -> 0 | V38: =IF(AND($A38<>"",$O38=1,$L38="Débit",N($Q38)>0,$A38>=Visualisation!$B$1,$A38<Visualisation!$D$1),MAX($V$1:V37)+1,"")
A39: 45561 | B39: Versement assurance-vie | C39: Banque A - Courant | D39: Assurance-vie | E39: 120 | K39: =IF($E39="","",ROUND($E39*IF(ISNA(MATCH($C39,'Paramètres'!$D:$D,0)),1,IF(INDEX('Paramètres'!$J:$J,MATCH($C39,'Paramètres'!$D:$D,0))="",1,INDEX('Paramètres'!$J:$J,MATCH($C39,'Paramètres'!$D:$D,0)))),2)) -> 120 | L39: =IF($D39="","",IF($F39<>"",$F39,IF(ISNA(MATCH($D39,'Paramètres'!$M:$M,0)),"⚠ Type inconnu",IFERROR(INDEX('Paramètres'!$P:$P,MATCH($D39,'Paramètres'!$M:$M,0))&"","")))) -> Débit | M39: =IF($D39="","",IF(ISNA(MATCH($D39,'Paramètres'!$M:$M,0)),"⚠ Type inconnu",IF($L39="Crédit","",IFERROR(INDEX('Paramètres'!$O:$O,MATCH($D39,'Paramètres'!$M:$M,0))&"","")))) | N39: =IF($D39="","",IFERROR(INDEX('Paramètres'!$Q:$Q,MATCH($D39,'Paramètres'!$M:$M,0))&"","")) -> Comptes Bancaires | O39: =IF($A39="","",IF(OR($J39<>"x",$A39<=FinReleve),1,0)) -> 1 | P39: =IF($D39="","",IF(AND($L39="Crédit",OR(IFERROR(INDEX('Paramètres'!$O:$O,MATCH($D39,'Paramètres'!$M:$M,0))&"","")<>"",ISNUMBER(SEARCH("remboursement",IFERROR(INDEX('Paramètres'!$N:$N,MATCH($D39,'Paramètres'!$M:$M,0))&"",""))))),1,0)) -> 0 | Q39: =IF($K39="","",IF(ISNUMBER(SEARCH("transfert-interne",IFERROR(INDEX('Paramètres'!$N:$N,MATCH($D39,'Paramètres'!$M:$M,0))&"",""))),0,IF($L39="Débit",$K39,IF($P39=1,-$K39,0)))) -> 120 | R39: =IF($K39="","",IF($L39="Crédit",$K39,-$K39)) -> -120 | S39: =IF($C39="","",IFERROR(INDEX('Paramètres'!$H:$H,MATCH($C39,'Paramètres'!$D:$D,0))&"","")) | T39: =IF($K39="","",IF($S39="",0,IF(ISNUMBER(SEARCH("apport-exterieur",IFERROR(INDEX('Paramètres'!$N:$N,MATCH($D39,'Paramètres'!$M:$M,0))&"",""))),0,IF(OR(IFERROR(INDEX('Paramètres'!$I:$I,MATCH($C39,'Paramètres'!$D:$D,0))&"","")="Les deux",IFERROR(INDEX('Paramètres'!$I:$I,MATCH($C39,'Paramètres'!$D:$D,0))&"","")=IF($P39=1,"Débit",$L39)),-IF($P39=1,-$K39,$K39),0)))) -> 0 | U39: =IF($K39="","",IF(ISNUMBER(SEARCH("sortie-epargne",IFERROR(INDEX('Paramètres'!$N:$N,MATCH($D39,'Paramètres'!$M:$M,0))&"",""))),$K39,0)) -> 0 | V39: =IF(AND($A39<>"",$O39=1,$L39="Débit",N($Q39)>0,$A39>=Visualisation!$B$1,$A39<Visualisation!$D$1),MAX($V$1:V38)+1,"")
A40: 45562 | B40: Virement salaire | C40: Banque A - Courant | D40: Salaire | E40: 2931.02 | G40: Salaire | K40: =IF($E40="","",ROUND($E40*IF(ISNA(MATCH($C40,'Paramètres'!$D:$D,0)),1,IF(INDEX('Paramètres'!$J:$J,MATCH($C40,'Paramètres'!$D:$D,0))="",1,INDEX('Paramètres'!$J:$J,MATCH($C40,'Paramètres'!$D:$D,0)))),2)) -> 2931.02 | L40: =IF($D40="","",IF($F40<>"",$F40,IF(ISNA(MATCH($D40,'Paramètres'!$M:$M,0)),"⚠ Type inconnu",IFERROR(INDEX('Paramètres'!$P:$P,MATCH($D40,'Paramètres'!$M:$M,0))&"","")))) -> Crédit | M40: =IF($D40="","",IF(ISNA(MATCH($D40,'Paramètres'!$M:$M,0)),"⚠ Type inconnu",IF($L40="Crédit","",IFERROR(INDEX('Paramètres'!$O:$O,MATCH($D40,'Paramètres'!$M:$M,0))&"","")))) | N40: =IF($D40="","",IFERROR(INDEX('Paramètres'!$Q:$Q,MATCH($D40,'Paramètres'!$M:$M,0))&"","")) | O40: =IF($A40="","",IF(OR($J40<>"x",$A40<=FinReleve),1,0)) -> 1 | P40: =IF($D40="","",IF(AND($L40="Crédit",OR(IFERROR(INDEX('Paramètres'!$O:$O,MATCH($D40,'Paramètres'!$M:$M,0))&"","")<>"",ISNUMBER(SEARCH("remboursement",IFERROR(INDEX('Paramètres'!$N:$N,MATCH($D40,'Paramètres'!$M:$M,0))&"",""))))),1,0)) -> 0 | Q40: =IF($K40="","",IF(ISNUMBER(SEARCH("transfert-interne",IFERROR(INDEX('Paramètres'!$N:$N,MATCH($D40,'Paramètres'!$M:$M,0))&"",""))),0,IF($L40="Débit",$K40,IF($P40=1,-$K40,0)))) -> 0 | R40: =IF($K40="","",IF($L40="Crédit",$K40,-$K40)) -> 2931.02 | S40: =IF($C40="","",IFERROR(INDEX('Paramètres'!$H:$H,MATCH($C40,'Paramètres'!$D:$D,0))&"","")) | T40: =IF($K40="","",IF($S40="",0,IF(ISNUMBER(SEARCH("apport-exterieur",IFERROR(INDEX('Paramètres'!$N:$N,MATCH($D40,'Paramètres'!$M:$M,0))&"",""))),0,IF(OR(IFERROR(INDEX('Paramètres'!$I:$I,MATCH($C40,'Paramètres'!$D:$D,0))&"","")="Les deux",IFERROR(INDEX('Paramètres'!$I:$I,MATCH($C40,'Paramètres'!$D:$D,0))&"","")=IF($P40=1,"Débit",$L40)),-IF($P40=1,-$K40,$K40),0)))) -> 0 | U40: =IF($K40="","",IF(ISNUMBER(SEARCH("sortie-epargne",IFERROR(INDEX('Paramètres'!$N:$N,MATCH($D40,'Paramètres'!$M:$M,0))&"",""))),$K40,0)) -> 0 | V40: =IF(AND($A40<>"",$O40=1,$L40="Débit",N($Q40)>0,$A40>=Visualisation!$B$1,$A40<Visualisation!$D$1),MAX($V$1:V39)+1,"")
A41: 45562 | B41: Achat carte | C41: Banque A - Part commune | D41: courses | E41: 142.96 | G41: Supermarché Centre | I41: Villebourg | K41: =IF($E41="","",ROUND($E41*IF(ISNA(MATCH($C41,'Paramètres'!$D:$D,0)),1,IF(INDEX('Paramètres'!$J:$J,MATCH($C41,'Paramètres'!$D:$D,0))="",1,INDEX('Paramètres'!$J:$J,MATCH($C41,'Paramètres'!$D:$D,0)))),2)) -> 71.48 | L41: =IF($D41="","",IF($F41<>"",$F41,IF(ISNA(MATCH($D41,'Paramètres'!$M:$M,0)),"⚠ Type inconnu",IFERROR(INDEX('Paramètres'!$P:$P,MATCH($D41,'Paramètres'!$M:$M,0))&"","")))) -> Débit | M41: =IF($D41="","",IF(ISNA(MATCH($D41,'Paramètres'!$M:$M,0)),"⚠ Type inconnu",IF($L41="Crédit","",IFERROR(INDEX('Paramètres'!$O:$O,MATCH($D41,'Paramètres'!$M:$M,0))&"","")))) -> Dépense Courante | N41: =IF($D41="","",IFERROR(INDEX('Paramètres'!$Q:$Q,MATCH($D41,'Paramètres'!$M:$M,0))&"","")) -> Alimentation | O41: =IF($A41="","",IF(OR($J41<>"x",$A41<=FinReleve),1,0)) -> 1 | P41: =IF($D41="","",IF(AND($L41="Crédit",OR(IFERROR(INDEX('Paramètres'!$O:$O,MATCH($D41,'Paramètres'!$M:$M,0))&"","")<>"",ISNUMBER(SEARCH("remboursement",IFERROR(INDEX('Paramètres'!$N:$N,MATCH($D41,'Paramètres'!$M:$M,0))&"",""))))),1,0)) -> 0 | Q41: =IF($K41="","",IF(ISNUMBER(SEARCH("transfert-interne",IFERROR(INDEX('Paramètres'!$N:$N,MATCH($D41,'Paramètres'!$M:$M,0))&"",""))),0,IF($L41="Débit",$K41,IF($P41=1,-$K41,0)))) -> 71.48 | R41: =IF($K41="","",IF($L41="Crédit",$K41,-$K41)) -> -71.48 | S41: =IF($C41="","",IFERROR(INDEX('Paramètres'!$H:$H,MATCH($C41,'Paramètres'!$D:$D,0))&"","")) -> Banque A - Courant | T41: =IF($K41="","",IF($S41="",0,IF(ISNUMBER(SEARCH("apport-exterieur",IFERROR(INDEX('Paramètres'!$N:$N,MATCH($D41,'Paramètres'!$M:$M,0))&"",""))),0,IF(OR(IFERROR(INDEX('Paramètres'!$I:$I,MATCH($C41,'Paramètres'!$D:$D,0))&"","")="Les deux",IFERROR(INDEX('Paramètres'!$I:$I,MATCH($C41,'Paramètres'!$D:$D,0))&"","")=IF($P41=1,"Débit",$L41)),-IF($P41=1,-$K41,$K41),0)))) -> -71.48 | U41: =IF($K41="","",IF(ISNUMBER(SEARCH("sortie-epargne",IFERROR(INDEX('Paramètres'!$N:$N,MATCH($D41,'Paramètres'!$M:$M,0))&"",""))),$K41,0)) -> 0 | V41: =IF(AND($A41<>"",$O41=1,$L41="Débit",N($Q41)>0,$A41>=Visualisation!$B$1,$A41<Visualisation!$D$1),MAX($V$1:V40)+1,"")
A42: 45562 | B42: Titre restaurant | C42: Titres-restaurant | D42: cantine | E42: 10 | G42: Cantine | I42: Villebourg-sur-Rive | K42: =IF($E42="","",ROUND($E42*IF(ISNA(MATCH($C42,'Paramètres'!$D:$D,0)),1,IF(INDEX('Paramètres'!$J:$J,MATCH($C42,'Paramètres'!$D:$D,0))="",1,INDEX('Paramètres'!$J:$J,MATCH($C42,'Paramètres'!$D:$D,0)))),2)) -> 10 | L42: =IF($D42="","",IF($F42<>"",$F42,IF(ISNA(MATCH($D42,'Paramètres'!$M:$M,0)),"⚠ Type inconnu",IFERROR(INDEX('Paramètres'!$P:$P,MATCH($D42,'Paramètres'!$M:$M,0))&"","")))) -> Débit | M42: =IF($D42="","",IF(ISNA(MATCH($D42,'Paramètres'!$M:$M,0)),"⚠ Type inconnu",IF($L42="Crédit","",IFERROR(INDEX('Paramètres'!$O:$O,MATCH($D42,'Paramètres'!$M:$M,0))&"","")))) -> Dépense Courante | N42: =IF($D42="","",IFERROR(INDEX('Paramètres'!$Q:$Q,MATCH($D42,'Paramètres'!$M:$M,0))&"","")) -> Alimentation | O42: =IF($A42="","",IF(OR($J42<>"x",$A42<=FinReleve),1,0)) -> 1 | P42: =IF($D42="","",IF(AND($L42="Crédit",OR(IFERROR(INDEX('Paramètres'!$O:$O,MATCH($D42,'Paramètres'!$M:$M,0))&"","")<>"",ISNUMBER(SEARCH("remboursement",IFERROR(INDEX('Paramètres'!$N:$N,MATCH($D42,'Paramètres'!$M:$M,0))&"",""))))),1,0)) -> 0 | Q42: =IF($K42="","",IF(ISNUMBER(SEARCH("transfert-interne",IFERROR(INDEX('Paramètres'!$N:$N,MATCH($D42,'Paramètres'!$M:$M,0))&"",""))),0,IF($L42="Débit",$K42,IF($P42=1,-$K42,0)))) -> 10 | R42: =IF($K42="","",IF($L42="Crédit",$K42,-$K42)) -> -10 | S42: =IF($C42="","",IFERROR(INDEX('Paramètres'!$H:$H,MATCH($C42,'Paramètres'!$D:$D,0))&"","")) | T42: =IF($K42="","",IF($S42="",0,IF(ISNUMBER(SEARCH("apport-exterieur",IFERROR(INDEX('Paramètres'!$N:$N,MATCH($D42,'Paramètres'!$M:$M,0))&"",""))),0,IF(OR(IFERROR(INDEX('Paramètres'!$I:$I,MATCH($C42,'Paramètres'!$D:$D,0))&"","")="Les deux",IFERROR(INDEX('Paramètres'!$I:$I,MATCH($C42,'Paramètres'!$D:$D,0))&"","")=IF($P42=1,"Débit",$L42)),-IF($P42=1,-$K42,$K42),0)))) -> 0 | U42: =IF($K42="","",IF(ISNUMBER(SEARCH("sortie-epargne",IFERROR(INDEX('Paramètres'!$N:$N,MATCH($D42,'Paramètres'!$M:$M,0))&"",""))),$K42,0)) -> 0 | V42: =IF(AND($A42<>"",$O42=1,$L42="Débit",N($Q42)>0,$A42>=Visualisation!$B$1,$A42<Visualisation!$D$1),MAX($V$1:V41)+1,"")
A43: 45562 | B43: Équipement | C43: Banque A - Part commune | D43: Équipement | E43: 366.04 | G43: Jardinerie | K43: =IF($E43="","",ROUND($E43*IF(ISNA(MATCH($C43,'Paramètres'!$D:$D,0)),1,IF(INDEX('Paramètres'!$J:$J,MATCH($C43,'Paramètres'!$D:$D,0))="",1,INDEX('Paramètres'!$J:$J,MATCH($C43,'Paramètres'!$D:$D,0)))),2)) -> 183.02 | L43: =IF($D43="","",IF($F43<>"",$F43,IF(ISNA(MATCH($D43,'Paramètres'!$M:$M,0)),"⚠ Type inconnu",IFERROR(INDEX('Paramètres'!$P:$P,MATCH($D43,'Paramètres'!$M:$M,0))&"","")))) -> Débit | M43: =IF($D43="","",IF(ISNA(MATCH($D43,'Paramètres'!$M:$M,0)),"⚠ Type inconnu",IF($L43="Crédit","",IFERROR(INDEX('Paramètres'!$O:$O,MATCH($D43,'Paramètres'!$M:$M,0))&"","")))) -> Dépense Occasionnelle | N43: =IF($D43="","",IFERROR(INDEX('Paramètres'!$Q:$Q,MATCH($D43,'Paramètres'!$M:$M,0))&"","")) -> Autre | O43: =IF($A43="","",IF(OR($J43<>"x",$A43<=FinReleve),1,0)) -> 1 | P43: =IF($D43="","",IF(AND($L43="Crédit",OR(IFERROR(INDEX('Paramètres'!$O:$O,MATCH($D43,'Paramètres'!$M:$M,0))&"","")<>"",ISNUMBER(SEARCH("remboursement",IFERROR(INDEX('Paramètres'!$N:$N,MATCH($D43,'Paramètres'!$M:$M,0))&"",""))))),1,0)) -> 0 | Q43: =IF($K43="","",IF(ISNUMBER(SEARCH("transfert-interne",IFERROR(INDEX('Paramètres'!$N:$N,MATCH($D43,'Paramètres'!$M:$M,0))&"",""))),0,IF($L43="Débit",$K43,IF($P43=1,-$K43,0)))) -> 183.02 | R43: =IF($K43="","",IF($L43="Crédit",$K43,-$K43)) -> -183.02 | S43: =IF($C43="","",IFERROR(INDEX('Paramètres'!$H:$H,MATCH($C43,'Paramètres'!$D:$D,0))&"","")) -> Banque A - Courant | T43: =IF($K43="","",IF($S43="",0,IF(ISNUMBER(SEARCH("apport-exterieur",IFERROR(INDEX('Paramètres'!$N:$N,MATCH($D43,'Paramètres'!$M:$M,0))&"",""))),0,IF(OR(IFERROR(INDEX('Paramètres'!$I:$I,MATCH($C43,'Paramètres'!$D:$D,0))&"","")="Les deux",IFERROR(INDEX('Paramètres'!$I:$I,MATCH($C43,'Paramètres'!$D:$D,0))&"","")=IF($P43=1,"Débit",$L43)),-IF($P43=1,-$K43,$K43),0)))) -> -183.02 | U43: =IF($K43="","",IF(ISNUMBER(SEARCH("sortie-epargne",IFERROR(INDEX('Paramètres'!$N:$N,MATCH($D43,'Paramètres'!$M:$M,0))&"",""))),$K43,0)) -> 0 | V43: =IF(AND($A43<>"",$O43=1,$L43="Débit",N($Q43)>0,$A43>=Visualisation!$B$1,$A43<Visualisation!$D$1),MAX($V$1:V42)+1,"")
A44: 45563 | B44: Frais Bancaires | C44: Banque A - Courant | D44: Frais Bancaires | E44: 3 | K44: =IF($E44="","",ROUND($E44*IF(ISNA(MATCH($C44,'Paramètres'!$D:$D,0)),1,IF(INDEX('Paramètres'!$J:$J,MATCH($C44,'Paramètres'!$D:$D,0))="",1,INDEX('Paramètres'!$J:$J,MATCH($C44,'Paramètres'!$D:$D,0)))),2)) -> 3 | L44: =IF($D44="","",IF($F44<>"",$F44,IF(ISNA(MATCH($D44,'Paramètres'!$M:$M,0)),"⚠ Type inconnu",IFERROR(INDEX('Paramètres'!$P:$P,MATCH($D44,'Paramètres'!$M:$M,0))&"","")))) -> Débit | M44: =IF($D44="","",IF(ISNA(MATCH($D44,'Paramètres'!$M:$M,0)),"⚠ Type inconnu",IF($L44="Crédit","",IFERROR(INDEX('Paramètres'!$O:$O,MATCH($D44,'Paramètres'!$M:$M,0))&"","")))) -> Dépense Fixe | N44: =IF($D44="","",IFERROR(INDEX('Paramètres'!$Q:$Q,MATCH($D44,'Paramètres'!$M:$M,0))&"","")) -> Banque | O44: =IF($A44="","",IF(OR($J44<>"x",$A44<=FinReleve),1,0)) -> 1 | P44: =IF($D44="","",IF(AND($L44="Crédit",OR(IFERROR(INDEX('Paramètres'!$O:$O,MATCH($D44,'Paramètres'!$M:$M,0))&"","")<>"",ISNUMBER(SEARCH("remboursement",IFERROR(INDEX('Paramètres'!$N:$N,MATCH($D44,'Paramètres'!$M:$M,0))&"",""))))),1,0)) -> 0 | Q44: =IF($K44="","",IF(ISNUMBER(SEARCH("transfert-interne",IFERROR(INDEX('Paramètres'!$N:$N,MATCH($D44,'Paramètres'!$M:$M,0))&"",""))),0,IF($L44="Débit",$K44,IF($P44=1,-$K44,0)))) -> 3 | R44: =IF($K44="","",IF($L44="Crédit",$K44,-$K44)) -> -3 | S44: =IF($C44="","",IFERROR(INDEX('Paramètres'!$H:$H,MATCH($C44,'Paramètres'!$D:$D,0))&"","")) | T44: =IF($K44="","",IF($S44="",0,IF(ISNUMBER(SEARCH("apport-exterieur",IFERROR(INDEX('Paramètres'!$N:$N,MATCH($D44,'Paramètres'!$M:$M,0))&"",""))),0,IF(OR(IFERROR(INDEX('Paramètres'!$I:$I,MATCH($C44,'Paramètres'!$D:$D,0))&"","")="Les deux",IFERROR(INDEX('Paramètres'!$I:$I,MATCH($C44,'Paramètres'!$D:$D,0))&"","")=IF($P44=1,"Débit",$L44)),-IF($P44=1,-$K44,$K44),0)))) -> 0 | U44: =IF($K44="","",IF(ISNUMBER(SEARCH("sortie-epargne",IFERROR(INDEX('Paramètres'!$N:$N,MATCH($D44,'Paramètres'!$M:$M,0))&"",""))),$K44,0)) -> 0 | V44: =IF(AND($A44<>"",$O44=1,$L44="Débit",N($Q44)>0,$A44>=Visualisation!$B$1,$A44<Visualisation!$D$1),MAX($V$1:V43)+1,"")
A45: 45566 | B45: Titre restaurant | C45: Titres-restaurant | D45: cantine | E45: 8.25 | G45: Cantine | I45: Grandval | K45: =IF($E45="","",ROUND($E45*IF(ISNA(MATCH($C45,'Paramètres'!$D:$D,0)),1,IF(INDEX('Paramètres'!$J:$J,MATCH($C45,'Paramètres'!$D:$D,0))="",1,INDEX('Paramètres'!$J:$J,MATCH($C45,'Paramètres'!$D:$D,0)))),2)) -> 8.25 | L45: =IF($D45="","",IF($F45<>"",$F45,IF(ISNA(MATCH($D45,'Paramètres'!$M:$M,0)),"⚠ Type inconnu",IFERROR(INDEX('Paramètres'!$P:$P,MATCH($D45,'Paramètres'!$M:$M,0))&"","")))) -> Débit | M45: =IF($D45="","",IF(ISNA(MATCH($D45,'Paramètres'!$M:$M,0)),"⚠ Type inconnu",IF($L45="Crédit","",IFERROR(INDEX('Paramètres'!$O:$O,MATCH($D45,'Paramètres'!$M:$M,0))&"","")))) -> Dépense Courante | N45: =IF($D45="","",IFERROR(INDEX('Paramètres'!$Q:$Q,MATCH($D45,'Paramètres'!$M:$M,0))&"","")) -> Alimentation | O45: =IF($A45="","",IF(OR($J45<>"x",$A45<=FinReleve),1,0)) -> 1 | P45: =IF($D45="","",IF(AND($L45="Crédit",OR(IFERROR(INDEX('Paramètres'!$O:$O,MATCH($D45,'Paramètres'!$M:$M,0))&"","")<>"",ISNUMBER(SEARCH("remboursement",IFERROR(INDEX('Paramètres'!$N:$N,MATCH($D45,'Paramètres'!$M:$M,0))&"",""))))),1,0)) -> 0 | Q45: =IF($K45="","",IF(ISNUMBER(SEARCH("transfert-interne",IFERROR(INDEX('Paramètres'!$N:$N,MATCH($D45,'Paramètres'!$M:$M,0))&"",""))),0,IF($L45="Débit",$K45,IF($P45=1,-$K45,0)))) -> 8.25 | R45: =IF($K45="","",IF($L45="Crédit",$K45,-$K45)) -> -8.25 | S45: =IF($C45="","",IFERROR(INDEX('Paramètres'!$H:$H,MATCH($C45,'Paramètres'!$D:$D,0))&"","")) | T45: =IF($K45="","",IF($S45="",0,IF(ISNUMBER(SEARCH("apport-exterieur",IFERROR(INDEX('Paramètres'!$N:$N,MATCH($D45,'Paramètres'!$M:$M,0))&"",""))),0,IF(OR(IFERROR(INDEX('Paramètres'!$I:$I,MATCH($C45,'Paramètres'!$D:$D,0))&"","")="Les deux",IFERROR(INDEX('Paramètres'!$I:$I,MATCH($C45,'Paramètres'!$D:$D,0))&"","")=IF($P45=1,"Débit",$L45)),-IF($P45=1,-$K45,$K45),0)))) -> 0 | U45: =IF($K45="","",IF(ISNUMBER(SEARCH("sortie-epargne",IFERROR(INDEX('Paramètres'!$N:$N,MATCH($D45,'Paramètres'!$M:$M,0))&"",""))),$K45,0)) -> 0 | V45: =IF(AND($A45<>"",$O45=1,$L45="Débit",N($Q45)>0,$A45>=Visualisation!$B$1,$A45<Visualisation!$D$1),MAX($V$1:V44)+1,"")
A46: 45566 | B46: Carburant | C46: Banque A - Courant | D46: Essence | E46: 70.7 | G46: Transport urbain | I46: Villebourg-sur-Rive | K46: =IF($E46="","",ROUND($E46*IF(ISNA(MATCH($C46,'Paramètres'!$D:$D,0)),1,IF(INDEX('Paramètres'!$J:$J,MATCH($C46,'Paramètres'!$D:$D,0))="",1,INDEX('Paramètres'!$J:$J,MATCH($C46,'Paramètres'!$D:$D,0)))),2)) -> 70.7 | L46: =IF($D46="","",IF($F46<>"",$F46,IF(ISNA(MATCH($D46,'Paramètres'!$M:$M,0)),"⚠ Type inconnu",IFERROR(INDEX('Paramètres'!$P:$P,MATCH($D46,'Paramètres'!$M:$M,0))&"","")))) -> Débit | M46: =IF($D46="","",IF(ISNA(MATCH($D46,'Paramètres'!$M:$M,0)),"⚠ Type inconnu",IF($L46="Crédit","",IFERROR(INDEX('Paramètres'!$O:$O,MATCH($D46,'Paramètres'!$M:$M,0))&"","")))) -> Dépense Courante | N46: =IF($D46="","",IFERROR(INDEX('Paramètres'!$Q:$Q,MATCH($D46,'Paramètres'!$M:$M,0))&"","")) -> Transport | O46: =IF($A46="","",IF(OR($J46<>"x",$A46<=FinReleve),1,0)) -> 1 | P46: =IF($D46="","",IF(AND($L46="Crédit",OR(IFERROR(INDEX('Paramètres'!$O:$O,MATCH($D46,'Paramètres'!$M:$M,0))&"","")<>"",ISNUMBER(SEARCH("remboursement",IFERROR(INDEX('Paramètres'!$N:$N,MATCH($D46,'Paramètres'!$M:$M,0))&"",""))))),1,0)) -> 0 | Q46: =IF($K46="","",IF(ISNUMBER(SEARCH("transfert-interne",IFERROR(INDEX('Paramètres'!$N:$N,MATCH($D46,'Paramètres'!$M:$M,0))&"",""))),0,IF($L46="Débit",$K46,IF($P46=1,-$K46,0)))) -> 70.7 | R46: =IF($K46="","",IF($L46="Crédit",$K46,-$K46)) -> -70.7 | S46: =IF($C46="","",IFERROR(INDEX('Paramètres'!$H:$H,MATCH($C46,'Paramètres'!$D:$D,0))&"","")) | T46: =IF($K46="","",IF($S46="",0,IF(ISNUMBER(SEARCH("apport-exterieur",IFERROR(INDEX('Paramètres'!$N:$N,MATCH($D46,'Paramètres'!$M:$M,0))&"",""))),0,IF(OR(IFERROR(INDEX('Paramètres'!$I:$I,MATCH($C46,'Paramètres'!$D:$D,0))&"","")="Les deux",IFERROR(INDEX('Paramètres'!$I:$I,MATCH($C46,'Paramètres'!$D:$D,0))&"","")=IF($P46=1,"Débit",$L46)),-IF($P46=1,-$K46,$K46),0)))) -> 0 | U46: =IF($K46="","",IF(ISNUMBER(SEARCH("sortie-epargne",IFERROR(INDEX('Paramètres'!$N:$N,MATCH($D46,'Paramètres'!$M:$M,0))&"",""))),$K46,0)) -> 0 | V46: =IF(AND($A46<>"",$O46=1,$L46="Débit",N($Q46)>0,$A46>=Visualisation!$B$1,$A46<Visualisation!$D$1),MAX($V$1:V45)+1,"")
A47: 45567 | B47: Alimentation compte joint | C47: Banque C - Compte joint | D47: Transfert Banque A vers Banque C | E47: 1160 | K47: =IF($E47="","",ROUND($E47*IF(ISNA(MATCH($C47,'Paramètres'!$D:$D,0)),1,IF(INDEX('Paramètres'!$J:$J,MATCH($C47,'Paramètres'!$D:$D,0))="",1,INDEX('Paramètres'!$J:$J,MATCH($C47,'Paramètres'!$D:$D,0)))),2)) -> 1160 | L47: =IF($D47="","",IF($F47<>"",$F47,IF(ISNA(MATCH($D47,'Paramètres'!$M:$M,0)),"⚠ Type inconnu",IFERROR(INDEX('Paramètres'!$P:$P,MATCH($D47,'Paramètres'!$M:$M,0))&"","")))) -> Crédit | M47: =IF($D47="","",IF(ISNA(MATCH($D47,'Paramètres'!$M:$M,0)),"⚠ Type inconnu",IF($L47="Crédit","",IFERROR(INDEX('Paramètres'!$O:$O,MATCH($D47,'Paramètres'!$M:$M,0))&"","")))) | N47: =IF($D47="","",IFERROR(INDEX('Paramètres'!$Q:$Q,MATCH($D47,'Paramètres'!$M:$M,0))&"","")) -> Comptes Bancaires | O47: =IF($A47="","",IF(OR($J47<>"x",$A47<=FinReleve),1,0)) -> 1 | P47: =IF($D47="","",IF(AND($L47="Crédit",OR(IFERROR(INDEX('Paramètres'!$O:$O,MATCH($D47,'Paramètres'!$M:$M,0))&"","")<>"",ISNUMBER(SEARCH("remboursement",IFERROR(INDEX('Paramètres'!$N:$N,MATCH($D47,'Paramètres'!$M:$M,0))&"",""))))),1,0)) -> 0 | Q47: =IF($K47="","",IF(ISNUMBER(SEARCH("transfert-interne",IFERROR(INDEX('Paramètres'!$N:$N,MATCH($D47,'Paramètres'!$M:$M,0))&"",""))),0,IF($L47="Débit",$K47,IF($P47=1,-$K47,0)))) -> 0 | R47: =IF($K47="","",IF($L47="Crédit",$K47,-$K47)) -> 1160 | S47: =IF($C47="","",IFERROR(INDEX('Paramètres'!$H:$H,MATCH($C47,'Paramètres'!$D:$D,0))&"","")) -> Banque A - Courant | T47: =IF($K47="","",IF($S47="",0,IF(ISNUMBER(SEARCH("apport-exterieur",IFERROR(INDEX('Paramètres'!$N:$N,MATCH($D47,'Paramètres'!$M:$M,0))&"",""))),0,IF(OR(IFERROR(INDEX('Paramètres'!$I:$I,MATCH($C47,'Paramètres'!$D:$D,0))&"","")="Les deux",IFERROR(INDEX('Paramètres'!$I:$I,MATCH($C47,'Paramètres'!$D:$D,0))&"","")=IF($P47=1,"Débit",$L47)),-IF($P47=1,-$K47,$K47),0)))) -> -1160 | U47: =IF($K47="","",IF(ISNUMBER(SEARCH("sortie-epargne",IFERROR(INDEX('Paramètres'!$N:$N,MATCH($D47,'Paramètres'!$M:$M,0))&"",""))),$K47,0)) -> 0 | V47: =IF(AND($A47<>"",$O47=1,$L47="Débit",N($Q47)>0,$A47>=Visualisation!$B$1,$A47<Visualisation!$D$1),MAX($V$1:V46)+1,"")
A48: 45567 | B48: Alimentation compte joint | C48: Banque B - Compte joint | D48: Transfert Banque A vers Banque B | E48: 600 | K48: =IF($E48="","",ROUND($E48*IF(ISNA(MATCH($C48,'Paramètres'!$D:$D,0)),1,IF(INDEX('Paramètres'!$J:$J,MATCH($C48,'Paramètres'!$D:$D,0))="",1,INDEX('Paramètres'!$J:$J,MATCH($C48,'Paramètres'!$D:$D,0)))),2)) -> 300 | L48: =IF($D48="","",IF($F48<>"",$F48,IF(ISNA(MATCH($D48,'Paramètres'!$M:$M,0)),"⚠ Type inconnu",IFERROR(INDEX('Paramètres'!$P:$P,MATCH($D48,'Paramètres'!$M:$M,0))&"","")))) -> Crédit | M48: =IF($D48="","",IF(ISNA(MATCH($D48,'Paramètres'!$M:$M,0)),"⚠ Type inconnu",IF($L48="Crédit","",IFERROR(INDEX('Paramètres'!$O:$O,MATCH($D48,'Paramètres'!$M:$M,0))&"","")))) | N48: =IF($D48="","",IFERROR(INDEX('Paramètres'!$Q:$Q,MATCH($D48,'Paramètres'!$M:$M,0))&"","")) -> Comptes Bancaires | O48: =IF($A48="","",IF(OR($J48<>"x",$A48<=FinReleve),1,0)) -> 1 | P48: =IF($D48="","",IF(AND($L48="Crédit",OR(IFERROR(INDEX('Paramètres'!$O:$O,MATCH($D48,'Paramètres'!$M:$M,0))&"","")<>"",ISNUMBER(SEARCH("remboursement",IFERROR(INDEX('Paramètres'!$N:$N,MATCH($D48,'Paramètres'!$M:$M,0))&"",""))))),1,0)) -> 0 | Q48: =IF($K48="","",IF(ISNUMBER(SEARCH("transfert-interne",IFERROR(INDEX('Paramètres'!$N:$N,MATCH($D48,'Paramètres'!$M:$M,0))&"",""))),0,IF($L48="Débit",$K48,IF($P48=1,-$K48,0)))) -> 0 | R48: =IF($K48="","",IF($L48="Crédit",$K48,-$K48)) -> 300 | S48: =IF($C48="","",IFERROR(INDEX('Paramètres'!$H:$H,MATCH($C48,'Paramètres'!$D:$D,0))&"","")) -> Banque A - Courant | T48: =IF($K48="","",IF($S48="",0,IF(ISNUMBER(SEARCH("apport-exterieur",IFERROR(INDEX('Paramètres'!$N:$N,MATCH($D48,'Paramètres'!$M:$M,0))&"",""))),0,IF(OR(IFERROR(INDEX('Paramètres'!$I:$I,MATCH($C48,'Paramètres'!$D:$D,0))&"","")="Les deux",IFERROR(INDEX('Paramètres'!$I:$I,MATCH($C48,'Paramètres'!$D:$D,0))&"","")=IF($P48=1,"Débit",$L48)),-IF($P48=1,-$K48,$K48),0)))) -> -300 | U48: =IF($K48="","",IF(ISNUMBER(SEARCH("sortie-epargne",IFERROR(INDEX('Paramètres'!$N:$N,MATCH($D48,'Paramètres'!$M:$M,0))&"",""))),$K48,0)) -> 0 | V48: =IF(AND($A48<>"",$O48=1,$L48="Débit",N($Q48)>0,$A48>=Visualisation!$B$1,$A48<Visualisation!$D$1),MAX($V$1:V47)+1,"")
A49: 45567 | B49: Titre restaurant | C49: Titres-restaurant | D49: cantine | E49: 12.56 | G49: Cantine | I49: Villebourg-sur-Rive | K49: =IF($E49="","",ROUND($E49*IF(ISNA(MATCH($C49,'Paramètres'!$D:$D,0)),1,IF(INDEX('Paramètres'!$J:$J,MATCH($C49,'Paramètres'!$D:$D,0))="",1,INDEX('Paramètres'!$J:$J,MATCH($C49,'Paramètres'!$D:$D,0)))),2)) -> 12.56 | L49: =IF($D49="","",IF($F49<>"",$F49,IF(ISNA(MATCH($D49,'Paramètres'!$M:$M,0)),"⚠ Type inconnu",IFERROR(INDEX('Paramètres'!$P:$P,MATCH($D49,'Paramètres'!$M:$M,0))&"","")))) -> Débit | M49: =IF($D49="","",IF(ISNA(MATCH($D49,'Paramètres'!$M:$M,0)),"⚠ Type inconnu",IF($L49="Crédit","",IFERROR(INDEX('Paramètres'!$O:$O,MATCH($D49,'Paramètres'!$M:$M,0))&"","")))) -> Dépense Courante | N49: =IF($D49="","",IFERROR(INDEX('Paramètres'!$Q:$Q,MATCH($D49,'Paramètres'!$M:$M,0))&"","")) -> Alimentation | O49: =IF($A49="","",IF(OR($J49<>"x",$A49<=FinReleve),1,0)) -> 1 | P49: =IF($D49="","",IF(AND($L49="Crédit",OR(IFERROR(INDEX('Paramètres'!$O:$O,MATCH($D49,'Paramètres'!$M:$M,0))&"","")<>"",ISNUMBER(SEARCH("remboursement",IFERROR(INDEX('Paramètres'!$N:$N,MATCH($D49,'Paramètres'!$M:$M,0))&"",""))))),1,0)) -> 0 | Q49: =IF($K49="","",IF(ISNUMBER(SEARCH("transfert-interne",IFERROR(INDEX('Paramètres'!$N:$N,MATCH($D49,'Paramètres'!$M:$M,0))&"",""))),0,IF($L49="Débit",$K49,IF($P49=1,-$K49,0)))) -> 12.56 | R49: =IF($K49="","",IF($L49="Crédit",$K49,-$K49)) -> -12.56 | S49: =IF($C49="","",IFERROR(INDEX('Paramètres'!$H:$H,MATCH($C49,'Paramètres'!$D:$D,0))&"","")) | T49: =IF($K49="","",IF($S49="",0,IF(ISNUMBER(SEARCH("apport-exterieur",IFERROR(INDEX('Paramètres'!$N:$N,MATCH($D49,'Paramètres'!$M:$M,0))&"",""))),0,IF(OR(IFERROR(INDEX('Paramètres'!$I:$I,MATCH($C49,'Paramètres'!$D:$D,0))&"","")="Les deux",IFERROR(INDEX('Paramètres'!$I:$I,MATCH($C49,'Paramètres'!$D:$D,0))&"","")=IF($P49=1,"Débit",$L49)),-IF($P49=1,-$K49,$K49),0)))) -> 0 | U49: =IF($K49="","",IF(ISNUMBER(SEARCH("sortie-epargne",IFERROR(INDEX('Paramètres'!$N:$N,MATCH($D49,'Paramètres'!$M:$M,0))&"",""))),$K49,0)) -> 0 | V49: =IF(AND($A49<>"",$O49=1,$L49="Débit",N($Q49)>0,$A49>=Visualisation!$B$1,$A49<Visualisation!$D$1),MAX($V$1:V48)+1,"")
A50: 45568 | B50: Abonnement transport | C50: Banque A - Courant | D50: Abonnement transport | E50: 88.8 | K50: =IF($E50="","",ROUND($E50*IF(ISNA(MATCH($C50,'Paramètres'!$D:$D,0)),1,IF(INDEX('Paramètres'!$J:$J,MATCH($C50,'Paramètres'!$D:$D,0))="",1,INDEX('Paramètres'!$J:$J,MATCH($C50,'Paramètres'!$D:$D,0)))),2)) -> 88.8 | L50: =IF($D50="","",IF($F50<>"",$F50,IF(ISNA(MATCH($D50,'Paramètres'!$M:$M,0)),"⚠ Type inconnu",IFERROR(INDEX('Paramètres'!$P:$P,MATCH($D50,'Paramètres'!$M:$M,0))&"","")))) -> Débit | M50: =IF($D50="","",IF(ISNA(MATCH($D50,'Paramètres'!$M:$M,0)),"⚠ Type inconnu",IF($L50="Crédit","",IFERROR(INDEX('Paramètres'!$O:$O,MATCH($D50,'Paramètres'!$M:$M,0))&"","")))) -> Dépense Fixe | N50: =IF($D50="","",IFERROR(INDEX('Paramètres'!$Q:$Q,MATCH($D50,'Paramètres'!$M:$M,0))&"","")) -> Transport | O50: =IF($A50="","",IF(OR($J50<>"x",$A50<=FinReleve),1,0)) -> 1 | P50: =IF($D50="","",IF(AND($L50="Crédit",OR(IFERROR(INDEX('Paramètres'!$O:$O,MATCH($D50,'Paramètres'!$M:$M,0))&"","")<>"",ISNUMBER(SEARCH("remboursement",IFERROR(INDEX('Paramètres'!$N:$N,MATCH($D50,'Paramètres'!$M:$M,0))&"",""))))),1,0)) -> 0 | Q50: =IF($K50="","",IF(ISNUMBER(SEARCH("transfert-interne",IFERROR(INDEX('Paramètres'!$N:$N,MATCH($D50,'Paramètres'!$M:$M,0))&"",""))),0,IF($L50="Débit",$K50,IF($P50=1,-$K50,0)))) -> 88.8 | R50: =IF($K50="","",IF($L50="Crédit",$K50,-$K50)) -> -88.8 | S50: =IF($C50="","",IFERROR(INDEX('Paramètres'!$H:$H,MATCH($C50,'Paramètres'!$D:$D,0))&"","")) | T50: =IF($K50="","",IF($S50="",0,IF(ISNUMBER(SEARCH("apport-exterieur",IFERROR(INDEX('Paramètres'!$N:$N,MATCH($D50,'Paramètres'!$M:$M,0))&"",""))),0,IF(OR(IFERROR(INDEX('Paramètres'!$I:$I,MATCH($C50,'Paramètres'!$D:$D,0))&"","")="Les deux",IFERROR(INDEX('Paramètres'!$I:$I,MATCH($C50,'Paramètres'!$D:$D,0))&"","")=IF($P50=1,"Débit",$L50)),-IF($P50=1,-$K50,$K50),0)))) -> 0 | U50: =IF($K50="","",IF(ISNUMBER(SEARCH("sortie-epargne",IFERROR(INDEX('Paramètres'!$N:$N,MATCH($D50,'Paramètres'!$M:$M,0))&"",""))),$K50,0)) -> 0 | V50: =IF(AND($A50<>"",$O50=1,$L50="Débit",N($Q50)>0,$A50>=Visualisation!$B$1,$A50<Visualisation!$D$1),MAX($V$1:V49)+1,"")
A51: 45568 | B51: Achat carte | C51: Banque B - Compte joint | D51: courses | E51: 135.24 | G51: Boulangerie | I51: Villebourg | K51: =IF($E51="","",ROUND($E51*IF(ISNA(MATCH($C51,'Paramètres'!$D:$D,0)),1,IF(INDEX('Paramètres'!$J:$J,MATCH($C51,'Paramètres'!$D:$D,0))="",1,INDEX('Paramètres'!$J:$J,MATCH($C51,'Paramètres'!$D:$D,0)))),2)) -> 67.62 | L51: =IF($D51="","",IF($F51<>"",$F51,IF(ISNA(MATCH($D51,'Paramètres'!$M:$M,0)),"⚠ Type inconnu",IFERROR(INDEX('Paramètres'!$P:$P,MATCH($D51,'Paramètres'!$M:$M,0))&"","")))) -> Débit | M51: =IF($D51="","",IF(ISNA(MATCH($D51,'Paramètres'!$M:$M,0)),"⚠ Type inconnu",IF($L51="Crédit","",IFERROR(INDEX('Paramètres'!$O:$O,MATCH($D51,'Paramètres'!$M:$M,0))&"","")))) -> Dépense Courante | N51: =IF($D51="","",IFERROR(INDEX('Paramètres'!$Q:$Q,MATCH($D51,'Paramètres'!$M:$M,0))&"","")) -> Alimentation | O51: =IF($A51="","",IF(OR($J51<>"x",$A51<=FinReleve),1,0)) -> 1 | P51: =IF($D51="","",IF(AND($L51="Crédit",OR(IFERROR(INDEX('Paramètres'!$O:$O,MATCH($D51,'Paramètres'!$M:$M,0))&"","")<>"",ISNUMBER(SEARCH("remboursement",IFERROR(INDEX('Paramètres'!$N:$N,MATCH($D51,'Paramètres'!$M:$M,0))&"",""))))),1,0)) -> 0 | Q51: =IF($K51="","",IF(ISNUMBER(SEARCH("transfert-interne",IFERROR(INDEX('Paramètres'!$N:$N,MATCH($D51,'Paramètres'!$M:$M,0))&"",""))),0,IF($L51="Débit",$K51,IF($P51=1,-$K51,0)))) -> 67.62 | R51: =IF($K51="","",IF($L51="Crédit",$K51,-$K51)) -> -67.62 | S51: =IF($C51="","",IFERROR(INDEX('Paramètres'!$H:$H,MATCH($C51,'Paramètres'!$D:$D,0))&"","")) -> Banque A - Courant | T51: =IF($K51="","",IF($S51="",0,IF(ISNUMBER(SEARCH("apport-exterieur",IFERROR(INDEX('Paramètres'!$N:$N,MATCH($D51,'Paramètres'!$M:$M,0))&"",""))),0,IF(OR(IFERROR(INDEX('Paramètres'!$I:$I,MATCH($C51,'Paramètres'!$D:$D,0))&"","")="Les deux",IFERROR(INDEX('Paramètres'!$I:$I,MATCH($C51,'Paramètres'!$D:$D,0))&"","")=IF($P51=1,"Débit",$L51)),-IF($P51=1,-$K51,$K51),0)))) -> 0 | U51: =IF($K51="","",IF(ISNUMBER(SEARCH("sortie-epargne",IFERROR(INDEX('Paramètres'!$N:$N,MATCH($D51,'Paramètres'!$M:$M,0))&"",""))),$K51,0)) -> 0 | V51: =IF(AND($A51<>"",$O51=1,$L51="Débit",N($Q51)>0,$A51>=Visualisation!$B$1,$A51<Visualisation!$D$1),MAX($V$1:V50)+1,"")
A52: 45568 | B52: Titre restaurant | C52: Titres-restaurant | D52: cantine | E52: 13.98 | G52: Cantine | I52: Villebourg | K52: =IF($E52="","",ROUND($E52*IF(ISNA(MATCH($C52,'Paramètres'!$D:$D,0)),1,IF(INDEX('Paramètres'!$J:$J,MATCH($C52,'Paramètres'!$D:$D,0))="",1,INDEX('Paramètres'!$J:$J,MATCH($C52,'Paramètres'!$D:$D,0)))),2)) -> 13.98 | L52: =IF($D52="","",IF($F52<>"",$F52,IF(ISNA(MATCH($D52,'Paramètres'!$M:$M,0)),"⚠ Type inconnu",IFERROR(INDEX('Paramètres'!$P:$P,MATCH($D52,'Paramètres'!$M:$M,0))&"","")))) -> Débit | M52: =IF($D52="","",IF(ISNA(MATCH($D52,'Paramètres'!$M:$M,0)),"⚠ Type inconnu",IF($L52="Crédit","",IFERROR(INDEX('Paramètres'!$O:$O,MATCH($D52,'Paramètres'!$M:$M,0))&"","")))) -> Dépense Courante | N52: =IF($D52="","",IFERROR(INDEX('Paramètres'!$Q:$Q,MATCH($D52,'Paramètres'!$M:$M,0))&"","")) -> Alimentation | O52: =IF($A52="","",IF(OR($J52<>"x",$A52<=FinReleve),1,0)) -> 1 | P52: =IF($D52="","",IF(AND($L52="Crédit",OR(IFERROR(INDEX('Paramètres'!$O:$O,MATCH($D52,'Paramètres'!$M:$M,0))&"","")<>"",ISNUMBER(SEARCH("remboursement",IFERROR(INDEX('Paramètres'!$N:$N,MATCH($D52,'Paramètres'!$M:$M,0))&"",""))))),1,0)) -> 0 | Q52: =IF($K52="","",IF(ISNUMBER(SEARCH("transfert-interne",IFERROR(INDEX('Paramètres'!$N:$N,MATCH($D52,'Paramètres'!$M:$M,0))&"",""))),0,IF($L52="Débit",$K52,IF($P52=1,-$K52,0)))) -> 13.98 | R52: =IF($K52="","",IF($L52="Crédit",$K52,-$K52)) -> -13.98 | S52: =IF($C52="","",IFERROR(INDEX('Paramètres'!$H:$H,MATCH($C52,'Paramètres'!$D:$D,0))&"","")) | T52: =IF($K52="","",IF($S52="",0,IF(ISNUMBER(SEARCH("apport-exterieur",IFERROR(INDEX('Paramètres'!$N:$N,MATCH($D52,'Paramètres'!$M:$M,0))&"",""))),0,IF(OR(IFERROR(INDEX('Paramètres'!$I:$I,MATCH($C52,'Paramètres'!$D:$D,0))&"","")="Les deux",IFERROR(INDEX('Paramètres'!$I:$I,MATCH($C52,'Paramètres'!$D:$D,0))&"","")=IF($P52=1,"Débit",$L52)),-IF($P52=1,-$K52,$K52),0)))) -> 0 | U52: =IF($K52="","",IF(ISNUMBER(SEARCH("sortie-epargne",IFERROR(INDEX('Paramètres'!$N:$N,MATCH($D52,'Paramètres'!$M:$M,0))&"",""))),$K52,0)) -> 0 | V52: =IF(AND($A52<>"",$O52=1,$L52="Débit",N($Q52)>0,$A52>=Visualisation!$B$1,$A52<Visualisation!$D$1),MAX($V$1:V51)+1,"")
A53: 45569 | B53: Dotation titres | C53: Titres-restaurant | D53: Ticket Restaurant | E53: 125.23 | K53: =IF($E53="","",ROUND($E53*IF(ISNA(MATCH($C53,'Paramètres'!$D:$D,0)),1,IF(INDEX('Paramètres'!$J:$J,MATCH($C53,'Paramètres'!$D:$D,0))="",1,INDEX('Paramètres'!$J:$J,MATCH($C53,'Paramètres'!$D:$D,0)))),2)) -> 125.23 | L53: =IF($D53="","",IF($F53<>"",$F53,IF(ISNA(MATCH($D53,'Paramètres'!$M:$M,0)),"⚠ Type inconnu",IFERROR(INDEX('Paramètres'!$P:$P,MATCH($D53,'Paramètres'!$M:$M,0))&"","")))) -> Crédit | M53: =IF($D53="","",IF(ISNA(MATCH($D53,'Paramètres'!$M:$M,0)),"⚠ Type inconnu",IF($L53="Crédit","",IFERROR(INDEX('Paramètres'!$O:$O,MATCH($D53,'Paramètres'!$M:$M,0))&"","")))) | N53: =IF($D53="","",IFERROR(INDEX('Paramètres'!$Q:$Q,MATCH($D53,'Paramètres'!$M:$M,0))&"","")) -> Comptes Bancaires | O53: =IF($A53="","",IF(OR($J53<>"x",$A53<=FinReleve),1,0)) -> 1 | P53: =IF($D53="","",IF(AND($L53="Crédit",OR(IFERROR(INDEX('Paramètres'!$O:$O,MATCH($D53,'Paramètres'!$M:$M,0))&"","")<>"",ISNUMBER(SEARCH("remboursement",IFERROR(INDEX('Paramètres'!$N:$N,MATCH($D53,'Paramètres'!$M:$M,0))&"",""))))),1,0)) -> 0 | Q53: =IF($K53="","",IF(ISNUMBER(SEARCH("transfert-interne",IFERROR(INDEX('Paramètres'!$N:$N,MATCH($D53,'Paramètres'!$M:$M,0))&"",""))),0,IF($L53="Débit",$K53,IF($P53=1,-$K53,0)))) -> 0 | R53: =IF($K53="","",IF($L53="Crédit",$K53,-$K53)) -> 125.23 | S53: =IF($C53="","",IFERROR(INDEX('Paramètres'!$H:$H,MATCH($C53,'Paramètres'!$D:$D,0))&"","")) | T53: =IF($K53="","",IF($S53="",0,IF(ISNUMBER(SEARCH("apport-exterieur",IFERROR(INDEX('Paramètres'!$N:$N,MATCH($D53,'Paramètres'!$M:$M,0))&"",""))),0,IF(OR(IFERROR(INDEX('Paramètres'!$I:$I,MATCH($C53,'Paramètres'!$D:$D,0))&"","")="Les deux",IFERROR(INDEX('Paramètres'!$I:$I,MATCH($C53,'Paramètres'!$D:$D,0))&"","")=IF($P53=1,"Débit",$L53)),-IF($P53=1,-$K53,$K53),0)))) -> 0 | U53: =IF($K53="","",IF(ISNUMBER(SEARCH("sortie-epargne",IFERROR(INDEX('Paramètres'!$N:$N,MATCH($D53,'Paramètres'!$M:$M,0))&"",""))),$K53,0)) -> 0 | V53: =IF(AND($A53<>"",$O53=1,$L53="Débit",N($Q53)>0,$A53>=Visualisation!$B$1,$A53<Visualisation!$D$1),MAX($V$1:V52)+1,"")
A54: 45570 | B54: Échéance prêt — capital | C54: Banque C - Compte joint | D54: Crédit Immobilier | E54: 646.48 | G54: Remboursement capital | K54: =IF($E54="","",ROUND($E54*IF(ISNA(MATCH($C54,'Paramètres'!$D:$D,0)),1,IF(INDEX('Paramètres'!$J:$J,MATCH($C54,'Paramètres'!$D:$D,0))="",1,INDEX('Paramètres'!$J:$J,MATCH($C54,'Paramètres'!$D:$D,0)))),2)) -> 646.48 | L54: =IF($D54="","",IF($F54<>"",$F54,IF(ISNA(MATCH($D54,'Paramètres'!$M:$M,0)),"⚠ Type inconnu",IFERROR(INDEX('Paramètres'!$P:$P,MATCH($D54,'Paramètres'!$M:$M,0))&"","")))) -> Débit | M54: =IF($D54="","",IF(ISNA(MATCH($D54,'Paramètres'!$M:$M,0)),"⚠ Type inconnu",IF($L54="Crédit","",IFERROR(INDEX('Paramètres'!$O:$O,MATCH($D54,'Paramètres'!$M:$M,0))&"","")))) | N54: =IF($D54="","",IFERROR(INDEX('Paramètres'!$Q:$Q,MATCH($D54,'Paramètres'!$M:$M,0))&"","")) -> Immobilier | O54: =IF($A54="","",IF(OR($J54<>"x",$A54<=FinReleve),1,0)) -> 1 | P54: =IF($D54="","",IF(AND($L54="Crédit",OR(IFERROR(INDEX('Paramètres'!$O:$O,MATCH($D54,'Paramètres'!$M:$M,0))&"","")<>"",ISNUMBER(SEARCH("remboursement",IFERROR(INDEX('Paramètres'!$N:$N,MATCH($D54,'Paramètres'!$M:$M,0))&"",""))))),1,0)) -> 0 | Q54: =IF($K54="","",IF(ISNUMBER(SEARCH("transfert-interne",IFERROR(INDEX('Paramètres'!$N:$N,MATCH($D54,'Paramètres'!$M:$M,0))&"",""))),0,IF($L54="Débit",$K54,IF($P54=1,-$K54,0)))) -> 646.48 | R54: =IF($K54="","",IF($L54="Crédit",$K54,-$K54)) -> -646.48 | S54: =IF($C54="","",IFERROR(INDEX('Paramètres'!$H:$H,MATCH($C54,'Paramètres'!$D:$D,0))&"","")) -> Banque A - Courant | T54: =IF($K54="","",IF($S54="",0,IF(ISNUMBER(SEARCH("apport-exterieur",IFERROR(INDEX('Paramètres'!$N:$N,MATCH($D54,'Paramètres'!$M:$M,0))&"",""))),0,IF(OR(IFERROR(INDEX('Paramètres'!$I:$I,MATCH($C54,'Paramètres'!$D:$D,0))&"","")="Les deux",IFERROR(INDEX('Paramètres'!$I:$I,MATCH($C54,'Paramètres'!$D:$D,0))&"","")=IF($P54=1,"Débit",$L54)),-IF($P54=1,-$K54,$K54),0)))) -> 0 | U54: =IF($K54="","",IF(ISNUMBER(SEARCH("sortie-epargne",IFERROR(INDEX('Paramètres'!$N:$N,MATCH($D54,'Paramètres'!$M:$M,0))&"",""))),$K54,0)) -> 0 | V54: =IF(AND($A54<>"",$O54=1,$L54="Débit",N($Q54)>0,$A54>=Visualisation!$B$1,$A54<Visualisation!$D$1),MAX($V$1:V53)+1,"")
A55: 45570 | B55: Échéance prêt — intérêts | C55: Banque C - Compte joint | D55: Intérêt du prêt | E55: 247.16 | G55: Intérêts | K55: =IF($E55="","",ROUND($E55*IF(ISNA(MATCH($C55,'Paramètres'!$D:$D,0)),1,IF(INDEX('Paramètres'!$J:$J,MATCH($C55,'Paramètres'!$D:$D,0))="",1,INDEX('Paramètres'!$J:$J,MATCH($C55,'Paramètres'!$D:$D,0)))),2)) -> 247.16 | L55: =IF($D55="","",IF($F55<>"",$F55,IF(ISNA(MATCH($D55,'Paramètres'!$M:$M,0)),"⚠ Type inconnu",IFERROR(INDEX('Paramètres'!$P:$P,MATCH($D55,'Paramètres'!$M:$M,0))&"","")))) -> Débit | M55: =IF($D55="","",IF(ISNA(MATCH($D55,'Paramètres'!$M:$M,0)),"⚠ Type inconnu",IF($L55="Crédit","",IFERROR(INDEX('Paramètres'!$O:$O,MATCH($D55,'Paramètres'!$M:$M,0))&"","")))) -> Dépense Fixe | N55: =IF($D55="","",IFERROR(INDEX('Paramètres'!$Q:$Q,MATCH($D55,'Paramètres'!$M:$M,0))&"","")) -> Immobilier | O55: =IF($A55="","",IF(OR($J55<>"x",$A55<=FinReleve),1,0)) -> 1 | P55: =IF($D55="","",IF(AND($L55="Crédit",OR(IFERROR(INDEX('Paramètres'!$O:$O,MATCH($D55,'Paramètres'!$M:$M,0))&"","")<>"",ISNUMBER(SEARCH("remboursement",IFERROR(INDEX('Paramètres'!$N:$N,MATCH($D55,'Paramètres'!$M:$M,0))&"",""))))),1,0)) -> 0 | Q55: =IF($K55="","",IF(ISNUMBER(SEARCH("transfert-interne",IFERROR(INDEX('Paramètres'!$N:$N,MATCH($D55,'Paramètres'!$M:$M,0))&"",""))),0,IF($L55="Débit",$K55,IF($P55=1,-$K55,0)))) -> 247.16 | R55: =IF($K55="","",IF($L55="Crédit",$K55,-$K55)) -> -247.16 | S55: =IF($C55="","",IFERROR(INDEX('Paramètres'!$H:$H,MATCH($C55,'Paramètres'!$D:$D,0))&"","")) -> Banque A - Courant | T55: =IF($K55="","",IF($S55="",0,IF(ISNUMBER(SEARCH("apport-exterieur",IFERROR(INDEX('Paramètres'!$N:$N,MATCH($D55,'Paramètres'!$M:$M,0))&"",""))),0,IF(OR(IFERROR(INDEX('Paramètres'!$I:$I,MATCH($C55,'Paramètres'!$D:$D,0))&"","")="Les deux",IFERROR(INDEX('Paramètres'!$I:$I,MATCH($C55,'Paramètres'!$D:$D,0))&"","")=IF($P55=1,"Débit",$L55)),-IF($P55=1,-$K55,$K55),0)))) -> 0 | U55: =IF($K55="","",IF(ISNUMBER(SEARCH("sortie-epargne",IFERROR(INDEX('Paramètres'!$N:$N,MATCH($D55,'Paramètres'!$M:$M,0))&"",""))),$K55,0)) -> 0 | V55: =IF(AND($A55<>"",$O55=1,$L55="Débit",N($Q55)>0,$A55>=Visualisation!$B$1,$A55<Visualisation!$D$1),MAX($V$1:V54)+1,"")
A56: 45570 | B56: Assurance prêt | C56: Banque C - Compte joint | D56: Assurance prêt | E56: 31.2 | K56: =IF($E56="","",ROUND($E56*IF(ISNA(MATCH($C56,'Paramètres'!$D:$D,0)),1,IF(INDEX('Paramètres'!$J:$J,MATCH($C56,'Paramètres'!$D:$D,0))="",1,INDEX('Paramètres'!$J:$J,MATCH($C56,'Paramètres'!$D:$D,0)))),2)) -> 31.2 | L56: =IF($D56="","",IF($F56<>"",$F56,IF(ISNA(MATCH($D56,'Paramètres'!$M:$M,0)),"⚠ Type inconnu",IFERROR(INDEX('Paramètres'!$P:$P,MATCH($D56,'Paramètres'!$M:$M,0))&"","")))) -> Débit | M56: =IF($D56="","",IF(ISNA(MATCH($D56,'Paramètres'!$M:$M,0)),"⚠ Type inconnu",IF($L56="Crédit","",IFERROR(INDEX('Paramètres'!$O:$O,MATCH($D56,'Paramètres'!$M:$M,0))&"","")))) -> Dépense Fixe | N56: =IF($D56="","",IFERROR(INDEX('Paramètres'!$Q:$Q,MATCH($D56,'Paramètres'!$M:$M,0))&"","")) -> Assurances | O56: =IF($A56="","",IF(OR($J56<>"x",$A56<=FinReleve),1,0)) -> 1 | P56: =IF($D56="","",IF(AND($L56="Crédit",OR(IFERROR(INDEX('Paramètres'!$O:$O,MATCH($D56,'Paramètres'!$M:$M,0))&"","")<>"",ISNUMBER(SEARCH("remboursement",IFERROR(INDEX('Paramètres'!$N:$N,MATCH($D56,'Paramètres'!$M:$M,0))&"",""))))),1,0)) -> 0 | Q56: =IF($K56="","",IF(ISNUMBER(SEARCH("transfert-interne",IFERROR(INDEX('Paramètres'!$N:$N,MATCH($D56,'Paramètres'!$M:$M,0))&"",""))),0,IF($L56="Débit",$K56,IF($P56=1,-$K56,0)))) -> 31.2 | R56: =IF($K56="","",IF($L56="Crédit",$K56,-$K56)) -> -31.2 | S56: =IF($C56="","",IFERROR(INDEX('Paramètres'!$H:$H,MATCH($C56,'Paramètres'!$D:$D,0))&"","")) -> Banque A - Courant | T56: =IF($K56="","",IF($S56="",0,IF(ISNUMBER(SEARCH("apport-exterieur",IFERROR(INDEX('Paramètres'!$N:$N,MATCH($D56,'Paramètres'!$M:$M,0))&"",""))),0,IF(OR(IFERROR(INDEX('Paramètres'!$I:$I,MATCH($C56,'Paramètres'!$D:$D,0))&"","")="Les deux",IFERROR(INDEX('Paramètres'!$I:$I,MATCH($C56,'Paramètres'!$D:$D,0))&"","")=IF($P56=1,"Débit",$L56)),-IF($P56=1,-$K56,$K56),0)))) -> 0 | U56: =IF($K56="","",IF(ISNUMBER(SEARCH("sortie-epargne",IFERROR(INDEX('Paramètres'!$N:$N,MATCH($D56,'Paramètres'!$M:$M,0))&"",""))),$K56,0)) -> 0 | V56: =IF(AND($A56<>"",$O56=1,$L56="Débit",N($Q56)>0,$A56>=Visualisation!$B$1,$A56<Visualisation!$D$1),MAX($V$1:V55)+1,"")
A57: 45571 | B57: Internet et Forfait téléphone | C57: Banque A - Courant | D57: Internet et Forfait téléphone | E57: 49.9 | K57: =IF($E57="","",ROUND($E57*IF(ISNA(MATCH($C57,'Paramètres'!$D:$D,0)),1,IF(INDEX('Paramètres'!$J:$J,MATCH($C57,'Paramètres'!$D:$D,0))="",1,INDEX('Paramètres'!$J:$J,MATCH($C57,'Paramètres'!$D:$D,0)))),2)) -> 49.9 | L57: =IF($D57="","",IF($F57<>"",$F57,IF(ISNA(MATCH($D57,'Paramètres'!$M:$M,0)),"⚠ Type inconnu",IFERROR(INDEX('Paramètres'!$P:$P,MATCH($D57,'Paramètres'!$M:$M,0))&"","")))) -> Débit | M57: =IF($D57="","",IF(ISNA(MATCH($D57,'Paramètres'!$M:$M,0)),"⚠ Type inconnu",IF($L57="Crédit","",IFERROR(INDEX('Paramètres'!$O:$O,MATCH($D57,'Paramètres'!$M:$M,0))&"","")))) -> Dépense Fixe | N57: =IF($D57="","",IFERROR(INDEX('Paramètres'!$Q:$Q,MATCH($D57,'Paramètres'!$M:$M,0))&"","")) -> Autre | O57: =IF($A57="","",IF(OR($J57<>"x",$A57<=FinReleve),1,0)) -> 1 | P57: =IF($D57="","",IF(AND($L57="Crédit",OR(IFERROR(INDEX('Paramètres'!$O:$O,MATCH($D57,'Paramètres'!$M:$M,0))&"","")<>"",ISNUMBER(SEARCH("remboursement",IFERROR(INDEX('Paramètres'!$N:$N,MATCH($D57,'Paramètres'!$M:$M,0))&"",""))))),1,0)) -> 0 | Q57: =IF($K57="","",IF(ISNUMBER(SEARCH("transfert-interne",IFERROR(INDEX('Paramètres'!$N:$N,MATCH($D57,'Paramètres'!$M:$M,0))&"",""))),0,IF($L57="Débit",$K57,IF($P57=1,-$K57,0)))) -> 49.9 | R57: =IF($K57="","",IF($L57="Crédit",$K57,-$K57)) -> -49.9 | S57: =IF($C57="","",IFERROR(INDEX('Paramètres'!$H:$H,MATCH($C57,'Paramètres'!$D:$D,0))&"","")) | T57: =IF($K57="","",IF($S57="",0,IF(ISNUMBER(SEARCH("apport-exterieur",IFERROR(INDEX('Paramètres'!$N:$N,MATCH($D57,'Paramètres'!$M:$M,0))&"",""))),0,IF(OR(IFERROR(INDEX('Paramètres'!$I:$I,MATCH($C57,'Paramètres'!$D:$D,0))&"","")="Les deux",IFERROR(INDEX('Paramètres'!$I:$I,MATCH($C57,'Paramètres'!$D:$D,0))&"","")=IF($P57=1,"Débit",$L57)),-IF($P57=1,-$K57,$K57),0)))) -> 0 | U57: =IF($K57="","",IF(ISNUMBER(SEARCH("sortie-epargne",IFERROR(INDEX('Paramètres'!$N:$N,MATCH($D57,'Paramètres'!$M:$M,0))&"",""))),$K57,0)) -> 0 | V57: =IF(AND($A57<>"",$O57=1,$L57="Débit",N($Q57)>0,$A57>=Visualisation!$B$1,$A57<Visualisation!$D$1),MAX($V$1:V56)+1,"")
A58: 45572 | B58: Achat carte | C58: Banque A - Part commune | D58: courses | E58: 171.78 | G58: Boulangerie | I58: Rocheville | K58: =IF($E58="","",ROUND($E58*IF(ISNA(MATCH($C58,'Paramètres'!$D:$D,0)),1,IF(INDEX('Paramètres'!$J:$J,MATCH($C58,'Paramètres'!$D:$D,0))="",1,INDEX('Paramètres'!$J:$J,MATCH($C58,'Paramètres'!$D:$D,0)))),2)) -> 85.89 | L58: =IF($D58="","",IF($F58<>"",$F58,IF(ISNA(MATCH($D58,'Paramètres'!$M:$M,0)),"⚠ Type inconnu",IFERROR(INDEX('Paramètres'!$P:$P,MATCH($D58,'Paramètres'!$M:$M,0))&"","")))) -> Débit | M58: =IF($D58="","",IF(ISNA(MATCH($D58,'Paramètres'!$M:$M,0)),"⚠ Type inconnu",IF($L58="Crédit","",IFERROR(INDEX('Paramètres'!$O:$O,MATCH($D58,'Paramètres'!$M:$M,0))&"","")))) -> Dépense Courante | N58: =IF($D58="","",IFERROR(INDEX('Paramètres'!$Q:$Q,MATCH($D58,'Paramètres'!$M:$M,0))&"","")) -> Alimentation | O58: =IF($A58="","",IF(OR($J58<>"x",$A58<=FinReleve),1,0)) -> 1 | P58: =IF($D58="","",IF(AND($L58="Crédit",OR(IFERROR(INDEX('Paramètres'!$O:$O,MATCH($D58,'Paramètres'!$M:$M,0))&"","")<>"",ISNUMBER(SEARCH("remboursement",IFERROR(INDEX('Paramètres'!$N:$N,MATCH($D58,'Paramètres'!$M:$M,0))&"",""))))),1,0)) -> 0 | Q58: =IF($K58="","",IF(ISNUMBER(SEARCH("transfert-interne",IFERROR(INDEX('Paramètres'!$N:$N,MATCH($D58,'Paramètres'!$M:$M,0))&"",""))),0,IF($L58="Débit",$K58,IF($P58=1,-$K58,0)))) -> 85.89 | R58: =IF($K58="","",IF($L58="Crédit",$K58,-$K58)) -> -85.89 | S58: =IF($C58="","",IFERROR(INDEX('Paramètres'!$H:$H,MATCH($C58,'Paramètres'!$D:$D,0))&"","")) -> Banque A - Courant | T58: =IF($K58="","",IF($S58="",0,IF(ISNUMBER(SEARCH("apport-exterieur",IFERROR(INDEX('Paramètres'!$N:$N,MATCH($D58,'Paramètres'!$M:$M,0))&"",""))),0,IF(OR(IFERROR(INDEX('Paramètres'!$I:$I,MATCH($C58,'Paramètres'!$D:$D,0))&"","")="Les deux",IFERROR(INDEX('Paramètres'!$I:$I,MATCH($C58,'Paramètres'!$D:$D,0))&"","")=IF($P58=1,"Débit",$L58)),-IF($P58=1,-$K58,$K58),0)))) -> -85.89 | U58: =IF($K58="","",IF(ISNUMBER(SEARCH("sortie-epargne",IFERROR(INDEX('Paramètres'!$N:$N,MATCH($D58,'Paramètres'!$M:$M,0))&"",""))),$K58,0)) -> 0 | V58: =IF(AND($A58<>"",$O58=1,$L58="Débit",N($Q58)>0,$A58>=Visualisation!$B$1,$A58<Visualisation!$D$1),MAX($V$1:V57)+1,"")
A59: 45573 | B59: Frais de Copropriété | C59: Banque C - Compte joint | D59: Frais de Copropriété | E59: 168 | K59: =IF($E59="","",ROUND($E59*IF(ISNA(MATCH($C59,'Paramètres'!$D:$D,0)),1,IF(INDEX('Paramètres'!$J:$J,MATCH($C59,'Paramètres'!$D:$D,0))="",1,INDEX('Paramètres'!$J:$J,MATCH($C59,'Paramètres'!$D:$D,0)))),2)) -> 168 | L59: =IF($D59="","",IF($F59<>"",$F59,IF(ISNA(MATCH($D59,'Paramètres'!$M:$M,0)),"⚠ Type inconnu",IFERROR(INDEX('Paramètres'!$P:$P,MATCH($D59,'Paramètres'!$M:$M,0))&"","")))) -> Débit | M59: =IF($D59="","",IF(ISNA(MATCH($D59,'Paramètres'!$M:$M,0)),"⚠ Type inconnu",IF($L59="Crédit","",IFERROR(INDEX('Paramètres'!$O:$O,MATCH($D59,'Paramètres'!$M:$M,0))&"","")))) -> Dépense Fixe | N59: =IF($D59="","",IFERROR(INDEX('Paramètres'!$Q:$Q,MATCH($D59,'Paramètres'!$M:$M,0))&"","")) -> Immobilier | O59: =IF($A59="","",IF(OR($J59<>"x",$A59<=FinReleve),1,0)) -> 1 | P59: =IF($D59="","",IF(AND($L59="Crédit",OR(IFERROR(INDEX('Paramètres'!$O:$O,MATCH($D59,'Paramètres'!$M:$M,0))&"","")<>"",ISNUMBER(SEARCH("remboursement",IFERROR(INDEX('Paramètres'!$N:$N,MATCH($D59,'Paramètres'!$M:$M,0))&"",""))))),1,0)) -> 0 | Q59: =IF($K59="","",IF(ISNUMBER(SEARCH("transfert-interne",IFERROR(INDEX('Paramètres'!$N:$N,MATCH($D59,'Paramètres'!$M:$M,0))&"",""))),0,IF($L59="Débit",$K59,IF($P59=1,-$K59,0)))) -> 168 | R59: =IF($K59="","",IF($L59="Crédit",$K59,-$K59)) -> -168 | S59: =IF($C59="","",IFERROR(INDEX('Paramètres'!$H:$H,MATCH($C59,'Paramètres'!$D:$D,0))&"","")) -> Banque A - Courant | T59: =IF($K59="","",IF($S59="",0,IF(ISNUMBER(SEARCH("apport-exterieur",IFERROR(INDEX('Paramètres'!$N:$N,MATCH($D59,'Paramètres'!$M:$M,0))&"",""))),0,IF(OR(IFERROR(INDEX('Paramètres'!$I:$I,MATCH($C59,'Paramètres'!$D:$D,0))&"","")="Les deux",IFERROR(INDEX('Paramètres'!$I:$I,MATCH($C59,'Paramètres'!$D:$D,0))&"","")=IF($P59=1,"Débit",$L59)),-IF($P59=1,-$K59,$K59),0)))) -> 0 | U59: =IF($K59="","",IF(ISNUMBER(SEARCH("sortie-epargne",IFERROR(INDEX('Paramètres'!$N:$N,MATCH($D59,'Paramètres'!$M:$M,0))&"",""))),$K59,0)) -> 0 | V59: =IF(AND($A59<>"",$O59=1,$L59="Débit",N($Q59)>0,$A59>=Visualisation!$B$1,$A59<Visualisation!$D$1),MAX($V$1:V58)+1,"")
A60: 45573 | B60: Achat carte | C60: Banque B - Compte joint | D60: courses | E60: 120.62 | G60: Supermarché Centre | I60: Villebourg | K60: =IF($E60="","",ROUND($E60*IF(ISNA(MATCH($C60,'Paramètres'!$D:$D,0)),1,IF(INDEX('Paramètres'!$J:$J,MATCH($C60,'Paramètres'!$D:$D,0))="",1,INDEX('Paramètres'!$J:$J,MATCH($C60,'Paramètres'!$D:$D,0)))),2)) -> 60.31 | L60: =IF($D60="","",IF($F60<>"",$F60,IF(ISNA(MATCH($D60,'Paramètres'!$M:$M,0)),"⚠ Type inconnu",IFERROR(INDEX('Paramètres'!$P:$P,MATCH($D60,'Paramètres'!$M:$M,0))&"","")))) -> Débit | M60: =IF($D60="","",IF(ISNA(MATCH($D60,'Paramètres'!$M:$M,0)),"⚠ Type inconnu",IF($L60="Crédit","",IFERROR(INDEX('Paramètres'!$O:$O,MATCH($D60,'Paramètres'!$M:$M,0))&"","")))) -> Dépense Courante | N60: =IF($D60="","",IFERROR(INDEX('Paramètres'!$Q:$Q,MATCH($D60,'Paramètres'!$M:$M,0))&"","")) -> Alimentation | O60: =IF($A60="","",IF(OR($J60<>"x",$A60<=FinReleve),1,0)) -> 1 | P60: =IF($D60="","",IF(AND($L60="Crédit",OR(IFERROR(INDEX('Paramètres'!$O:$O,MATCH($D60,'Paramètres'!$M:$M,0))&"","")<>"",ISNUMBER(SEARCH("remboursement",IFERROR(INDEX('Paramètres'!$N:$N,MATCH($D60,'Paramètres'!$M:$M,0))&"",""))))),1,0)) -> 0 | Q60: =IF($K60="","",IF(ISNUMBER(SEARCH("transfert-interne",IFERROR(INDEX('Paramètres'!$N:$N,MATCH($D60,'Paramètres'!$M:$M,0))&"",""))),0,IF($L60="Débit",$K60,IF($P60=1,-$K60,0)))) -> 60.31 | R60: =IF($K60="","",IF($L60="Crédit",$K60,-$K60)) -> -60.31 | S60: =IF($C60="","",IFERROR(INDEX('Paramètres'!$H:$H,MATCH($C60,'Paramètres'!$D:$D,0))&"","")) -> Banque A - Courant | T60: =IF($K60="","",IF($S60="",0,IF(ISNUMBER(SEARCH("apport-exterieur",IFERROR(INDEX('Paramètres'!$N:$N,MATCH($D60,'Paramètres'!$M:$M,0))&"",""))),0,IF(OR(IFERROR(INDEX('Paramètres'!$I:$I,MATCH($C60,'Paramètres'!$D:$D,0))&"","")="Les deux",IFERROR(INDEX('Paramètres'!$I:$I,MATCH($C60,'Paramètres'!$D:$D,0))&"","")=IF($P60=1,"Débit",$L60)),-IF($P60=1,-$K60,$K60),0)))) -> 0 | U60: =IF($K60="","",IF(ISNUMBER(SEARCH("sortie-epargne",IFERROR(INDEX('Paramètres'!$N:$N,MATCH($D60,'Paramètres'!$M:$M,0))&"",""))),$K60,0)) -> 0 | V60: =IF(AND($A60<>"",$O60=1,$L60="Débit",N($Q60)>0,$A60>=Visualisation!$B$1,$A60<Visualisation!$D$1),MAX($V$1:V59)+1,"")
A61: 45573 | B61: Titre restaurant | C61: Titres-restaurant | D61: cantine | E61: 11.11 | G61: Cantine | I61: Villebourg-sur-Rive | K61: =IF($E61="","",ROUND($E61*IF(ISNA(MATCH($C61,'Paramètres'!$D:$D,0)),1,IF(INDEX('Paramètres'!$J:$J,MATCH($C61,'Paramètres'!$D:$D,0))="",1,INDEX('Paramètres'!$J:$J,MATCH($C61,'Paramètres'!$D:$D,0)))),2)) -> 11.11 | L61: =IF($D61="","",IF($F61<>"",$F61,IF(ISNA(MATCH($D61,'Paramètres'!$M:$M,0)),"⚠ Type inconnu",IFERROR(INDEX('Paramètres'!$P:$P,MATCH($D61,'Paramètres'!$M:$M,0))&"","")))) -> Débit | M61: =IF($D61="","",IF(ISNA(MATCH($D61,'Paramètres'!$M:$M,0)),"⚠ Type inconnu",IF($L61="Crédit","",IFERROR(INDEX('Paramètres'!$O:$O,MATCH($D61,'Paramètres'!$M:$M,0))&"","")))) -> Dépense Courante | N61: =IF($D61="","",IFERROR(INDEX('Paramètres'!$Q:$Q,MATCH($D61,'Paramètres'!$M:$M,0))&"","")) -> Alimentation | O61: =IF($A61="","",IF(OR($J61<>"x",$A61<=FinReleve),1,0)) -> 1 | P61: =IF($D61="","",IF(AND($L61="Crédit",OR(IFERROR(INDEX('Paramètres'!$O:$O,MATCH($D61,'Paramètres'!$M:$M,0))&"","")<>"",ISNUMBER(SEARCH("remboursement",IFERROR(INDEX('Paramètres'!$N:$N,MATCH($D61,'Paramètres'!$M:$M,0))&"",""))))),1,0)) -> 0 | Q61: =IF($K61="","",IF(ISNUMBER(SEARCH("transfert-interne",IFERROR(INDEX('Paramètres'!$N:$N,MATCH($D61,'Paramètres'!$M:$M,0))&"",""))),0,IF($L61="Débit",$K61,IF($P61=1,-$K61,0)))) -> 11.11 | R61: =IF($K61="","",IF($L61="Crédit",$K61,-$K61)) -> -11.11 | S61: =IF($C61="","",IFERROR(INDEX('Paramètres'!$H:$H,MATCH($C61,'Paramètres'!$D:$D,0))&"","")) | T61: =IF($K61="","",IF($S61="",0,IF(ISNUMBER(SEARCH("apport-exterieur",IFERROR(INDEX('Paramètres'!$N:$N,MATCH($D61,'Paramètres'!$M:$M,0))&"",""))),0,IF(OR(IFERROR(INDEX('Paramètres'!$I:$I,MATCH($C61,'Paramètres'!$D:$D,0))&"","")="Les deux",IFERROR(INDEX('Paramètres'!$I:$I,MATCH($C61,'Paramètres'!$D:$D,0))&"","")=IF($P61=1,"Débit",$L61)),-IF($P61=1,-$K61,$K61),0)))) -> 0 | U61: =IF($K61="","",IF(ISNUMBER(SEARCH("sortie-epargne",IFERROR(INDEX('Paramètres'!$N:$N,MATCH($D61,'Paramètres'!$M:$M,0))&"",""))),$K61,0)) -> 0 | V61: =IF(AND($A61<>"",$O61=1,$L61="Débit",N($Q61)>0,$A61>=Visualisation!$B$1,$A61<Visualisation!$D$1),MAX($V$1:V60)+1,"")
A62: 45575 | B62: Assurance habitation | C62: Banque A - Courant | D62: Assurance habitation | E62: 22.4 | K62: =IF($E62="","",ROUND($E62*IF(ISNA(MATCH($C62,'Paramètres'!$D:$D,0)),1,IF(INDEX('Paramètres'!$J:$J,MATCH($C62,'Paramètres'!$D:$D,0))="",1,INDEX('Paramètres'!$J:$J,MATCH($C62,'Paramètres'!$D:$D,0)))),2)) -> 22.4 | L62: =IF($D62="","",IF($F62<>"",$F62,IF(ISNA(MATCH($D62,'Paramètres'!$M:$M,0)),"⚠ Type inconnu",IFERROR(INDEX('Paramètres'!$P:$P,MATCH($D62,'Paramètres'!$M:$M,0))&"","")))) -> Débit | M62: =IF($D62="","",IF(ISNA(MATCH($D62,'Paramètres'!$M:$M,0)),"⚠ Type inconnu",IF($L62="Crédit","",IFERROR(INDEX('Paramètres'!$O:$O,MATCH($D62,'Paramètres'!$M:$M,0))&"","")))) -> Dépense Fixe | N62: =IF($D62="","",IFERROR(INDEX('Paramètres'!$Q:$Q,MATCH($D62,'Paramètres'!$M:$M,0))&"","")) -> Assurances | O62: =IF($A62="","",IF(OR($J62<>"x",$A62<=FinReleve),1,0)) -> 1 | P62: =IF($D62="","",IF(AND($L62="Crédit",OR(IFERROR(INDEX('Paramètres'!$O:$O,MATCH($D62,'Paramètres'!$M:$M,0))&"","")<>"",ISNUMBER(SEARCH("remboursement",IFERROR(INDEX('Paramètres'!$N:$N,MATCH($D62,'Paramètres'!$M:$M,0))&"",""))))),1,0)) -> 0 | Q62: =IF($K62="","",IF(ISNUMBER(SEARCH("transfert-interne",IFERROR(INDEX('Paramètres'!$N:$N,MATCH($D62,'Paramètres'!$M:$M,0))&"",""))),0,IF($L62="Débit",$K62,IF($P62=1,-$K62,0)))) -> 22.4 | R62: =IF($K62="","",IF($L62="Crédit",$K62,-$K62)) -> -22.4 | S62: =IF($C62="","",IFERROR(INDEX('Paramètres'!$H:$H,MATCH($C62,'Paramètres'!$D:$D,0))&"","")) | T62: =IF($K62="","",IF($S62="",0,IF(ISNUMBER(SEARCH("apport-exterieur",IFERROR(INDEX('Paramètres'!$N:$N,MATCH($D62,'Paramètres'!$M:$M,0))&"",""))),0,IF(OR(IFERROR(INDEX('Paramètres'!$I:$I,MATCH($C62,'Paramètres'!$D:$D,0))&"","")="Les deux",IFERROR(INDEX('Paramètres'!$I:$I,MATCH($C62,'Paramètres'!$D:$D,0))&"","")=IF($P62=1,"Débit",$L62)),-IF($P62=1,-$K62,$K62),0)))) -> 0 | U62: =IF($K62="","",IF(ISNUMBER(SEARCH("sortie-epargne",IFERROR(INDEX('Paramètres'!$N:$N,MATCH($D62,'Paramètres'!$M:$M,0))&"",""))),$K62,0)) -> 0 | V62: =IF(AND($A62<>"",$O62=1,$L62="Débit",N($Q62)>0,$A62>=Visualisation!$B$1,$A62<Visualisation!$D$1),MAX($V$1:V61)+1,"")
A63: 45575 | B63: Titre restaurant | C63: Titres-restaurant | D63: cantine | E63: 8.43 | G63: Cantine | I63: Villebourg | K63: =IF($E63="","",ROUND($E63*IF(ISNA(MATCH($C63,'Paramètres'!$D:$D,0)),1,IF(INDEX('Paramètres'!$J:$J,MATCH($C63,'Paramètres'!$D:$D,0))="",1,INDEX('Paramètres'!$J:$J,MATCH($C63,'Paramètres'!$D:$D,0)))),2)) -> 8.43 | L63: =IF($D63="","",IF($F63<>"",$F63,IF(ISNA(MATCH($D63,'Paramètres'!$M:$M,0)),"⚠ Type inconnu",IFERROR(INDEX('Paramètres'!$P:$P,MATCH($D63,'Paramètres'!$M:$M,0))&"","")))) -> Débit | M63: =IF($D63="","",IF(ISNA(MATCH($D63,'Paramètres'!$M:$M,0)),"⚠ Type inconnu",IF($L63="Crédit","",IFERROR(INDEX('Paramètres'!$O:$O,MATCH($D63,'Paramètres'!$M:$M,0))&"","")))) -> Dépense Courante | N63: =IF($D63="","",IFERROR(INDEX('Paramètres'!$Q:$Q,MATCH($D63,'Paramètres'!$M:$M,0))&"","")) -> Alimentation | O63: =IF($A63="","",IF(OR($J63<>"x",$A63<=FinReleve),1,0)) -> 1 | P63: =IF($D63="","",IF(AND($L63="Crédit",OR(IFERROR(INDEX('Paramètres'!$O:$O,MATCH($D63,'Paramètres'!$M:$M,0))&"","")<>"",ISNUMBER(SEARCH("remboursement",IFERROR(INDEX('Paramètres'!$N:$N,MATCH($D63,'Paramètres'!$M:$M,0))&"",""))))),1,0)) -> 0 | Q63: =IF($K63="","",IF(ISNUMBER(SEARCH("transfert-interne",IFERROR(INDEX('Paramètres'!$N:$N,MATCH($D63,'Paramètres'!$M:$M,0))&"",""))),0,IF($L63="Débit",$K63,IF($P63=1,-$K63,0)))) -> 8.43 | R63: =IF($K63="","",IF($L63="Crédit",$K63,-$K63)) -> -8.43 | S63: =IF($C63="","",IFERROR(INDEX('Paramètres'!$H:$H,MATCH($C63,'Paramètres'!$D:$D,0))&"","")) | T63: =IF($K63="","",IF($S63="",0,IF(ISNUMBER(SEARCH("apport-exterieur",IFERROR(INDEX('Paramètres'!$N:$N,MATCH($D63,'Paramètres'!$M:$M,0))&"",""))),0,IF(OR(IFERROR(INDEX('Paramètres'!$I:$I,MATCH($C63,'Paramètres'!$D:$D,0))&"","")="Les deux",IFERROR(INDEX('Paramètres'!$I:$I,MATCH($C63,'Paramètres'!$D:$D,0))&"","")=IF($P63=1,"Débit",$L63)),-IF($P63=1,-$K63,$K63),0)))) -> 0 | U63: =IF($K63="","",IF(ISNUMBER(SEARCH("sortie-epargne",IFERROR(INDEX('Paramètres'!$N:$N,MATCH($D63,'Paramètres'!$M:$M,0))&"",""))),$K63,0)) -> 0 | V63: =IF(AND($A63<>"",$O63=1,$L63="Débit",N($Q63)>0,$A63>=Visualisation!$B$1,$A63<Visualisation!$D$1),MAX($V$1:V62)+1,"")
A64: 45576 | B64: Achat carte | C64: Banque B - Compte joint | D64: courses | E64: 163.12 | G64: Boulangerie | I64: Rocheville | K64: =IF($E64="","",ROUND($E64*IF(ISNA(MATCH($C64,'Paramètres'!$D:$D,0)),1,IF(INDEX('Paramètres'!$J:$J,MATCH($C64,'Paramètres'!$D:$D,0))="",1,INDEX('Paramètres'!$J:$J,MATCH($C64,'Paramètres'!$D:$D,0)))),2)) -> 81.56 | L64: =IF($D64="","",IF($F64<>"",$F64,IF(ISNA(MATCH($D64,'Paramètres'!$M:$M,0)),"⚠ Type inconnu",IFERROR(INDEX('Paramètres'!$P:$P,MATCH($D64,'Paramètres'!$M:$M,0))&"","")))) -> Débit | M64: =IF($D64="","",IF(ISNA(MATCH($D64,'Paramètres'!$M:$M,0)),"⚠ Type inconnu",IF($L64="Crédit","",IFERROR(INDEX('Paramètres'!$O:$O,MATCH($D64,'Paramètres'!$M:$M,0))&"","")))) -> Dépense Courante | N64: =IF($D64="","",IFERROR(INDEX('Paramètres'!$Q:$Q,MATCH($D64,'Paramètres'!$M:$M,0))&"","")) -> Alimentation | O64: =IF($A64="","",IF(OR($J64<>"x",$A64<=FinReleve),1,0)) -> 1 | P64: =IF($D64="","",IF(AND($L64="Crédit",OR(IFERROR(INDEX('Paramètres'!$O:$O,MATCH($D64,'Paramètres'!$M:$M,0))&"","")<>"",ISNUMBER(SEARCH("remboursement",IFERROR(INDEX('Paramètres'!$N:$N,MATCH($D64,'Paramètres'!$M:$M,0))&"",""))))),1,0)) -> 0 | Q64: =IF($K64="","",IF(ISNUMBER(SEARCH("transfert-interne",IFERROR(INDEX('Paramètres'!$N:$N,MATCH($D64,'Paramètres'!$M:$M,0))&"",""))),0,IF($L64="Débit",$K64,IF($P64=1,-$K64,0)))) -> 81.56 | R64: =IF($K64="","",IF($L64="Crédit",$K64,-$K64)) -> -81.56 | S64: =IF($C64="","",IFERROR(INDEX('Paramètres'!$H:$H,MATCH($C64,'Paramètres'!$D:$D,0))&"","")) -> Banque A - Courant | T64: =IF($K64="","",IF($S64="",0,IF(ISNUMBER(SEARCH("apport-exterieur",IFERROR(INDEX('Paramètres'!$N:$N,MATCH($D64,'Paramètres'!$M:$M,0))&"",""))),0,IF(OR(IFERROR(INDEX('Paramètres'!$I:$I,MATCH($C64,'Paramètres'!$D:$D,0))&"","")="Les deux",IFERROR(INDEX('Paramètres'!$I:$I,MATCH($C64,'Paramètres'!$D:$D,0))&"","")=IF($P64=1,"Débit",$L64)),-IF($P64=1,-$K64,$K64),0)))) -> 0 | U64: =IF($K64="","",IF(ISNUMBER(SEARCH("sortie-epargne",IFERROR(INDEX('Paramètres'!$N:$N,MATCH($D64,'Paramètres'!$M:$M,0))&"",""))),$K64,0)) -> 0 | V64: =IF(AND($A64<>"",$O64=1,$L64="Débit",N($Q64)>0,$A64>=Visualisation!$B$1,$A64<Visualisation!$D$1),MAX($V$1:V63)+1,"")
A65: 45576 | B65: Achat carte | C65: Banque B - Compte joint | D65: courses | E65: 114.72 | G65: Boulangerie | I65: Villebourg | K65: =IF($E65="","",ROUND($E65*IF(ISNA(MATCH($C65,'Paramètres'!$D:$D,0)),1,IF(INDEX('Paramètres'!$J:$J,MATCH($C65,'Paramètres'!$D:$D,0))="",1,INDEX('Paramètres'!$J:$J,MATCH($C65,'Paramètres'!$D:$D,0)))),2)) -> 57.36 | L65: =IF($D65="","",IF($F65<>"",$F65,IF(ISNA(MATCH($D65,'Paramètres'!$M:$M,0)),"⚠ Type inconnu",IFERROR(INDEX('Paramètres'!$P:$P,MATCH($D65,'Paramètres'!$M:$M,0))&"","")))) -> Débit | M65: =IF($D65="","",IF(ISNA(MATCH($D65,'Paramètres'!$M:$M,0)),"⚠ Type inconnu",IF($L65="Crédit","",IFERROR(INDEX('Paramètres'!$O:$O,MATCH($D65,'Paramètres'!$M:$M,0))&"","")))) -> Dépense Courante | N65: =IF($D65="","",IFERROR(INDEX('Paramètres'!$Q:$Q,MATCH($D65,'Paramètres'!$M:$M,0))&"","")) -> Alimentation | O65: =IF($A65="","",IF(OR($J65<>"x",$A65<=FinReleve),1,0)) -> 1 | P65: =IF($D65="","",IF(AND($L65="Crédit",OR(IFERROR(INDEX('Paramètres'!$O:$O,MATCH($D65,'Paramètres'!$M:$M,0))&"","")<>"",ISNUMBER(SEARCH("remboursement",IFERROR(INDEX('Paramètres'!$N:$N,MATCH($D65,'Paramètres'!$M:$M,0))&"",""))))),1,0)) -> 0 | Q65: =IF($K65="","",IF(ISNUMBER(SEARCH("transfert-interne",IFERROR(INDEX('Paramètres'!$N:$N,MATCH($D65,'Paramètres'!$M:$M,0))&"",""))),0,IF($L65="Débit",$K65,IF($P65=1,-$K65,0)))) -> 57.36 | R65: =IF($K65="","",IF($L65="Crédit",$K65,-$K65)) -> -57.36 | S65: =IF($C65="","",IFERROR(INDEX('Paramètres'!$H:$H,MATCH($C65,'Paramètres'!$D:$D,0))&"","")) -> Banque A - Courant | T65: =IF($K65="","",IF($S65="",0,IF(ISNUMBER(SEARCH("apport-exterieur",IFERROR(INDEX('Paramètres'!$N:$N,MATCH($D65,'Paramètres'!$M:$M,0))&"",""))),0,IF(OR(IFERROR(INDEX('Paramètres'!$I:$I,MATCH($C65,'Paramètres'!$D:$D,0))&"","")="Les deux",IFERROR(INDEX('Paramètres'!$I:$I,MATCH($C65,'Paramètres'!$D:$D,0))&"","")=IF($P65=1,"Débit",$L65)),-IF($P65=1,-$K65,$K65),0)))) -> 0 | U65: =IF($K65="","",IF(ISNUMBER(SEARCH("sortie-epargne",IFERROR(INDEX('Paramètres'!$N:$N,MATCH($D65,'Paramètres'!$M:$M,0))&"",""))),$K65,0)) -> 0 | V65: =IF(AND($A65<>"",$O65=1,$L65="Débit",N($Q65)>0,$A65>=Visualisation!$B$1,$A65<Visualisation!$D$1),MAX($V$1:V64)+1,"")
A66: 45576 | B66: Restaurant | C66: Banque A - Part commune | D66: Restaurant | E66: 60.42 | G66: Restaurant | H66: Anniversaire | I66: Villebourg-sur-Rive | K66: =IF($E66="","",ROUND($E66*IF(ISNA(MATCH($C66,'Paramètres'!$D:$D,0)),1,IF(INDEX('Paramètres'!$J:$J,MATCH($C66,'Paramètres'!$D:$D,0))="",1,INDEX('Paramètres'!$J:$J,MATCH($C66,'Paramètres'!$D:$D,0)))),2)) -> 30.21 | L66: =IF($D66="","",IF($F66<>"",$F66,IF(ISNA(MATCH($D66,'Paramètres'!$M:$M,0)),"⚠ Type inconnu",IFERROR(INDEX('Paramètres'!$P:$P,MATCH($D66,'Paramètres'!$M:$M,0))&"","")))) -> Débit | M66: =IF($D66="","",IF(ISNA(MATCH($D66,'Paramètres'!$M:$M,0)),"⚠ Type inconnu",IF($L66="Crédit","",IFERROR(INDEX('Paramètres'!$O:$O,MATCH($D66,'Paramètres'!$M:$M,0))&"","")))) -> Dépense Occasionnelle | N66: =IF($D66="","",IFERROR(INDEX('Paramètres'!$Q:$Q,MATCH($D66,'Paramètres'!$M:$M,0))&"","")) -> Alimentation | O66: =IF($A66="","",IF(OR($J66<>"x",$A66<=FinReleve),1,0)) -> 1 | P66: =IF($D66="","",IF(AND($L66="Crédit",OR(IFERROR(INDEX('Paramètres'!$O:$O,MATCH($D66,'Paramètres'!$M:$M,0))&"","")<>"",ISNUMBER(SEARCH("remboursement",IFERROR(INDEX('Paramètres'!$N:$N,MATCH($D66,'Paramètres'!$M:$M,0))&"",""))))),1,0)) -> 0 | Q66: =IF($K66="","",IF(ISNUMBER(SEARCH("transfert-interne",IFERROR(INDEX('Paramètres'!$N:$N,MATCH($D66,'Paramètres'!$M:$M,0))&"",""))),0,IF($L66="Débit",$K66,IF($P66=1,-$K66,0)))) -> 30.21 | R66: =IF($K66="","",IF($L66="Crédit",$K66,-$K66)) -> -30.21 | S66: =IF($C66="","",IFERROR(INDEX('Paramètres'!$H:$H,MATCH($C66,'Paramètres'!$D:$D,0))&"","")) -> Banque A - Courant | T66: =IF($K66="","",IF($S66="",0,IF(ISNUMBER(SEARCH("apport-exterieur",IFERROR(INDEX('Paramètres'!$N:$N,MATCH($D66,'Paramètres'!$M:$M,0))&"",""))),0,IF(OR(IFERROR(INDEX('Paramètres'!$I:$I,MATCH($C66,'Paramètres'!$D:$D,0))&"","")="Les deux",IFERROR(INDEX('Paramètres'!$I:$I,MATCH($C66,'Paramètres'!$D:$D,0))&"","")=IF($P66=1,"Débit",$L66)),-IF($P66=1,-$K66,$K66),0)))) -> -30.21 | U66: =IF($K66="","",IF(ISNUMBER(SEARCH("sortie-epargne",IFERROR(INDEX('Paramètres'!$N:$N,MATCH($D66,'Paramètres'!$M:$M,0))&"",""))),$K66,0)) -> 0 | V66: =IF(AND($A66<>"",$O66=1,$L66="Débit",N($Q66)>0,$A66>=Visualisation!$B$1,$A66<Visualisation!$D$1),MAX($V$1:V65)+1,"")
A67: 45577 | B67: Assurance auto | C67: Banque A - Courant | D67: Assurance auto | E67: 47.9 | K67: =IF($E67="","",ROUND($E67*IF(ISNA(MATCH($C67,'Paramètres'!$D:$D,0)),1,IF(INDEX('Paramètres'!$J:$J,MATCH($C67,'Paramètres'!$D:$D,0))="",1,INDEX('Paramètres'!$J:$J,MATCH($C67,'Paramètres'!$D:$D,0)))),2)) -> 47.9 | L67: =IF($D67="","",IF($F67<>"",$F67,IF(ISNA(MATCH($D67,'Paramètres'!$M:$M,0)),"⚠ Type inconnu",IFERROR(INDEX('Paramètres'!$P:$P,MATCH($D67,'Paramètres'!$M:$M,0))&"","")))) -> Débit | M67: =IF($D67="","",IF(ISNA(MATCH($D67,'Paramètres'!$M:$M,0)),"⚠ Type inconnu",IF($L67="Crédit","",IFERROR(INDEX('Paramètres'!$O:$O,MATCH($D67,'Paramètres'!$M:$M,0))&"","")))) -> Dépense Fixe | N67: =IF($D67="","",IFERROR(INDEX('Paramètres'!$Q:$Q,MATCH($D67,'Paramètres'!$M:$M,0))&"","")) -> Assurances | O67: =IF($A67="","",IF(OR($J67<>"x",$A67<=FinReleve),1,0)) -> 1 | P67: =IF($D67="","",IF(AND($L67="Crédit",OR(IFERROR(INDEX('Paramètres'!$O:$O,MATCH($D67,'Paramètres'!$M:$M,0))&"","")<>"",ISNUMBER(SEARCH("remboursement",IFERROR(INDEX('Paramètres'!$N:$N,MATCH($D67,'Paramètres'!$M:$M,0))&"",""))))),1,0)) -> 0 | Q67: =IF($K67="","",IF(ISNUMBER(SEARCH("transfert-interne",IFERROR(INDEX('Paramètres'!$N:$N,MATCH($D67,'Paramètres'!$M:$M,0))&"",""))),0,IF($L67="Débit",$K67,IF($P67=1,-$K67,0)))) -> 47.9 | R67: =IF($K67="","",IF($L67="Crédit",$K67,-$K67)) -> -47.9 | S67: =IF($C67="","",IFERROR(INDEX('Paramètres'!$H:$H,MATCH($C67,'Paramètres'!$D:$D,0))&"","")) | T67: =IF($K67="","",IF($S67="",0,IF(ISNUMBER(SEARCH("apport-exterieur",IFERROR(INDEX('Paramètres'!$N:$N,MATCH($D67,'Paramètres'!$M:$M,0))&"",""))),0,IF(OR(IFERROR(INDEX('Paramètres'!$I:$I,MATCH($C67,'Paramètres'!$D:$D,0))&"","")="Les deux",IFERROR(INDEX('Paramètres'!$I:$I,MATCH($C67,'Paramètres'!$D:$D,0))&"","")=IF($P67=1,"Débit",$L67)),-IF($P67=1,-$K67,$K67),0)))) -> 0 | U67: =IF($K67="","",IF(ISNUMBER(SEARCH("sortie-epargne",IFERROR(INDEX('Paramètres'!$N:$N,MATCH($D67,'Paramètres'!$M:$M,0))&"",""))),$K67,0)) -> 0 | V67: =IF(AND($A67<>"",$O67=1,$L67="Débit",N($Q67)>0,$A67>=Visualisation!$B$1,$A67<Visualisation!$D$1),MAX($V$1:V66)+1,"")
A68: 45578 | B68: Titre restaurant | C68: Titres-restaurant | D68: cantine | E68: 7.72 | G68: Cantine | I68: Villebourg-sur-Rive | K68: =IF($E68="","",ROUND($E68*IF(ISNA(MATCH($C68,'Paramètres'!$D:$D,0)),1,IF(INDEX('Paramètres'!$J:$J,MATCH($C68,'Paramètres'!$D:$D,0))="",1,INDEX('Paramètres'!$J:$J,MATCH($C68,'Paramètres'!$D:$D,0)))),2)) -> 7.72 | L68: =IF($D68="","",IF($F68<>"",$F68,IF(ISNA(MATCH($D68,'Paramètres'!$M:$M,0)),"⚠ Type inconnu",IFERROR(INDEX('Paramètres'!$P:$P,MATCH($D68,'Paramètres'!$M:$M,0))&"","")))) -> Débit | M68: =IF($D68="","",IF(ISNA(MATCH($D68,'Paramètres'!$M:$M,0)),"⚠ Type inconnu",IF($L68="Crédit","",IFERROR(INDEX('Paramètres'!$O:$O,MATCH($D68,'Paramètres'!$M:$M,0))&"","")))) -> Dépense Courante | N68: =IF($D68="","",IFERROR(INDEX('Paramètres'!$Q:$Q,MATCH($D68,'Paramètres'!$M:$M,0))&"","")) -> Alimentation | O68: =IF($A68="","",IF(OR($J68<>"x",$A68<=FinReleve),1,0)) -> 1 | P68: =IF($D68="","",IF(AND($L68="Crédit",OR(IFERROR(INDEX('Paramètres'!$O:$O,MATCH($D68,'Paramètres'!$M:$M,0))&"","")<>"",ISNUMBER(SEARCH("remboursement",IFERROR(INDEX('Paramètres'!$N:$N,MATCH($D68,'Paramètres'!$M:$M,0))&"",""))))),1,0)) -> 0 | Q68: =IF($K68="","",IF(ISNUMBER(SEARCH("transfert-interne",IFERROR(INDEX('Paramètres'!$N:$N,MATCH($D68,'Paramètres'!$M:$M,0))&"",""))),0,IF($L68="Débit",$K68,IF($P68=1,-$K68,0)))) -> 7.72 | R68: =IF($K68="","",IF($L68="Crédit",$K68,-$K68)) -> -7.72 | S68: =IF($C68="","",IFERROR(INDEX('Paramètres'!$H:$H,MATCH($C68,'Paramètres'!$D:$D,0))&"","")) | T68: =IF($K68="","",IF($S68="",0,IF(ISNUMBER(SEARCH("apport-exterieur",IFERROR(INDEX('Paramètres'!$N:$N,MATCH($D68,'Paramètres'!$M:$M,0))&"",""))),0,IF(OR(IFERROR(INDEX('Paramètres'!$I:$I,MATCH($C68,'Paramètres'!$D:$D,0))&"","")="Les deux",IFERROR(INDEX('Paramètres'!$I:$I,MATCH($C68,'Paramètres'!$D:$D,0))&"","")=IF($P68=1,"Débit",$L68)),-IF($P68=1,-$K68,$K68),0)))) -> 0 | U68: =IF($K68="","",IF(ISNUMBER(SEARCH("sortie-epargne",IFERROR(INDEX('Paramètres'!$N:$N,MATCH($D68,'Paramètres'!$M:$M,0))&"",""))),$K68,0)) -> 0 | V68: =IF(AND($A68<>"",$O68=1,$L68="Débit",N($Q68)>0,$A68>=Visualisation!$B$1,$A68<Visualisation!$D$1),MAX($V$1:V67)+1,"")
A69: 45579 | B69: Achat carte | C69: Banque A - Part commune | D69: courses | E69: 59.3 | G69: Boulangerie | I69: Villebourg-sur-Rive | K69: =IF($E69="","",ROUND($E69*IF(ISNA(MATCH($C69,'Paramètres'!$D:$D,0)),1,IF(INDEX('Paramètres'!$J:$J,MATCH($C69,'Paramètres'!$D:$D,0))="",1,INDEX('Paramètres'!$J:$J,MATCH($C69,'Paramètres'!$D:$D,0)))),2)) -> 29.65 | L69: =IF($D69="","",IF($F69<>"",$F69,IF(ISNA(MATCH($D69,'Paramètres'!$M:$M,0)),"⚠ Type inconnu",IFERROR(INDEX('Paramètres'!$P:$P,MATCH($D69,'Paramètres'!$M:$M,0))&"","")))) -> Débit | M69: =IF($D69="","",IF(ISNA(MATCH($D69,'Paramètres'!$M:$M,0)),"⚠ Type inconnu",IF($L69="Crédit","",IFERROR(INDEX('Paramètres'!$O:$O,MATCH($D69,'Paramètres'!$M:$M,0))&"","")))) -> Dépense Courante | N69: =IF($D69="","",IFERROR(INDEX('Paramètres'!$Q:$Q,MATCH($D69,'Paramètres'!$M:$M,0))&"","")) -> Alimentation | O69: =IF($A69="","",IF(OR($J69<>"x",$A69<=FinReleve),1,0)) -> 1 | P69: =IF($D69="","",IF(AND($L69="Crédit",OR(IFERROR(INDEX('Paramètres'!$O:$O,MATCH($D69,'Paramètres'!$M:$M,0))&"","")<>"",ISNUMBER(SEARCH("remboursement",IFERROR(INDEX('Paramètres'!$N:$N,MATCH($D69,'Paramètres'!$M:$M,0))&"",""))))),1,0)) -> 0 | Q69: =IF($K69="","",IF(ISNUMBER(SEARCH("transfert-interne",IFERROR(INDEX('Paramètres'!$N:$N,MATCH($D69,'Paramètres'!$M:$M,0))&"",""))),0,IF($L69="Débit",$K69,IF($P69=1,-$K69,0)))) -> 29.65 | R69: =IF($K69="","",IF($L69="Crédit",$K69,-$K69)) -> -29.65 | S69: =IF($C69="","",IFERROR(INDEX('Paramètres'!$H:$H,MATCH($C69,'Paramètres'!$D:$D,0))&"","")) -> Banque A - Courant | T69: =IF($K69="","",IF($S69="",0,IF(ISNUMBER(SEARCH("apport-exterieur",IFERROR(INDEX('Paramètres'!$N:$N,MATCH($D69,'Paramètres'!$M:$M,0))&"",""))),0,IF(OR(IFERROR(INDEX('Paramètres'!$I:$I,MATCH($C69,'Paramètres'!$D:$D,0))&"","")="Les deux",IFERROR(INDEX('Paramètres'!$I:$I,MATCH($C69,'Paramètres'!$D:$D,0))&"","")=IF($P69=1,"Débit",$L69)),-IF($P69=1,-$K69,$K69),0)))) -> -29.65 | U69: =IF($K69="","",IF(ISNUMBER(SEARCH("sortie-epargne",IFERROR(INDEX('Paramètres'!$N:$N,MATCH($D69,'Paramètres'!$M:$M,0))&"",""))),$K69,0)) -> 0 | V69: =IF(AND($A69<>"",$O69=1,$L69="Débit",N($Q69)>0,$A69>=Visualisation!$B$1,$A69<Visualisation!$D$1),MAX($V$1:V68)+1,"")
A70: 45579 | B70: Cadeaux | C70: Banque A - Part commune | D70: Cadeaux | E70: 200.8 | G70: Café | H70: Anniversaire | I70: Villebourg | K70: =IF($E70="","",ROUND($E70*IF(ISNA(MATCH($C70,'Paramètres'!$D:$D,0)),1,IF(INDEX('Paramètres'!$J:$J,MATCH($C70,'Paramètres'!$D:$D,0))="",1,INDEX('Paramètres'!$J:$J,MATCH($C70,'Paramètres'!$D:$D,0)))),2)) -> 100.4 | L70: =IF($D70="","",IF($F70<>"",$F70,IF(ISNA(MATCH($D70,'Paramètres'!$M:$M,0)),"⚠ Type inconnu",IFERROR(INDEX('Paramètres'!$P:$P,MATCH($D70,'Paramètres'!$M:$M,0))&"","")))) -> Débit | M70: =IF($D70="","",IF(ISNA(MATCH($D70,'Paramètres'!$M:$M,0)),"⚠ Type inconnu",IF($L70="Crédit","",IFERROR(INDEX('Paramètres'!$O:$O,MATCH($D70,'Paramètres'!$M:$M,0))&"","")))) -> Dépense Occasionnelle | N70: =IF($D70="","",IFERROR(INDEX('Paramètres'!$Q:$Q,MATCH($D70,'Paramètres'!$M:$M,0))&"","")) -> Autre | O70: =IF($A70="","",IF(OR($J70<>"x",$A70<=FinReleve),1,0)) -> 1 | P70: =IF($D70="","",IF(AND($L70="Crédit",OR(IFERROR(INDEX('Paramètres'!$O:$O,MATCH($D70,'Paramètres'!$M:$M,0))&"","")<>"",ISNUMBER(SEARCH("remboursement",IFERROR(INDEX('Paramètres'!$N:$N,MATCH($D70,'Paramètres'!$M:$M,0))&"",""))))),1,0)) -> 0 | Q70: =IF($K70="","",IF(ISNUMBER(SEARCH("transfert-interne",IFERROR(INDEX('Paramètres'!$N:$N,MATCH($D70,'Paramètres'!$M:$M,0))&"",""))),0,IF($L70="Débit",$K70,IF($P70=1,-$K70,0)))) -> 100.4 | R70: =IF($K70="","",IF($L70="Crédit",$K70,-$K70)) -> -100.4 | S70: =IF($C70="","",IFERROR(INDEX('Paramètres'!$H:$H,MATCH($C70,'Paramètres'!$D:$D,0))&"","")) -> Banque A - Courant | T70: =IF($K70="","",IF($S70="",0,IF(ISNUMBER(SEARCH("apport-exterieur",IFERROR(INDEX('Paramètres'!$N:$N,MATCH($D70,'Paramètres'!$M:$M,0))&"",""))),0,IF(OR(IFERROR(INDEX('Paramètres'!$I:$I,MATCH($C70,'Paramètres'!$D:$D,0))&"","")="Les deux",IFERROR(INDEX('Paramètres'!$I:$I,MATCH($C70,'Paramètres'!$D:$D,0))&"","")=IF($P70=1,"Débit",$L70)),-IF($P70=1,-$K70,$K70),0)))) -> -100.4 | U70: =IF($K70="","",IF(ISNUMBER(SEARCH("sortie-epargne",IFERROR(INDEX('Paramètres'!$N:$N,MATCH($D70,'Paramètres'!$M:$M,0))&"",""))),$K70,0)) -> 0 | V70: =IF(AND($A70<>"",$O70=1,$L70="Débit",N($Q70)>0,$A70>=Visualisation!$B$1,$A70<Visualisation!$D$1),MAX($V$1:V69)+1,"")
A71: 45580 | B71: Electricité | C71: Banque C - Compte joint | D71: Electricité | E71: 63.83 | K71: =IF($E71="","",ROUND($E71*IF(ISNA(MATCH($C71,'Paramètres'!$D:$D,0)),1,IF(INDEX('Paramètres'!$J:$J,MATCH($C71,'Paramètres'!$D:$D,0))="",1,INDEX('Paramètres'!$J:$J,MATCH($C71,'Paramètres'!$D:$D,0)))),2)) -> 63.83 | L71: =IF($D71="","",IF($F71<>"",$F71,IF(ISNA(MATCH($D71,'Paramètres'!$M:$M,0)),"⚠ Type inconnu",IFERROR(INDEX('Paramètres'!$P:$P,MATCH($D71,'Paramètres'!$M:$M,0))&"","")))) -> Débit | M71: =IF($D71="","",IF(ISNA(MATCH($D71,'Paramètres'!$M:$M,0)),"⚠ Type inconnu",IF($L71="Crédit","",IFERROR(INDEX('Paramètres'!$O:$O,MATCH($D71,'Paramètres'!$M:$M,0))&"","")))) -> Dépense Fixe | N71: =IF($D71="","",IFERROR(INDEX('Paramètres'!$Q:$Q,MATCH($D71,'Paramètres'!$M:$M,0))&"","")) -> Immobilier | O71: =IF($A71="","",IF(OR($J71<>"x",$A71<=FinReleve),1,0)) -> 1 | P71: =IF($D71="","",IF(AND($L71="Crédit",OR(IFERROR(INDEX('Paramètres'!$O:$O,MATCH($D71,'Paramètres'!$M:$M,0))&"","")<>"",ISNUMBER(SEARCH("remboursement",IFERROR(INDEX('Paramètres'!$N:$N,MATCH($D71,'Paramètres'!$M:$M,0))&"",""))))),1,0)) -> 0 | Q71: =IF($K71="","",IF(ISNUMBER(SEARCH("transfert-interne",IFERROR(INDEX('Paramètres'!$N:$N,MATCH($D71,'Paramètres'!$M:$M,0))&"",""))),0,IF($L71="Débit",$K71,IF($P71=1,-$K71,0)))) -> 63.83 | R71: =IF($K71="","",IF($L71="Crédit",$K71,-$K71)) -> -63.83 | S71: =IF($C71="","",IFERROR(INDEX('Paramètres'!$H:$H,MATCH($C71,'Paramètres'!$D:$D,0))&"","")) -> Banque A - Courant | T71: =IF($K71="","",IF($S71="",0,IF(ISNUMBER(SEARCH("apport-exterieur",IFERROR(INDEX('Paramètres'!$N:$N,MATCH($D71,'Paramètres'!$M:$M,0))&"",""))),0,IF(OR(IFERROR(INDEX('Paramètres'!$I:$I,MATCH($C71,'Paramètres'!$D:$D,0))&"","")="Les deux",IFERROR(INDEX('Paramètres'!$I:$I,MATCH($C71,'Paramètres'!$D:$D,0))&"","")=IF($P71=1,"Débit",$L71)),-IF($P71=1,-$K71,$K71),0)))) -> 0 | U71: =IF($K71="","",IF(ISNUMBER(SEARCH("sortie-epargne",IFERROR(INDEX('Paramètres'!$N:$N,MATCH($D71,'Paramètres'!$M:$M,0))&"",""))),$K71,0)) -> 0 | V71: =IF(AND($A71<>"",$O71=1,$L71="Débit",N($Q71)>0,$A71>=Visualisation!$B$1,$A71<Visualisation!$D$1),MAX($V$1:V70)+1,"")
A72: 45580 | B72: Achat carte | C72: Banque A - Part commune | D72: courses | E72: 58.76 | G72: Boulangerie | K72: =IF($E72="","",ROUND($E72*IF(ISNA(MATCH($C72,'Paramètres'!$D:$D,0)),1,IF(INDEX('Paramètres'!$J:$J,MATCH($C72,'Paramètres'!$D:$D,0))="",1,INDEX('Paramètres'!$J:$J,MATCH($C72,'Paramètres'!$D:$D,0)))),2)) -> 29.38 | L72: =IF($D72="","",IF($F72<>"",$F72,IF(ISNA(MATCH($D72,'Paramètres'!$M:$M,0)),"⚠ Type inconnu",IFERROR(INDEX('Paramètres'!$P:$P,MATCH($D72,'Paramètres'!$M:$M,0))&"","")))) -> Débit | M72: =IF($D72="","",IF(ISNA(MATCH($D72,'Paramètres'!$M:$M,0)),"⚠ Type inconnu",IF($L72="Crédit","",IFERROR(INDEX('Paramètres'!$O:$O,MATCH($D72,'Paramètres'!$M:$M,0))&"","")))) -> Dépense Courante | N72: =IF($D72="","",IFERROR(INDEX('Paramètres'!$Q:$Q,MATCH($D72,'Paramètres'!$M:$M,0))&"","")) -> Alimentation | O72: =IF($A72="","",IF(OR($J72<>"x",$A72<=FinReleve),1,0)) -> 1 | P72: =IF($D72="","",IF(AND($L72="Crédit",OR(IFERROR(INDEX('Paramètres'!$O:$O,MATCH($D72,'Paramètres'!$M:$M,0))&"","")<>"",ISNUMBER(SEARCH("remboursement",IFERROR(INDEX('Paramètres'!$N:$N,MATCH($D72,'Paramètres'!$M:$M,0))&"",""))))),1,0)) -> 0 | Q72: =IF($K72="","",IF(ISNUMBER(SEARCH("transfert-interne",IFERROR(INDEX('Paramètres'!$N:$N,MATCH($D72,'Paramètres'!$M:$M,0))&"",""))),0,IF($L72="Débit",$K72,IF($P72=1,-$K72,0)))) -> 29.38 | R72: =IF($K72="","",IF($L72="Crédit",$K72,-$K72)) -> -29.38 | S72: =IF($C72="","",IFERROR(INDEX('Paramètres'!$H:$H,MATCH($C72,'Paramètres'!$D:$D,0))&"","")) -> Banque A - Courant | T72: =IF($K72="","",IF($S72="",0,IF(ISNUMBER(SEARCH("apport-exterieur",IFERROR(INDEX('Paramètres'!$N:$N,MATCH($D72,'Paramètres'!$M:$M,0))&"",""))),0,IF(OR(IFERROR(INDEX('Paramètres'!$I:$I,MATCH($C72,'Paramètres'!$D:$D,0))&"","")="Les deux",IFERROR(INDEX('Paramètres'!$I:$I,MATCH($C72,'Paramètres'!$D:$D,0))&"","")=IF($P72=1,"Débit",$L72)),-IF($P72=1,-$K72,$K72),0)))) -> -29.38 | U72: =IF($K72="","",IF(ISNUMBER(SEARCH("sortie-epargne",IFERROR(INDEX('Paramètres'!$N:$N,MATCH($D72,'Paramètres'!$M:$M,0))&"",""))),$K72,0)) -> 0 | V72: =IF(AND($A72<>"",$O72=1,$L72="Débit",N($Q72)>0,$A72>=Visualisation!$B$1,$A72<Visualisation!$D$1),MAX($V$1:V71)+1,"")
A73: 45580 | B73: Restaurant | C73: Banque A - Part commune | D73: Restaurant | E73: 48.12 | G73: Pressing | H73: Anniversaire | I73: Villebourg-sur-Rive | K73: =IF($E73="","",ROUND($E73*IF(ISNA(MATCH($C73,'Paramètres'!$D:$D,0)),1,IF(INDEX('Paramètres'!$J:$J,MATCH($C73,'Paramètres'!$D:$D,0))="",1,INDEX('Paramètres'!$J:$J,MATCH($C73,'Paramètres'!$D:$D,0)))),2)) -> 24.06 | L73: =IF($D73="","",IF($F73<>"",$F73,IF(ISNA(MATCH($D73,'Paramètres'!$M:$M,0)),"⚠ Type inconnu",IFERROR(INDEX('Paramètres'!$P:$P,MATCH($D73,'Paramètres'!$M:$M,0))&"","")))) -> Débit | M73: =IF($D73="","",IF(ISNA(MATCH($D73,'Paramètres'!$M:$M,0)),"⚠ Type inconnu",IF($L73="Crédit","",IFERROR(INDEX('Paramètres'!$O:$O,MATCH($D73,'Paramètres'!$M:$M,0))&"","")))) -> Dépense Occasionnelle | N73: =IF($D73="","",IFERROR(INDEX('Paramètres'!$Q:$Q,MATCH($D73,'Paramètres'!$M:$M,0))&"","")) -> Alimentation | O73: =IF($A73="","",IF(OR($J73<>"x",$A73<=FinReleve),1,0)) -> 1 | P73: =IF($D73="","",IF(AND($L73="Crédit",OR(IFERROR(INDEX('Paramètres'!$O:$O,MATCH($D73,'Paramètres'!$M:$M,0))&"","")<>"",ISNUMBER(SEARCH("remboursement",IFERROR(INDEX('Paramètres'!$N:$N,MATCH($D73,'Paramètres'!$M:$M,0))&"",""))))),1,0)) -> 0 | Q73: =IF($K73="","",IF(ISNUMBER(SEARCH("transfert-interne",IFERROR(INDEX('Paramètres'!$N:$N,MATCH($D73,'Paramètres'!$M:$M,0))&"",""))),0,IF($L73="Débit",$K73,IF($P73=1,-$K73,0)))) -> 24.06 | R73: =IF($K73="","",IF($L73="Crédit",$K73,-$K73)) -> -24.06 | S73: =IF($C73="","",IFERROR(INDEX('Paramètres'!$H:$H,MATCH($C73,'Paramètres'!$D:$D,0))&"","")) -> Banque A - Courant | T73: =IF($K73="","",IF($S73="",0,IF(ISNUMBER(SEARCH("apport-exterieur",IFERROR(INDEX('Paramètres'!$N:$N,MATCH($D73,'Paramètres'!$M:$M,0))&"",""))),0,IF(OR(IFERROR(INDEX('Paramètres'!$I:$I,MATCH($C73,'Paramètres'!$D:$D,0))&"","")="Les deux",IFERROR(INDEX('Paramètres'!$I:$I,MATCH($C73,'Paramètres'!$D:$D,0))&"","")=IF($P73=1,"Débit",$L73)),-IF($P73=1,-$K73,$K73),0)))) -> -24.06 | U73: =IF($K73="","",IF(ISNUMBER(SEARCH("sortie-epargne",IFERROR(INDEX('Paramètres'!$N:$N,MATCH($D73,'Paramètres'!$M:$M,0))&"",""))),$K73,0)) -> 0 | V73: =IF(AND($A73<>"",$O73=1,$L73="Débit",N($Q73)>0,$A73>=Visualisation!$B$1,$A73<Visualisation!$D$1),MAX($V$1:V72)+1,"")
A74: 45583 | B74: Impôt sur Revenu | C74: Banque A - Courant | D74: Impôt sur Revenu | E74: 212 | K74: =IF($E74="","",ROUND($E74*IF(ISNA(MATCH($C74,'Paramètres'!$D:$D,0)),1,IF(INDEX('Paramètres'!$J:$J,MATCH($C74,'Paramètres'!$D:$D,0))="",1,INDEX('Paramètres'!$J:$J,MATCH($C74,'Paramètres'!$D:$D,0)))),2)) -> 212 | L74: =IF($D74="","",IF($F74<>"",$F74,IF(ISNA(MATCH($D74,'Paramètres'!$M:$M,0)),"⚠ Type inconnu",IFERROR(INDEX('Paramètres'!$P:$P,MATCH($D74,'Paramètres'!$M:$M,0))&"","")))) -> Débit | M74: =IF($D74="","",IF(ISNA(MATCH($D74,'Paramètres'!$M:$M,0)),"⚠ Type inconnu",IF($L74="Crédit","",IFERROR(INDEX('Paramètres'!$O:$O,MATCH($D74,'Paramètres'!$M:$M,0))&"","")))) -> Dépense Fixe | N74: =IF($D74="","",IFERROR(INDEX('Paramètres'!$Q:$Q,MATCH($D74,'Paramètres'!$M:$M,0))&"","")) -> Impots | O74: =IF($A74="","",IF(OR($J74<>"x",$A74<=FinReleve),1,0)) -> 1 | P74: =IF($D74="","",IF(AND($L74="Crédit",OR(IFERROR(INDEX('Paramètres'!$O:$O,MATCH($D74,'Paramètres'!$M:$M,0))&"","")<>"",ISNUMBER(SEARCH("remboursement",IFERROR(INDEX('Paramètres'!$N:$N,MATCH($D74,'Paramètres'!$M:$M,0))&"",""))))),1,0)) -> 0 | Q74: =IF($K74="","",IF(ISNUMBER(SEARCH("transfert-interne",IFERROR(INDEX('Paramètres'!$N:$N,MATCH($D74,'Paramètres'!$M:$M,0))&"",""))),0,IF($L74="Débit",$K74,IF($P74=1,-$K74,0)))) -> 212 | R74: =IF($K74="","",IF($L74="Crédit",$K74,-$K74)) -> -212 | S74: =IF($C74="","",IFERROR(INDEX('Paramètres'!$H:$H,MATCH($C74,'Paramètres'!$D:$D,0))&"","")) | T74: =IF($K74="","",IF($S74="",0,IF(ISNUMBER(SEARCH("apport-exterieur",IFERROR(INDEX('Paramètres'!$N:$N,MATCH($D74,'Paramètres'!$M:$M,0))&"",""))),0,IF(OR(IFERROR(INDEX('Paramètres'!$I:$I,MATCH($C74,'Paramètres'!$D:$D,0))&"","")="Les deux",IFERROR(INDEX('Paramètres'!$I:$I,MATCH($C74,'Paramètres'!$D:$D,0))&"","")=IF($P74=1,"Débit",$L74)),-IF($P74=1,-$K74,$K74),0)))) -> 0 | U74: =IF($K74="","",IF(ISNUMBER(SEARCH("sortie-epargne",IFERROR(INDEX('Paramètres'!$N:$N,MATCH($D74,'Paramètres'!$M:$M,0))&"",""))),$K74,0)) -> 0 | V74: =IF(AND($A74<>"",$O74=1,$L74="Débit",N($Q74)>0,$A74>=Visualisation!$B$1,$A74<Visualisation!$D$1),MAX($V$1:V73)+1,"")
A75: 45583 | B75: Achat carte | C75: Banque A - Part commune | D75: courses | E75: 99.66 | G75: Supermarché Ouest | I75: Villebourg-sur-Rive | K75: =IF($E75="","",ROUND($E75*IF(ISNA(MATCH($C75,'Paramètres'!$D:$D,0)),1,IF(INDEX('Paramètres'!$J:$J,MATCH($C75,'Paramètres'!$D:$D,0))="",1,INDEX('Paramètres'!$J:$J,MATCH($C75,'Paramètres'!$D:$D,0)))),2)) -> 49.83 | L75: =IF($D75="","",IF($F75<>"",$F75,IF(ISNA(MATCH($D75,'Paramètres'!$M:$M,0)),"⚠ Type inconnu",IFERROR(INDEX('Paramètres'!$P:$P,MATCH($D75,'Paramètres'!$M:$M,0))&"","")))) -> Débit | M75: =IF($D75="","",IF(ISNA(MATCH($D75,'Paramètres'!$M:$M,0)),"⚠ Type inconnu",IF($L75="Crédit","",IFERROR(INDEX('Paramètres'!$O:$O,MATCH($D75,'Paramètres'!$M:$M,0))&"","")))) -> Dépense Courante | N75: =IF($D75="","",IFERROR(INDEX('Paramètres'!$Q:$Q,MATCH($D75,'Paramètres'!$M:$M,0))&"","")) -> Alimentation | O75: =IF($A75="","",IF(OR($J75<>"x",$A75<=FinReleve),1,0)) -> 1 | P75: =IF($D75="","",IF(AND($L75="Crédit",OR(IFERROR(INDEX('Paramètres'!$O:$O,MATCH($D75,'Paramètres'!$M:$M,0))&"","")<>"",ISNUMBER(SEARCH("remboursement",IFERROR(INDEX('Paramètres'!$N:$N,MATCH($D75,'Paramètres'!$M:$M,0))&"",""))))),1,0)) -> 0 | Q75: =IF($K75="","",IF(ISNUMBER(SEARCH("transfert-interne",IFERROR(INDEX('Paramètres'!$N:$N,MATCH($D75,'Paramètres'!$M:$M,0))&"",""))),0,IF($L75="Débit",$K75,IF($P75=1,-$K75,0)))) -> 49.83 | R75: =IF($K75="","",IF($L75="Crédit",$K75,-$K75)) -> -49.83 | S75: =IF($C75="","",IFERROR(INDEX('Paramètres'!$H:$H,MATCH($C75,'Paramètres'!$D:$D,0))&"","")) -> Banque A - Courant | T75: =IF($K75="","",IF($S75="",0,IF(ISNUMBER(SEARCH("apport-exterieur",IFERROR(INDEX('Paramètres'!$N:$N,MATCH($D75,'Paramètres'!$M:$M,0))&"",""))),0,IF(OR(IFERROR(INDEX('Paramètres'!$I:$I,MATCH($C75,'Paramètres'!$D:$D,0))&"","")="Les deux",IFERROR(INDEX('Paramètres'!$I:$I,MATCH($C75,'Paramètres'!$D:$D,0))&"","")=IF($P75=1,"Débit",$L75)),-IF($P75=1,-$K75,$K75),0)))) -> -49.83 | U75: =IF($K75="","",IF(ISNUMBER(SEARCH("sortie-epargne",IFERROR(INDEX('Paramètres'!$N:$N,MATCH($D75,'Paramètres'!$M:$M,0))&"",""))),$K75,0)) -> 0 | V75: =IF(AND($A75<>"",$O75=1,$L75="Débit",N($Q75)>0,$A75>=Visualisation!$B$1,$A75<Visualisation!$D$1),MAX($V$1:V74)+1,"")
A76: 45583 | B76: Habillement | C76: Banque A - Courant | D76: Vêtement courant | E76: 88.21 | G76: Prêt-à-porter | I76: Rocheville | K76: =IF($E76="","",ROUND($E76*IF(ISNA(MATCH($C76,'Paramètres'!$D:$D,0)),1,IF(INDEX('Paramètres'!$J:$J,MATCH($C76,'Paramètres'!$D:$D,0))="",1,INDEX('Paramètres'!$J:$J,MATCH($C76,'Paramètres'!$D:$D,0)))),2)) -> 88.21 | L76: =IF($D76="","",IF($F76<>"",$F76,IF(ISNA(MATCH($D76,'Paramètres'!$M:$M,0)),"⚠ Type inconnu",IFERROR(INDEX('Paramètres'!$P:$P,MATCH($D76,'Paramètres'!$M:$M,0))&"","")))) -> Débit | M76: =IF($D76="","",IF(ISNA(MATCH($D76,'Paramètres'!$M:$M,0)),"⚠ Type inconnu",IF($L76="Crédit","",IFERROR(INDEX('Paramètres'!$O:$O,MATCH($D76,'Paramètres'!$M:$M,0))&"","")))) -> Dépense Courante | N76: =IF($D76="","",IFERROR(INDEX('Paramètres'!$Q:$Q,MATCH($D76,'Paramètres'!$M:$M,0))&"","")) -> Habillement | O76: =IF($A76="","",IF(OR($J76<>"x",$A76<=FinReleve),1,0)) -> 1 | P76: =IF($D76="","",IF(AND($L76="Crédit",OR(IFERROR(INDEX('Paramètres'!$O:$O,MATCH($D76,'Paramètres'!$M:$M,0))&"","")<>"",ISNUMBER(SEARCH("remboursement",IFERROR(INDEX('Paramètres'!$N:$N,MATCH($D76,'Paramètres'!$M:$M,0))&"",""))))),1,0)) -> 0 | Q76: =IF($K76="","",IF(ISNUMBER(SEARCH("transfert-interne",IFERROR(INDEX('Paramètres'!$N:$N,MATCH($D76,'Paramètres'!$M:$M,0))&"",""))),0,IF($L76="Débit",$K76,IF($P76=1,-$K76,0)))) -> 88.21 | R76: =IF($K76="","",IF($L76="Crédit",$K76,-$K76)) -> -88.21 | S76: =IF($C76="","",IFERROR(INDEX('Paramètres'!$H:$H,MATCH($C76,'Paramètres'!$D:$D,0))&"","")) | T76: =IF($K76="","",IF($S76="",0,IF(ISNUMBER(SEARCH("apport-exterieur",IFERROR(INDEX('Paramètres'!$N:$N,MATCH($D76,'Paramètres'!$M:$M,0))&"",""))),0,IF(OR(IFERROR(INDEX('Paramètres'!$I:$I,MATCH($C76,'Paramètres'!$D:$D,0))&"","")="Les deux",IFERROR(INDEX('Paramètres'!$I:$I,MATCH($C76,'Paramètres'!$D:$D,0))&"","")=IF($P76=1,"Débit",$L76)),-IF($P76=1,-$K76,$K76),0)))) -> 0 | U76: =IF($K76="","",IF(ISNUMBER(SEARCH("sortie-epargne",IFERROR(INDEX('Paramètres'!$N:$N,MATCH($D76,'Paramètres'!$M:$M,0))&"",""))),$K76,0)) -> 0 | V76: =IF(AND($A76<>"",$O76=1,$L76="Débit",N($Q76)>0,$A76>=Visualisation!$B$1,$A76<Visualisation!$D$1),MAX($V$1:V75)+1,"")
A77: 45584 | B77: Restaurant | C77: Appli partagée - Part commune | D77: Restaurant | E77: 164.98 | G77: Café | H77: Anniversaire | I77: Villebourg | K77: =IF($E77="","",ROUND($E77*IF(ISNA(MATCH($C77,'Paramètres'!$D:$D,0)),1,IF(INDEX('Paramètres'!$J:$J,MATCH($C77,'Paramètres'!$D:$D,0))="",1,INDEX('Paramètres'!$J:$J,MATCH($C77,'Paramètres'!$D:$D,0)))),2)) -> 82.49 | L77: =IF($D77="","",IF($F77<>"",$F77,IF(ISNA(MATCH($D77,'Paramètres'!$M:$M,0)),"⚠ Type inconnu",IFERROR(INDEX('Paramètres'!$P:$P,MATCH($D77,'Paramètres'!$M:$M,0))&"","")))) -> Débit | M77: =IF($D77="","",IF(ISNA(MATCH($D77,'Paramètres'!$M:$M,0)),"⚠ Type inconnu",IF($L77="Crédit","",IFERROR(INDEX('Paramètres'!$O:$O,MATCH($D77,'Paramètres'!$M:$M,0))&"","")))) -> Dépense Occasionnelle | N77: =IF($D77="","",IFERROR(INDEX('Paramètres'!$Q:$Q,MATCH($D77,'Paramètres'!$M:$M,0))&"","")) -> Alimentation | O77: =IF($A77="","",IF(OR($J77<>"x",$A77<=FinReleve),1,0)) -> 1 | P77: =IF($D77="","",IF(AND($L77="Crédit",OR(IFERROR(INDEX('Paramètres'!$O:$O,MATCH($D77,'Paramètres'!$M:$M,0))&"","")<>"",ISNUMBER(SEARCH("remboursement",IFERROR(INDEX('Paramètres'!$N:$N,MATCH($D77,'Paramètres'!$M:$M,0))&"",""))))),1,0)) -> 0 | Q77: =IF($K77="","",IF(ISNUMBER(SEARCH("transfert-interne",IFERROR(INDEX('Paramètres'!$N:$N,MATCH($D77,'Paramètres'!$M:$M,0))&"",""))),0,IF($L77="Débit",$K77,IF($P77=1,-$K77,0)))) -> 82.49 | R77: =IF($K77="","",IF($L77="Crédit",$K77,-$K77)) -> -82.49 | S77: =IF($C77="","",IFERROR(INDEX('Paramètres'!$H:$H,MATCH($C77,'Paramètres'!$D:$D,0))&"","")) -> Banque A - Courant | T77: =IF($K77="","",IF($S77="",0,IF(ISNUMBER(SEARCH("apport-exterieur",IFERROR(INDEX('Paramètres'!$N:$N,MATCH($D77,'Paramètres'!$M:$M,0))&"",""))),0,IF(OR(IFERROR(INDEX('Paramètres'!$I:$I,MATCH($C77,'Paramètres'!$D:$D,0))&"","")="Les deux",IFERROR(INDEX('Paramètres'!$I:$I,MATCH($C77,'Paramètres'!$D:$D,0))&"","")=IF($P77=1,"Débit",$L77)),-IF($P77=1,-$K77,$K77),0)))) -> -82.49 | U77: =IF($K77="","",IF(ISNUMBER(SEARCH("sortie-epargne",IFERROR(INDEX('Paramètres'!$N:$N,MATCH($D77,'Paramètres'!$M:$M,0))&"",""))),$K77,0)) -> 0 | V77: =IF(AND($A77<>"",$O77=1,$L77="Débit",N($Q77)>0,$A77>=Visualisation!$B$1,$A77<Visualisation!$D$1),MAX($V$1:V76)+1,"")
A78: 45585 | B78: Carburant | C78: Banque A - Courant | D78: Essence | E78: 50.23 | G78: Parking | I78: Rocheville | K78: =IF($E78="","",ROUND($E78*IF(ISNA(MATCH($C78,'Paramètres'!$D:$D,0)),1,IF(INDEX('Paramètres'!$J:$J,MATCH($C78,'Paramètres'!$D:$D,0))="",1,INDEX('Paramètres'!$J:$J,MATCH($C78,'Paramètres'!$D:$D,0)))),2)) -> 50.23 | L78: =IF($D78="","",IF($F78<>"",$F78,IF(ISNA(MATCH($D78,'Paramètres'!$M:$M,0)),"⚠ Type inconnu",IFERROR(INDEX('Paramètres'!$P:$P,MATCH($D78,'Paramètres'!$M:$M,0))&"","")))) -> Débit | M78: =IF($D78="","",IF(ISNA(MATCH($D78,'Paramètres'!$M:$M,0)),"⚠ Type inconnu",IF($L78="Crédit","",IFERROR(INDEX('Paramètres'!$O:$O,MATCH($D78,'Paramètres'!$M:$M,0))&"","")))) -> Dépense Courante | N78: =IF($D78="","",IFERROR(INDEX('Paramètres'!$Q:$Q,MATCH($D78,'Paramètres'!$M:$M,0))&"","")) -> Transport | O78: =IF($A78="","",IF(OR($J78<>"x",$A78<=FinReleve),1,0)) -> 1 | P78: =IF($D78="","",IF(AND($L78="Crédit",OR(IFERROR(INDEX('Paramètres'!$O:$O,MATCH($D78,'Paramètres'!$M:$M,0))&"","")<>"",ISNUMBER(SEARCH("remboursement",IFERROR(INDEX('Paramètres'!$N:$N,MATCH($D78,'Paramètres'!$M:$M,0))&"",""))))),1,0)) -> 0 | Q78: =IF($K78="","",IF(ISNUMBER(SEARCH("transfert-interne",IFERROR(INDEX('Paramètres'!$N:$N,MATCH($D78,'Paramètres'!$M:$M,0))&"",""))),0,IF($L78="Débit",$K78,IF($P78=1,-$K78,0)))) -> 50.23 | R78: =IF($K78="","",IF($L78="Crédit",$K78,-$K78)) -> -50.23 | S78: =IF($C78="","",IFERROR(INDEX('Paramètres'!$H:$H,MATCH($C78,'Paramètres'!$D:$D,0))&"","")) | T78: =IF($K78="","",IF($S78="",0,IF(ISNUMBER(SEARCH("apport-exterieur",IFERROR(INDEX('Paramètres'!$N:$N,MATCH($D78,'Paramètres'!$M:$M,0))&"",""))),0,IF(OR(IFERROR(INDEX('Paramètres'!$I:$I,MATCH($C78,'Paramètres'!$D:$D,0))&"","")="Les deux",IFERROR(INDEX('Paramètres'!$I:$I,MATCH($C78,'Paramètres'!$D:$D,0))&"","")=IF($P78=1,"Débit",$L78)),-IF($P78=1,-$K78,$K78),0)))) -> 0 | U78: =IF($K78="","",IF(ISNUMBER(SEARCH("sortie-epargne",IFERROR(INDEX('Paramètres'!$N:$N,MATCH($D78,'Paramètres'!$M:$M,0))&"",""))),$K78,0)) -> 0 | V78: =IF(AND($A78<>"",$O78=1,$L78="Débit",N($Q78)>0,$A78>=Visualisation!$B$1,$A78<Visualisation!$D$1),MAX($V$1:V77)+1,"")
A79: 45587 | B79: Achat carte | C79: Banque B - Compte joint | D79: courses | E79: 36.96 | G79: Supermarché Ouest | K79: =IF($E79="","",ROUND($E79*IF(ISNA(MATCH($C79,'Paramètres'!$D:$D,0)),1,IF(INDEX('Paramètres'!$J:$J,MATCH($C79,'Paramètres'!$D:$D,0))="",1,INDEX('Paramètres'!$J:$J,MATCH($C79,'Paramètres'!$D:$D,0)))),2)) -> 18.48 | L79: =IF($D79="","",IF($F79<>"",$F79,IF(ISNA(MATCH($D79,'Paramètres'!$M:$M,0)),"⚠ Type inconnu",IFERROR(INDEX('Paramètres'!$P:$P,MATCH($D79,'Paramètres'!$M:$M,0))&"","")))) -> Débit | M79: =IF($D79="","",IF(ISNA(MATCH($D79,'Paramètres'!$M:$M,0)),"⚠ Type inconnu",IF($L79="Crédit","",IFERROR(INDEX('Paramètres'!$O:$O,MATCH($D79,'Paramètres'!$M:$M,0))&"","")))) -> Dépense Courante | N79: =IF($D79="","",IFERROR(INDEX('Paramètres'!$Q:$Q,MATCH($D79,'Paramètres'!$M:$M,0))&"","")) -> Alimentation | O79: =IF($A79="","",IF(OR($J79<>"x",$A79<=FinReleve),1,0)) -> 1 | P79: =IF($D79="","",IF(AND($L79="Crédit",OR(IFERROR(INDEX('Paramètres'!$O:$O,MATCH($D79,'Paramètres'!$M:$M,0))&"","")<>"",ISNUMBER(SEARCH("remboursement",IFERROR(INDEX('Paramètres'!$N:$N,MATCH($D79,'Paramètres'!$M:$M,0))&"",""))))),1,0)) -> 0 | Q79: =IF($K79="","",IF(ISNUMBER(SEARCH("transfert-interne",IFERROR(INDEX('Paramètres'!$N:$N,MATCH($D79,'Paramètres'!$M:$M,0))&"",""))),0,IF($L79="Débit",$K79,IF($P79=1,-$K79,0)))) -> 18.48 | R79: =IF($K79="","",IF($L79="Crédit",$K79,-$K79)) -> -18.48 | S79: =IF($C79="","",IFERROR(INDEX('Paramètres'!$H:$H,MATCH($C79,'Paramètres'!$D:$D,0))&"","")) -> Banque A - Courant | T79: =IF($K79="","",IF($S79="",0,IF(ISNUMBER(SEARCH("apport-exterieur",IFERROR(INDEX('Paramètres'!$N:$N,MATCH($D79,'Paramètres'!$M:$M,0))&"",""))),0,IF(OR(IFERROR(INDEX('Paramètres'!$I:$I,MATCH($C79,'Paramètres'!$D:$D,0))&"","")="Les deux",IFERROR(INDEX('Paramètres'!$I:$I,MATCH($C79,'Paramètres'!$D:$D,0))&"","")=IF($P79=1,"Débit",$L79)),-IF($P79=1,-$K79,$K79),0)))) -> 0 | U79: =IF($K79="","",IF(ISNUMBER(SEARCH("sortie-epargne",IFERROR(INDEX('Paramètres'!$N:$N,MATCH($D79,'Paramètres'!$M:$M,0))&"",""))),$K79,0)) -> 0 | V79: =IF(AND($A79<>"",$O79=1,$L79="Débit",N($Q79)>0,$A79>=Visualisation!$B$1,$A79<Visualisation!$D$1),MAX($V$1:V78)+1,"")
A80: 45587 | B80: Titre restaurant | C80: Titres-restaurant | D80: cantine | E80: 14.07 | G80: Cantine | I80: Rocheville | K80: =IF($E80="","",ROUND($E80*IF(ISNA(MATCH($C80,'Paramètres'!$D:$D,0)),1,IF(INDEX('Paramètres'!$J:$J,MATCH($C80,'Paramètres'!$D:$D,0))="",1,INDEX('Paramètres'!$J:$J,MATCH($C80,'Paramètres'!$D:$D,0)))),2)) -> 14.07 | L80: =IF($D80="","",IF($F80<>"",$F80,IF(ISNA(MATCH($D80,'Paramètres'!$M:$M,0)),"⚠ Type inconnu",IFERROR(INDEX('Paramètres'!$P:$P,MATCH($D80,'Paramètres'!$M:$M,0))&"","")))) -> Débit | M80: =IF($D80="","",IF(ISNA(MATCH($D80,'Paramètres'!$M:$M,0)),"⚠ Type inconnu",IF($L80="Crédit","",IFERROR(INDEX('Paramètres'!$O:$O,MATCH($D80,'Paramètres'!$M:$M,0))&"","")))) -> Dépense Courante | N80: =IF($D80="","",IFERROR(INDEX('Paramètres'!$Q:$Q,MATCH($D80,'Paramètres'!$M:$M,0))&"","")) -> Alimentation | O80: =IF($A80="","",IF(OR($J80<>"x",$A80<=FinReleve),1,0)) -> 1 | P80: =IF($D80="","",IF(AND($L80="Crédit",OR(IFERROR(INDEX('Paramètres'!$O:$O,MATCH($D80,'Paramètres'!$M:$M,0))&"","")<>"",ISNUMBER(SEARCH("remboursement",IFERROR(INDEX('Paramètres'!$N:$N,MATCH($D80,'Paramètres'!$M:$M,0))&"",""))))),1,0)) -> 0 | Q80: =IF($K80="","",IF(ISNUMBER(SEARCH("transfert-interne",IFERROR(INDEX('Paramètres'!$N:$N,MATCH($D80,'Paramètres'!$M:$M,0))&"",""))),0,IF($L80="Débit",$K80,IF($P80=1,-$K80,0)))) -> 14.07 | R80: =IF($K80="","",IF($L80="Crédit",$K80,-$K80)) -> -14.07 | S80: =IF($C80="","",IFERROR(INDEX('Paramètres'!$H:$H,MATCH($C80,'Paramètres'!$D:$D,0))&"","")) | T80: =IF($K80="","",IF($S80="",0,IF(ISNUMBER(SEARCH("apport-exterieur",IFERROR(INDEX('Paramètres'!$N:$N,MATCH($D80,'Paramètres'!$M:$M,0))&"",""))),0,IF(OR(IFERROR(INDEX('Paramètres'!$I:$I,MATCH($C80,'Paramètres'!$D:$D,0))&"","")="Les deux",IFERROR(INDEX('Paramètres'!$I:$I,MATCH($C80,'Paramètres'!$D:$D,0))&"","")=IF($P80=1,"Débit",$L80)),-IF($P80=1,-$K80,$K80),0)))) -> 0 | U80: =IF($K80="","",IF(ISNUMBER(SEARCH("sortie-epargne",IFERROR(INDEX('Paramètres'!$N:$N,MATCH($D80,'Paramètres'!$M:$M,0))&"",""))),$K80,0)) -> 0 | V80: =IF(AND($A80<>"",$O80=1,$L80="Débit",N($Q80)>0,$A80>=Visualisation!$B$1,$A80<Visualisation!$D$1),MAX($V$1:V79)+1,"")
A81: 45587 | B81: Virement épargne | C81: Banque A - Courant | D81: Epargne Banque B | E81: 285.2 | K81: =IF($E81="","",ROUND($E81*IF(ISNA(MATCH($C81,'Paramètres'!$D:$D,0)),1,IF(INDEX('Paramètres'!$J:$J,MATCH($C81,'Paramètres'!$D:$D,0))="",1,INDEX('Paramètres'!$J:$J,MATCH($C81,'Paramètres'!$D:$D,0)))),2)) -> 285.2 | L81: =IF($D81="","",IF($F81<>"",$F81,IF(ISNA(MATCH($D81,'Paramètres'!$M:$M,0)),"⚠ Type inconnu",IFERROR(INDEX('Paramètres'!$P:$P,MATCH($D81,'Paramètres'!$M:$M,0))&"","")))) -> Débit | M81: =IF($D81="","",IF(ISNA(MATCH($D81,'Paramètres'!$M:$M,0)),"⚠ Type inconnu",IF($L81="Crédit","",IFERROR(INDEX('Paramètres'!$O:$O,MATCH($D81,'Paramètres'!$M:$M,0))&"","")))) | N81: =IF($D81="","",IFERROR(INDEX('Paramètres'!$Q:$Q,MATCH($D81,'Paramètres'!$M:$M,0))&"","")) -> Comptes Bancaires | O81: =IF($A81="","",IF(OR($J81<>"x",$A81<=FinReleve),1,0)) -> 1 | P81: =IF($D81="","",IF(AND($L81="Crédit",OR(IFERROR(INDEX('Paramètres'!$O:$O,MATCH($D81,'Paramètres'!$M:$M,0))&"","")<>"",ISNUMBER(SEARCH("remboursement",IFERROR(INDEX('Paramètres'!$N:$N,MATCH($D81,'Paramètres'!$M:$M,0))&"",""))))),1,0)) -> 0 | Q81: =IF($K81="","",IF(ISNUMBER(SEARCH("transfert-interne",IFERROR(INDEX('Paramètres'!$N:$N,MATCH($D81,'Paramètres'!$M:$M,0))&"",""))),0,IF($L81="Débit",$K81,IF($P81=1,-$K81,0)))) -> 285.2 | R81: =IF($K81="","",IF($L81="Crédit",$K81,-$K81)) -> -285.2 | S81: =IF($C81="","",IFERROR(INDEX('Paramètres'!$H:$H,MATCH($C81,'Paramètres'!$D:$D,0))&"","")) | T81: =IF($K81="","",IF($S81="",0,IF(ISNUMBER(SEARCH("apport-exterieur",IFERROR(INDEX('Paramètres'!$N:$N,MATCH($D81,'Paramètres'!$M:$M,0))&"",""))),0,IF(OR(IFERROR(INDEX('Paramètres'!$I:$I,MATCH($C81,'Paramètres'!$D:$D,0))&"","")="Les deux",IFERROR(INDEX('Paramètres'!$I:$I,MATCH($C81,'Paramètres'!$D:$D,0))&"","")=IF($P81=1,"Débit",$L81)),-IF($P81=1,-$K81,$K81),0)))) -> 0 | U81: =IF($K81="","",IF(ISNUMBER(SEARCH("sortie-epargne",IFERROR(INDEX('Paramètres'!$N:$N,MATCH($D81,'Paramètres'!$M:$M,0))&"",""))),$K81,0)) -> 0 | V81: =IF(AND($A81<>"",$O81=1,$L81="Débit",N($Q81)>0,$A81>=Visualisation!$B$1,$A81<Visualisation!$D$1),MAX($V$1:V80)+1,"")
A82: 45589 | B82: Achat carte | C82: Banque A - Part commune | D82: courses | E82: 172.02 | G82: Primeur | I82: Grandval | K82: =IF($E82="","",ROUND($E82*IF(ISNA(MATCH($C82,'Paramètres'!$D:$D,0)),1,IF(INDEX('Paramètres'!$J:$J,MATCH($C82,'Paramètres'!$D:$D,0))="",1,INDEX('Paramètres'!$J:$J,MATCH($C82,'Paramètres'!$D:$D,0)))),2)) -> 86.01 | L82: =IF($D82="","",IF($F82<>"",$F82,IF(ISNA(MATCH($D82,'Paramètres'!$M:$M,0)),"⚠ Type inconnu",IFERROR(INDEX('Paramètres'!$P:$P,MATCH($D82,'Paramètres'!$M:$M,0))&"","")))) -> Débit | M82: =IF($D82="","",IF(ISNA(MATCH($D82,'Paramètres'!$M:$M,0)),"⚠ Type inconnu",IF($L82="Crédit","",IFERROR(INDEX('Paramètres'!$O:$O,MATCH($D82,'Paramètres'!$M:$M,0))&"","")))) -> Dépense Courante | N82: =IF($D82="","",IFERROR(INDEX('Paramètres'!$Q:$Q,MATCH($D82,'Paramètres'!$M:$M,0))&"","")) -> Alimentation | O82: =IF($A82="","",IF(OR($J82<>"x",$A82<=FinReleve),1,0)) -> 1 | P82: =IF($D82="","",IF(AND($L82="Crédit",OR(IFERROR(INDEX('Paramètres'!$O:$O,MATCH($D82,'Paramètres'!$M:$M,0))&"","")<>"",ISNUMBER(SEARCH("remboursement",IFERROR(INDEX('Paramètres'!$N:$N,MATCH($D82,'Paramètres'!$M:$M,0))&"",""))))),1,0)) -> 0 | Q82: =IF($K82="","",IF(ISNUMBER(SEARCH("transfert-interne",IFERROR(INDEX('Paramètres'!$N:$N,MATCH($D82,'Paramètres'!$M:$M,0))&"",""))),0,IF($L82="Débit",$K82,IF($P82=1,-$K82,0)))) -> 86.01 | R82: =IF($K82="","",IF($L82="Crédit",$K82,-$K82)) -> -86.01 | S82: =IF($C82="","",IFERROR(INDEX('Paramètres'!$H:$H,MATCH($C82,'Paramètres'!$D:$D,0))&"","")) -> Banque A - Courant | T82: =IF($K82="","",IF($S82="",0,IF(ISNUMBER(SEARCH("apport-exterieur",IFERROR(INDEX('Paramètres'!$N:$N,MATCH($D82,'Paramètres'!$M:$M,0))&"",""))),0,IF(OR(IFERROR(INDEX('Paramètres'!$I:$I,MATCH($C82,'Paramètres'!$D:$D,0))&"","")="Les deux",IFERROR(INDEX('Paramètres'!$I:$I,MATCH($C82,'Paramètres'!$D:$D,0))&"","")=IF($P82=1,"Débit",$L82)),-IF($P82=1,-$K82,$K82),0)))) -> -86.01 | U82: =IF($K82="","",IF(ISNUMBER(SEARCH("sortie-epargne",IFERROR(INDEX('Paramètres'!$N:$N,MATCH($D82,'Paramètres'!$M:$M,0))&"",""))),$K82,0)) -> 0 | V82: =IF(AND($A82<>"",$O82=1,$L82="Débit",N($Q82)>0,$A82>=Visualisation!$B$1,$A82<Visualisation!$D$1),MAX($V$1:V81)+1,"")
A83: 45589 | B83: Achat carte | C83: Banque A - Part commune | D83: courses | E83: 145.44 | G83: Supermarché Ouest | I83: Grandval | K83: =IF($E83="","",ROUND($E83*IF(ISNA(MATCH($C83,'Paramètres'!$D:$D,0)),1,IF(INDEX('Paramètres'!$J:$J,MATCH($C83,'Paramètres'!$D:$D,0))="",1,INDEX('Paramètres'!$J:$J,MATCH($C83,'Paramètres'!$D:$D,0)))),2)) -> 72.72 | L83: =IF($D83="","",IF($F83<>"",$F83,IF(ISNA(MATCH($D83,'Paramètres'!$M:$M,0)),"⚠ Type inconnu",IFERROR(INDEX('Paramètres'!$P:$P,MATCH($D83,'Paramètres'!$M:$M,0))&"","")))) -> Débit | M83: =IF($D83="","",IF(ISNA(MATCH($D83,'Paramètres'!$M:$M,0)),"⚠ Type inconnu",IF($L83="Crédit","",IFERROR(INDEX('Paramètres'!$O:$O,MATCH($D83,'Paramètres'!$M:$M,0))&"","")))) -> Dépense Courante | N83: =IF($D83="","",IFERROR(INDEX('Paramètres'!$Q:$Q,MATCH($D83,'Paramètres'!$M:$M,0))&"","")) -> Alimentation | O83: =IF($A83="","",IF(OR($J83<>"x",$A83<=FinReleve),1,0)) -> 1 | P83: =IF($D83="","",IF(AND($L83="Crédit",OR(IFERROR(INDEX('Paramètres'!$O:$O,MATCH($D83,'Paramètres'!$M:$M,0))&"","")<>"",ISNUMBER(SEARCH("remboursement",IFERROR(INDEX('Paramètres'!$N:$N,MATCH($D83,'Paramètres'!$M:$M,0))&"",""))))),1,0)) -> 0 | Q83: =IF($K83="","",IF(ISNUMBER(SEARCH("transfert-interne",IFERROR(INDEX('Paramètres'!$N:$N,MATCH($D83,'Paramètres'!$M:$M,0))&"",""))),0,IF($L83="Débit",$K83,IF($P83=1,-$K83,0)))) -> 72.72 | R83: =IF($K83="","",IF($L83="Crédit",$K83,-$K83)) -> -72.72 | S83: =IF($C83="","",IFERROR(INDEX('Paramètres'!$H:$H,MATCH($C83,'Paramètres'!$D:$D,0))&"","")) -> Banque A - Courant | T83: =IF($K83="","",IF($S83="",0,IF(ISNUMBER(SEARCH("apport-exterieur",IFERROR(INDEX('Paramètres'!$N:$N,MATCH($D83,'Paramètres'!$M:$M,0))&"",""))),0,IF(OR(IFERROR(INDEX('Paramètres'!$I:$I,MATCH($C83,'Paramètres'!$D:$D,0))&"","")="Les deux",IFERROR(INDEX('Paramètres'!$I:$I,MATCH($C83,'Paramètres'!$D:$D,0))&"","")=IF($P83=1,"Débit",$L83)),-IF($P83=1,-$K83,$K83),0)))) -> -72.72 | U83: =IF($K83="","",IF(ISNUMBER(SEARCH("sortie-epargne",IFERROR(INDEX('Paramètres'!$N:$N,MATCH($D83,'Paramètres'!$M:$M,0))&"",""))),$K83,0)) -> 0 | V83: =IF(AND($A83<>"",$O83=1,$L83="Débit",N($Q83)>0,$A83>=Visualisation!$B$1,$A83<Visualisation!$D$1),MAX($V$1:V82)+1,"")
A84: 45589 | B84: Cadeaux | C84: Appli partagée - Part commune | D84: Cadeaux | E84: 235.42 | G84: Café | H84: Anniversaire | I84: Grandval | K84: =IF($E84="","",ROUND($E84*IF(ISNA(MATCH($C84,'Paramètres'!$D:$D,0)),1,IF(INDEX('Paramètres'!$J:$J,MATCH($C84,'Paramètres'!$D:$D,0))="",1,INDEX('Paramètres'!$J:$J,MATCH($C84,'Paramètres'!$D:$D,0)))),2)) -> 117.71 | L84: =IF($D84="","",IF($F84<>"",$F84,IF(ISNA(MATCH($D84,'Paramètres'!$M:$M,0)),"⚠ Type inconnu",IFERROR(INDEX('Paramètres'!$P:$P,MATCH($D84,'Paramètres'!$M:$M,0))&"","")))) -> Débit | M84: =IF($D84="","",IF(ISNA(MATCH($D84,'Paramètres'!$M:$M,0)),"⚠ Type inconnu",IF($L84="Crédit","",IFERROR(INDEX('Paramètres'!$O:$O,MATCH($D84,'Paramètres'!$M:$M,0))&"","")))) -> Dépense Occasionnelle | N84: =IF($D84="","",IFERROR(INDEX('Paramètres'!$Q:$Q,MATCH($D84,'Paramètres'!$M:$M,0))&"","")) -> Autre | O84: =IF($A84="","",IF(OR($J84<>"x",$A84<=FinReleve),1,0)) -> 1 | P84: =IF($D84="","",IF(AND($L84="Crédit",OR(IFERROR(INDEX('Paramètres'!$O:$O,MATCH($D84,'Paramètres'!$M:$M,0))&"","")<>"",ISNUMBER(SEARCH("remboursement",IFERROR(INDEX('Paramètres'!$N:$N,MATCH($D84,'Paramètres'!$M:$M,0))&"",""))))),1,0)) -> 0 | Q84: =IF($K84="","",IF(ISNUMBER(SEARCH("transfert-interne",IFERROR(INDEX('Paramètres'!$N:$N,MATCH($D84,'Paramètres'!$M:$M,0))&"",""))),0,IF($L84="Débit",$K84,IF($P84=1,-$K84,0)))) -> 117.71 | R84: =IF($K84="","",IF($L84="Crédit",$K84,-$K84)) -> -117.71 | S84: =IF($C84="","",IFERROR(INDEX('Paramètres'!$H:$H,MATCH($C84,'Paramètres'!$D:$D,0))&"","")) -> Banque A - Courant | T84: =IF($K84="","",IF($S84="",0,IF(ISNUMBER(SEARCH("apport-exterieur",IFERROR(INDEX('Paramètres'!$N:$N,MATCH($D84,'Paramètres'!$M:$M,0))&"",""))),0,IF(OR(IFERROR(INDEX('Paramètres'!$I:$I,MATCH($C84,'Paramètres'!$D:$D,0))&"","")="Les deux",IFERROR(INDEX('Paramètres'!$I:$I,MATCH($C84,'Paramètres'!$D:$D,0))&"","")=IF($P84=1,"Débit",$L84)),-IF($P84=1,-$K84,$K84),0)))) -> -117.71 | U84: =IF($K84="","",IF(ISNUMBER(SEARCH("sortie-epargne",IFERROR(INDEX('Paramètres'!$N:$N,MATCH($D84,'Paramètres'!$M:$M,0))&"",""))),$K84,0)) -> 0 | V84: =IF(AND($A84<>"",$O84=1,$L84="Débit",N($Q84)>0,$A84>=Visualisation!$B$1,$A84<Visualisation!$D$1),MAX($V$1:V83)+1,"")
A85: 45591 | B85: Achat carte | C85: Banque B - Compte joint | D85: courses | E85: 26.24 | G85: Supermarché Centre | K85: =IF($E85="","",ROUND($E85*IF(ISNA(MATCH($C85,'Paramètres'!$D:$D,0)),1,IF(INDEX('Paramètres'!$J:$J,MATCH($C85,'Paramètres'!$D:$D,0))="",1,INDEX('Paramètres'!$J:$J,MATCH($C85,'Paramètres'!$D:$D,0)))),2)) -> 13.12 | L85: =IF($D85="","",IF($F85<>"",$F85,IF(ISNA(MATCH($D85,'Paramètres'!$M:$M,0)),"⚠ Type inconnu",IFERROR(INDEX('Paramètres'!$P:$P,MATCH($D85,'Paramètres'!$M:$M,0))&"","")))) -> Débit | M85: =IF($D85="","",IF(ISNA(MATCH($D85,'Paramètres'!$M:$M,0)),"⚠ Type inconnu",IF($L85="Crédit","",IFERROR(INDEX('Paramètres'!$O:$O,MATCH($D85,'Paramètres'!$M:$M,0))&"","")))) -> Dépense Courante | N85: =IF($D85="","",IFERROR(INDEX('Paramètres'!$Q:$Q,MATCH($D85,'Paramètres'!$M:$M,0))&"","")) -> Alimentation | O85: =IF($A85="","",IF(OR($J85<>"x",$A85<=FinReleve),1,0)) -> 1 | P85: =IF($D85="","",IF(AND($L85="Crédit",OR(IFERROR(INDEX('Paramètres'!$O:$O,MATCH($D85,'Paramètres'!$M:$M,0))&"","")<>"",ISNUMBER(SEARCH("remboursement",IFERROR(INDEX('Paramètres'!$N:$N,MATCH($D85,'Paramètres'!$M:$M,0))&"",""))))),1,0)) -> 0 | Q85: =IF($K85="","",IF(ISNUMBER(SEARCH("transfert-interne",IFERROR(INDEX('Paramètres'!$N:$N,MATCH($D85,'Paramètres'!$M:$M,0))&"",""))),0,IF($L85="Débit",$K85,IF($P85=1,-$K85,0)))) -> 13.12 | R85: =IF($K85="","",IF($L85="Crédit",$K85,-$K85)) -> -13.12 | S85: =IF($C85="","",IFERROR(INDEX('Paramètres'!$H:$H,MATCH($C85,'Paramètres'!$D:$D,0))&"","")) -> Banque A - Courant | T85: =IF($K85="","",IF($S85="",0,IF(ISNUMBER(SEARCH("apport-exterieur",IFERROR(INDEX('Paramètres'!$N:$N,MATCH($D85,'Paramètres'!$M:$M,0))&"",""))),0,IF(OR(IFERROR(INDEX('Paramètres'!$I:$I,MATCH($C85,'Paramètres'!$D:$D,0))&"","")="Les deux",IFERROR(INDEX('Paramètres'!$I:$I,MATCH($C85,'Paramètres'!$D:$D,0))&"","")=IF($P85=1,"Débit",$L85)),-IF($P85=1,-$K85,$K85),0)))) -> 0 | U85: =IF($K85="","",IF(ISNUMBER(SEARCH("sortie-epargne",IFERROR(INDEX('Paramètres'!$N:$N,MATCH($D85,'Paramètres'!$M:$M,0))&"",""))),$K85,0)) -> 0 | V85: =IF(AND($A85<>"",$O85=1,$L85="Débit",N($Q85)>0,$A85>=Visualisation!$B$1,$A85<Visualisation!$D$1),MAX($V$1:V84)+1,"")
A86: 45591 | B86: Virement épargne | C86: Banque A - Courant | D86: Epargne Banque A | E86: 150 | K86: =IF($E86="","",ROUND($E86*IF(ISNA(MATCH($C86,'Paramètres'!$D:$D,0)),1,IF(INDEX('Paramètres'!$J:$J,MATCH($C86,'Paramètres'!$D:$D,0))="",1,INDEX('Paramètres'!$J:$J,MATCH($C86,'Paramètres'!$D:$D,0)))),2)) -> 150 | L86: =IF($D86="","",IF($F86<>"",$F86,IF(ISNA(MATCH($D86,'Paramètres'!$M:$M,0)),"⚠ Type inconnu",IFERROR(INDEX('Paramètres'!$P:$P,MATCH($D86,'Paramètres'!$M:$M,0))&"","")))) -> Débit | M86: =IF($D86="","",IF(ISNA(MATCH($D86,'Paramètres'!$M:$M,0)),"⚠ Type inconnu",IF($L86="Crédit","",IFERROR(INDEX('Paramètres'!$O:$O,MATCH($D86,'Paramètres'!$M:$M,0))&"","")))) | N86: =IF($D86="","",IFERROR(INDEX('Paramètres'!$Q:$Q,MATCH($D86,'Paramètres'!$M:$M,0))&"","")) -> Comptes Bancaires | O86: =IF($A86="","",IF(OR($J86<>"x",$A86<=FinReleve),1,0)) -> 1 | P86: =IF($D86="","",IF(AND($L86="Crédit",OR(IFERROR(INDEX('Paramètres'!$O:$O,MATCH($D86,'Paramètres'!$M:$M,0))&"","")<>"",ISNUMBER(SEARCH("remboursement",IFERROR(INDEX('Paramètres'!$N:$N,MATCH($D86,'Paramètres'!$M:$M,0))&"",""))))),1,0)) -> 0 | Q86: =IF($K86="","",IF(ISNUMBER(SEARCH("transfert-interne",IFERROR(INDEX('Paramètres'!$N:$N,MATCH($D86,'Paramètres'!$M:$M,0))&"",""))),0,IF($L86="Débit",$K86,IF($P86=1,-$K86,0)))) -> 0 | R86: =IF($K86="","",IF($L86="Crédit",$K86,-$K86)) -> -150 | S86: =IF($C86="","",IFERROR(INDEX('Paramètres'!$H:$H,MATCH($C86,'Paramètres'!$D:$D,0))&"","")) | T86: =IF($K86="","",IF($S86="",0,IF(ISNUMBER(SEARCH("apport-exterieur",IFERROR(INDEX('Paramètres'!$N:$N,MATCH($D86,'Paramètres'!$M:$M,0))&"",""))),0,IF(OR(IFERROR(INDEX('Paramètres'!$I:$I,MATCH($C86,'Paramètres'!$D:$D,0))&"","")="Les deux",IFERROR(INDEX('Paramètres'!$I:$I,MATCH($C86,'Paramètres'!$D:$D,0))&"","")=IF($P86=1,"Débit",$L86)),-IF($P86=1,-$K86,$K86),0)))) -> 0 | U86: =IF($K86="","",IF(ISNUMBER(SEARCH("sortie-epargne",IFERROR(INDEX('Paramètres'!$N:$N,MATCH($D86,'Paramètres'!$M:$M,0))&"",""))),$K86,0)) -> 0 | V86: =IF(AND($A86<>"",$O86=1,$L86="Débit",N($Q86)>0,$A86>=Visualisation!$B$1,$A86<Visualisation!$D$1),MAX($V$1:V85)+1,"")
A87: 45591 | B87: Virement épargne | C87: Banque A - Courant | D87: Epargne Banque C | E87: 200 | K87: =IF($E87="","",ROUND($E87*IF(ISNA(MATCH($C87,'Paramètres'!$D:$D,0)),1,IF(INDEX('Paramètres'!$J:$J,MATCH($C87,'Paramètres'!$D:$D,0))="",1,INDEX('Paramètres'!$J:$J,MATCH($C87,'Paramètres'!$D:$D,0)))),2)) -> 200 | L87: =IF($D87="","",IF($F87<>"",$F87,IF(ISNA(MATCH($D87,'Paramètres'!$M:$M,0)),"⚠ Type inconnu",IFERROR(INDEX('Paramètres'!$P:$P,MATCH($D87,'Paramètres'!$M:$M,0))&"","")))) -> Débit | M87: =IF($D87="","",IF(ISNA(MATCH($D87,'Paramètres'!$M:$M,0)),"⚠ Type inconnu",IF($L87="Crédit","",IFERROR(INDEX('Paramètres'!$O:$O,MATCH($D87,'Paramètres'!$M:$M,0))&"","")))) | N87: =IF($D87="","",IFERROR(INDEX('Paramètres'!$Q:$Q,MATCH($D87,'Paramètres'!$M:$M,0))&"","")) -> Comptes Bancaires | O87: =IF($A87="","",IF(OR($J87<>"x",$A87<=FinReleve),1,0)) -> 1 | P87: =IF($D87="","",IF(AND($L87="Crédit",OR(IFERROR(INDEX('Paramètres'!$O:$O,MATCH($D87,'Paramètres'!$M:$M,0))&"","")<>"",ISNUMBER(SEARCH("remboursement",IFERROR(INDEX('Paramètres'!$N:$N,MATCH($D87,'Paramètres'!$M:$M,0))&"",""))))),1,0)) -> 0 | Q87: =IF($K87="","",IF(ISNUMBER(SEARCH("transfert-interne",IFERROR(INDEX('Paramètres'!$N:$N,MATCH($D87,'Paramètres'!$M:$M,0))&"",""))),0,IF($L87="Débit",$K87,IF($P87=1,-$K87,0)))) -> 200 | R87: =IF($K87="","",IF($L87="Crédit",$K87,-$K87)) -> -200 | S87: =IF($C87="","",IFERROR(INDEX('Paramètres'!$H:$H,MATCH($C87,'Paramètres'!$D:$D,0))&"","")) | T87: =IF($K87="","",IF($S87="",0,IF(ISNUMBER(SEARCH("apport-exterieur",IFERROR(INDEX('Paramètres'!$N:$N,MATCH($D87,'Paramètres'!$M:$M,0))&"",""))),0,IF(OR(IFERROR(INDEX('Paramètres'!$I:$I,MATCH($C87,'Paramètres'!$D:$D,0))&"","")="Les deux",IFERROR(INDEX('Paramètres'!$I:$I,MATCH($C87,'Paramètres'!$D:$D,0))&"","")=IF($P87=1,"Débit",$L87)),-IF($P87=1,-$K87,$K87),0)))) -> 0 | U87: =IF($K87="","",IF(ISNUMBER(SEARCH("sortie-epargne",IFERROR(INDEX('Paramètres'!$N:$N,MATCH($D87,'Paramètres'!$M:$M,0))&"",""))),$K87,0)) -> 0 | V87: =IF(AND($A87<>"",$O87=1,$L87="Débit",N($Q87)>0,$A87>=Visualisation!$B$1,$A87<Visualisation!$D$1),MAX($V$1:V86)+1,"")
A88: 45591 | B88: Versement assurance-vie | C88: Banque A - Courant | D88: Assurance-vie | E88: 120 | K88: =IF($E88="","",ROUND($E88*IF(ISNA(MATCH($C88,'Paramètres'!$D:$D,0)),1,IF(INDEX('Paramètres'!$J:$J,MATCH($C88,'Paramètres'!$D:$D,0))="",1,INDEX('Paramètres'!$J:$J,MATCH($C88,'Paramètres'!$D:$D,0)))),2)) -> 120 | L88: =IF($D88="","",IF($F88<>"",$F88,IF(ISNA(MATCH($D88,'Paramètres'!$M:$M,0)),"⚠ Type inconnu",IFERROR(INDEX('Paramètres'!$P:$P,MATCH($D88,'Paramètres'!$M:$M,0))&"","")))) -> Débit | M88: =IF($D88="","",IF(ISNA(MATCH($D88,'Paramètres'!$M:$M,0)),"⚠ Type inconnu",IF($L88="Crédit","",IFERROR(INDEX('Paramètres'!$O:$O,MATCH($D88,'Paramètres'!$M:$M,0))&"","")))) | N88: =IF($D88="","",IFERROR(INDEX('Paramètres'!$Q:$Q,MATCH($D88,'Paramètres'!$M:$M,0))&"","")) -> Comptes Bancaires | O88: =IF($A88="","",IF(OR($J88<>"x",$A88<=FinReleve),1,0)) -> 1 | P88: =IF($D88="","",IF(AND($L88="Crédit",OR(IFERROR(INDEX('Paramètres'!$O:$O,MATCH($D88,'Paramètres'!$M:$M,0))&"","")<>"",ISNUMBER(SEARCH("remboursement",IFERROR(INDEX('Paramètres'!$N:$N,MATCH($D88,'Paramètres'!$M:$M,0))&"",""))))),1,0)) -> 0 | Q88: =IF($K88="","",IF(ISNUMBER(SEARCH("transfert-interne",IFERROR(INDEX('Paramètres'!$N:$N,MATCH($D88,'Paramètres'!$M:$M,0))&"",""))),0,IF($L88="Débit",$K88,IF($P88=1,-$K88,0)))) -> 120 | R88: =IF($K88="","",IF($L88="Crédit",$K88,-$K88)) -> -120 | S88: =IF($C88="","",IFERROR(INDEX('Paramètres'!$H:$H,MATCH($C88,'Paramètres'!$D:$D,0))&"","")) | T88: =IF($K88="","",IF($S88="",0,IF(ISNUMBER(SEARCH("apport-exterieur",IFERROR(INDEX('Paramètres'!$N:$N,MATCH($D88,'Paramètres'!$M:$M,0))&"",""))),0,IF(OR(IFERROR(INDEX('Paramètres'!$I:$I,MATCH($C88,'Paramètres'!$D:$D,0))&"","")="Les deux",IFERROR(INDEX('Paramètres'!$I:$I,MATCH($C88,'Paramètres'!$D:$D,0))&"","")=IF($P88=1,"Débit",$L88)),-IF($P88=1,-$K88,$K88),0)))) -> 0 | U88: =IF($K88="","",IF(ISNUMBER(SEARCH("sortie-epargne",IFERROR(INDEX('Paramètres'!$N:$N,MATCH($D88,'Paramètres'!$M:$M,0))&"",""))),$K88,0)) -> 0 | V88: =IF(AND($A88<>"",$O88=1,$L88="Débit",N($Q88)>0,$A88>=Visualisation!$B$1,$A88<Visualisation!$D$1),MAX($V$1:V87)+1,"")
A89: 45592 | B89: Virement salaire | C89: Banque A - Courant | D89: Salaire | E89: 2968.34 | G89: Salaire | K89: =IF($E89="","",ROUND($E89*IF(ISNA(MATCH($C89,'Paramètres'!$D:$D,0)),1,IF(INDEX('Paramètres'!$J:$J,MATCH($C89,'Paramètres'!$D:$D,0))="",1,INDEX('Paramètres'!$J:$J,MATCH($C89,'Paramètres'!$D:$D,0)))),2)) -> 2968.34 | L89: =IF($D89="","",IF($F89<>"",$F89,IF(ISNA(MATCH($D89,'Paramètres'!$M:$M,0)),"⚠ Type inconnu",IFERROR(INDEX('Paramètres'!$P:$P,MATCH($D89,'Paramètres'!$M:$M,0))&"","")))) -> Crédit | M89: =IF($D89="","",IF(ISNA(MATCH($D89,'Paramètres'!$M:$M,0)),"⚠ Type inconnu",IF($L89="Crédit","",IFERROR(INDEX('Paramètres'!$O:$O,MATCH($D89,'Paramètres'!$M:$M,0))&"","")))) | N89: =IF($D89="","",IFERROR(INDEX('Paramètres'!$Q:$Q,MATCH($D89,'Paramètres'!$M:$M,0))&"","")) | O89: =IF($A89="","",IF(OR($J89<>"x",$A89<=FinReleve),1,0)) -> 1 | P89: =IF($D89="","",IF(AND($L89="Crédit",OR(IFERROR(INDEX('Paramètres'!$O:$O,MATCH($D89,'Paramètres'!$M:$M,0))&"","")<>"",ISNUMBER(SEARCH("remboursement",IFERROR(INDEX('Paramètres'!$N:$N,MATCH($D89,'Paramètres'!$M:$M,0))&"",""))))),1,0)) -> 0 | Q89: =IF($K89="","",IF(ISNUMBER(SEARCH("transfert-interne",IFERROR(INDEX('Paramètres'!$N:$N,MATCH($D89,'Paramètres'!$M:$M,0))&"",""))),0,IF($L89="Débit",$K89,IF($P89=1,-$K89,0)))) -> 0 | R89: =IF($K89="","",IF($L89="Crédit",$K89,-$K89)) -> 2968.34 | S89: =IF($C89="","",IFERROR(INDEX('Paramètres'!$H:$H,MATCH($C89,'Paramètres'!$D:$D,0))&"","")) | T89: =IF($K89="","",IF($S89="",0,IF(ISNUMBER(SEARCH("apport-exterieur",IFERROR(INDEX('Paramètres'!$N:$N,MATCH($D89,'Paramètres'!$M:$M,0))&"",""))),0,IF(OR(IFERROR(INDEX('Paramètres'!$I:$I,MATCH($C89,'Paramètres'!$D:$D,0))&"","")="Les deux",IFERROR(INDEX('Paramètres'!$I:$I,MATCH($C89,'Paramètres'!$D:$D,0))&"","")=IF($P89=1,"Débit",$L89)),-IF($P89=1,-$K89,$K89),0)))) -> 0 | U89: =IF($K89="","",IF(ISNUMBER(SEARCH("sortie-epargne",IFERROR(INDEX('Paramètres'!$N:$N,MATCH($D89,'Paramètres'!$M:$M,0))&"",""))),$K89,0)) -> 0 | V89: =IF(AND($A89<>"",$O89=1,$L89="Débit",N($Q89)>0,$A89>=Visualisation!$B$1,$A89<Visualisation!$D$1),MAX($V$1:V88)+1,"")
A90: 45592 | B90: Achat carte | C90: Banque B - Compte joint | D90: courses | E90: 54.88 | G90: Primeur | I90: Villebourg | K90: =IF($E90="","",ROUND($E90*IF(ISNA(MATCH($C90,'Paramètres'!$D:$D,0)),1,IF(INDEX('Paramètres'!$J:$J,MATCH($C90,'Paramètres'!$D:$D,0))="",1,INDEX('Paramètres'!$J:$J,MATCH($C90,'Paramètres'!$D:$D,0)))),2)) -> 27.44 | L90: =IF($D90="","",IF($F90<>"",$F90,IF(ISNA(MATCH($D90,'Paramètres'!$M:$M,0)),"⚠ Type inconnu",IFERROR(INDEX('Paramètres'!$P:$P,MATCH($D90,'Paramètres'!$M:$M,0))&"","")))) -> Débit | M90: =IF($D90="","",IF(ISNA(MATCH($D90,'Paramètres'!$M:$M,0)),"⚠ Type inconnu",IF($L90="Crédit","",IFERROR(INDEX('Paramètres'!$O:$O,MATCH($D90,'Paramètres'!$M:$M,0))&"","")))) -> Dépense Courante | N90: =IF($D90="","",IFERROR(INDEX('Paramètres'!$Q:$Q,MATCH($D90,'Paramètres'!$M:$M,0))&"","")) -> Alimentation | O90: =IF($A90="","",IF(OR($J90<>"x",$A90<=FinReleve),1,0)) -> 1 | P90: =IF($D90="","",IF(AND($L90="Crédit",OR(IFERROR(INDEX('Paramètres'!$O:$O,MATCH($D90,'Paramètres'!$M:$M,0))&"","")<>"",ISNUMBER(SEARCH("remboursement",IFERROR(INDEX('Paramètres'!$N:$N,MATCH($D90,'Paramètres'!$M:$M,0))&"",""))))),1,0)) -> 0 | Q90: =IF($K90="","",IF(ISNUMBER(SEARCH("transfert-interne",IFERROR(INDEX('Paramètres'!$N:$N,MATCH($D90,'Paramètres'!$M:$M,0))&"",""))),0,IF($L90="Débit",$K90,IF($P90=1,-$K90,0)))) -> 27.44 | R90: =IF($K90="","",IF($L90="Crédit",$K90,-$K90)) -> -27.44 | S90: =IF($C90="","",IFERROR(INDEX('Paramètres'!$H:$H,MATCH($C90,'Paramètres'!$D:$D,0))&"","")) -> Banque A - Courant | T90: =IF($K90="","",IF($S90="",0,IF(ISNUMBER(SEARCH("apport-exterieur",IFERROR(INDEX('Paramètres'!$N:$N,MATCH($D90,'Paramètres'!$M:$M,0))&"",""))),0,IF(OR(IFERROR(INDEX('Paramètres'!$I:$I,MATCH($C90,'Paramètres'!$D:$D,0))&"","")="Les deux",IFERROR(INDEX('Paramètres'!$I:$I,MATCH($C90,'Paramètres'!$D:$D,0))&"","")=IF($P90=1,"Débit",$L90)),-IF($P90=1,-$K90,$K90),0)))) -> 0 | U90: =IF($K90="","",IF(ISNUMBER(SEARCH("sortie-epargne",IFERROR(INDEX('Paramètres'!$N:$N,MATCH($D90,'Paramètres'!$M:$M,0))&"",""))),$K90,0)) -> 0 | V90: =IF(AND($A90<>"",$O90=1,$L90="Débit",N($Q90)>0,$A90>=Visualisation!$B$1,$A90<Visualisation!$D$1),MAX($V$1:V89)+1,"")
A91: 45592 | B91: Restaurant | C91: Appli partagée - Part commune | D91: Restaurant | E91: 57.4 | G91: Cadeau | H91: Anniversaire | K91: =IF($E91="","",ROUND($E91*IF(ISNA(MATCH($C91,'Paramètres'!$D:$D,0)),1,IF(INDEX('Paramètres'!$J:$J,MATCH($C91,'Paramètres'!$D:$D,0))="",1,INDEX('Paramètres'!$J:$J,MATCH($C91,'Paramètres'!$D:$D,0)))),2)) -> 28.7 | L91: =IF($D91="","",IF($F91<>"",$F91,IF(ISNA(MATCH($D91,'Paramètres'!$M:$M,0)),"⚠ Type inconnu",IFERROR(INDEX('Paramètres'!$P:$P,MATCH($D91,'Paramètres'!$M:$M,0))&"","")))) -> Débit | M91: =IF($D91="","",IF(ISNA(MATCH($D91,'Paramètres'!$M:$M,0)),"⚠ Type inconnu",IF($L91="Crédit","",IFERROR(INDEX('Paramètres'!$O:$O,MATCH($D91,'Paramètres'!$M:$M,0))&"","")))) -> Dépense Occasionnelle | N91: =IF($D91="","",IFERROR(INDEX('Paramètres'!$Q:$Q,MATCH($D91,'Paramètres'!$M:$M,0))&"","")) -> Alimentation | O91: =IF($A91="","",IF(OR($J91<>"x",$A91<=FinReleve),1,0)) -> 1 | P91: =IF($D91="","",IF(AND($L91="Crédit",OR(IFERROR(INDEX('Paramètres'!$O:$O,MATCH($D91,'Paramètres'!$M:$M,0))&"","")<>"",ISNUMBER(SEARCH("remboursement",IFERROR(INDEX('Paramètres'!$N:$N,MATCH($D91,'Paramètres'!$M:$M,0))&"",""))))),1,0)) -> 0 | Q91: =IF($K91="","",IF(ISNUMBER(SEARCH("transfert-interne",IFERROR(INDEX('Paramètres'!$N:$N,MATCH($D91,'Paramètres'!$M:$M,0))&"",""))),0,IF($L91="Débit",$K91,IF($P91=1,-$K91,0)))) -> 28.7 | R91: =IF($K91="","",IF($L91="Crédit",$K91,-$K91)) -> -28.7 | S91: =IF($C91="","",IFERROR(INDEX('Paramètres'!$H:$H,MATCH($C91,'Paramètres'!$D:$D,0))&"","")) -> Banque A - Courant | T91: =IF($K91="","",IF($S91="",0,IF(ISNUMBER(SEARCH("apport-exterieur",IFERROR(INDEX('Paramètres'!$N:$N,MATCH($D91,'Paramètres'!$M:$M,0))&"",""))),0,IF(OR(IFERROR(INDEX('Paramètres'!$I:$I,MATCH($C91,'Paramètres'!$D:$D,0))&"","")="Les deux",IFERROR(INDEX('Paramètres'!$I:$I,MATCH($C91,'Paramètres'!$D:$D,0))&"","")=IF($P91=1,"Débit",$L91)),-IF($P91=1,-$K91,$K91),0)))) -> -28.7 | U91: =IF($K91="","",IF(ISNUMBER(SEARCH("sortie-epargne",IFERROR(INDEX('Paramètres'!$N:$N,MATCH($D91,'Paramètres'!$M:$M,0))&"",""))),$K91,0)) -> 0 | V91: =IF(AND($A91<>"",$O91=1,$L91="Débit",N($Q91)>0,$A91>=Visualisation!$B$1,$A91<Visualisation!$D$1),MAX($V$1:V90)+1,"")
A92: 45593 | B92: Frais Bancaires | C92: Banque A - Courant | D92: Frais Bancaires | E92: 3 | K92: =IF($E92="","",ROUND($E92*IF(ISNA(MATCH($C92,'Paramètres'!$D:$D,0)),1,IF(INDEX('Paramètres'!$J:$J,MATCH($C92,'Paramètres'!$D:$D,0))="",1,INDEX('Paramètres'!$J:$J,MATCH($C92,'Paramètres'!$D:$D,0)))),2)) -> 3 | L92: =IF($D92="","",IF($F92<>"",$F92,IF(ISNA(MATCH($D92,'Paramètres'!$M:$M,0)),"⚠ Type inconnu",IFERROR(INDEX('Paramètres'!$P:$P,MATCH($D92,'Paramètres'!$M:$M,0))&"","")))) -> Débit | M92: =IF($D92="","",IF(ISNA(MATCH($D92,'Paramètres'!$M:$M,0)),"⚠ Type inconnu",IF($L92="Crédit","",IFERROR(INDEX('Paramètres'!$O:$O,MATCH($D92,'Paramètres'!$M:$M,0))&"","")))) -> Dépense Fixe | N92: =IF($D92="","",IFERROR(INDEX('Paramètres'!$Q:$Q,MATCH($D92,'Paramètres'!$M:$M,0))&"","")) -> Banque | O92: =IF($A92="","",IF(OR($J92<>"x",$A92<=FinReleve),1,0)) -> 1 | P92: =IF($D92="","",IF(AND($L92="Crédit",OR(IFERROR(INDEX('Paramètres'!$O:$O,MATCH($D92,'Paramètres'!$M:$M,0))&"","")<>"",ISNUMBER(SEARCH("remboursement",IFERROR(INDEX('Paramètres'!$N:$N,MATCH($D92,'Paramètres'!$M:$M,0))&"",""))))),1,0)) -> 0 | Q92: =IF($K92="","",IF(ISNUMBER(SEARCH("transfert-interne",IFERROR(INDEX('Paramètres'!$N:$N,MATCH($D92,'Paramètres'!$M:$M,0))&"",""))),0,IF($L92="Débit",$K92,IF($P92=1,-$K92,0)))) -> 3 | R92: =IF($K92="","",IF($L92="Crédit",$K92,-$K92)) -> -3 | S92: =IF($C92="","",IFERROR(INDEX('Paramètres'!$H:$H,MATCH($C92,'Paramètres'!$D:$D,0))&"","")) | T92: =IF($K92="","",IF($S92="",0,IF(ISNUMBER(SEARCH("apport-exterieur",IFERROR(INDEX('Paramètres'!$N:$N,MATCH($D92,'Paramètres'!$M:$M,0))&"",""))),0,IF(OR(IFERROR(INDEX('Paramètres'!$I:$I,MATCH($C92,'Paramètres'!$D:$D,0))&"","")="Les deux",IFERROR(INDEX('Paramètres'!$I:$I,MATCH($C92,'Paramètres'!$D:$D,0))&"","")=IF($P92=1,"Débit",$L92)),-IF($P92=1,-$K92,$K92),0)))) -> 0 | U92: =IF($K92="","",IF(ISNUMBER(SEARCH("sortie-epargne",IFERROR(INDEX('Paramètres'!$N:$N,MATCH($D92,'Paramètres'!$M:$M,0))&"",""))),$K92,0)) -> 0 | V92: =IF(AND($A92<>"",$O92=1,$L92="Débit",N($Q92)>0,$A92>=Visualisation!$B$1,$A92<Visualisation!$D$1),MAX($V$1:V91)+1,"")
A93: 45597 | B93: Achat carte | C93: Banque A - Part commune | D93: courses | E93: 92.36 | G93: Boulangerie | I93: Rocheville | K93: =IF($E93="","",ROUND($E93*IF(ISNA(MATCH($C93,'Paramètres'!$D:$D,0)),1,IF(INDEX('Paramètres'!$J:$J,MATCH($C93,'Paramètres'!$D:$D,0))="",1,INDEX('Paramètres'!$J:$J,MATCH($C93,'Paramètres'!$D:$D,0)))),2)) -> 46.18 | L93: =IF($D93="","",IF($F93<>"",$F93,IF(ISNA(MATCH($D93,'Paramètres'!$M:$M,0)),"⚠ Type inconnu",IFERROR(INDEX('Paramètres'!$P:$P,MATCH($D93,'Paramètres'!$M:$M,0))&"","")))) -> Débit | M93: =IF($D93="","",IF(ISNA(MATCH($D93,'Paramètres'!$M:$M,0)),"⚠ Type inconnu",IF($L93="Crédit","",IFERROR(INDEX('Paramètres'!$O:$O,MATCH($D93,'Paramètres'!$M:$M,0))&"","")))) -> Dépense Courante | N93: =IF($D93="","",IFERROR(INDEX('Paramètres'!$Q:$Q,MATCH($D93,'Paramètres'!$M:$M,0))&"","")) -> Alimentation | O93: =IF($A93="","",IF(OR($J93<>"x",$A93<=FinReleve),1,0)) -> 1 | P93: =IF($D93="","",IF(AND($L93="Crédit",OR(IFERROR(INDEX('Paramètres'!$O:$O,MATCH($D93,'Paramètres'!$M:$M,0))&"","")<>"",ISNUMBER(SEARCH("remboursement",IFERROR(INDEX('Paramètres'!$N:$N,MATCH($D93,'Paramètres'!$M:$M,0))&"",""))))),1,0)) -> 0 | Q93: =IF($K93="","",IF(ISNUMBER(SEARCH("transfert-interne",IFERROR(INDEX('Paramètres'!$N:$N,MATCH($D93,'Paramètres'!$M:$M,0))&"",""))),0,IF($L93="Débit",$K93,IF($P93=1,-$K93,0)))) -> 46.18 | R93: =IF($K93="","",IF($L93="Crédit",$K93,-$K93)) -> -46.18 | S93: =IF($C93="","",IFERROR(INDEX('Paramètres'!$H:$H,MATCH($C93,'Paramètres'!$D:$D,0))&"","")) -> Banque A - Courant | T93: =IF($K93="","",IF($S93="",0,IF(ISNUMBER(SEARCH("apport-exterieur",IFERROR(INDEX('Paramètres'!$N:$N,MATCH($D93,'Paramètres'!$M:$M,0))&"",""))),0,IF(OR(IFERROR(INDEX('Paramètres'!$I:$I,MATCH($C93,'Paramètres'!$D:$D,0))&"","")="Les deux",IFERROR(INDEX('Paramètres'!$I:$I,MATCH($C93,'Paramètres'!$D:$D,0))&"","")=IF($P93=1,"Débit",$L93)),-IF($P93=1,-$K93,$K93),0)))) -> -46.18 | U93: =IF($K93="","",IF(ISNUMBER(SEARCH("sortie-epargne",IFERROR(INDEX('Paramètres'!$N:$N,MATCH($D93,'Paramètres'!$M:$M,0))&"",""))),$K93,0)) -> 0 | V93: =IF(AND($A93<>"",$O93=1,$L93="Débit",N($Q93)>0,$A93>=Visualisation!$B$1,$A93<Visualisation!$D$1),MAX($V$1:V92)+1,"")
